Workbook

Sheet Final
A6: Month | B6: Hours | C6: Max_Capacity | D6: X_Stockpile_t | E6: X_Colombian_t | F6: X_Russian_t | G6: X_Scottish_t | H6: X_Wood_t | I6: Thermal_Input_GJ | J6: Total_MWh | K6: Wood_Chips_MWh | L6: Price_per MWh | M6: Revenue | N6: ROC_Revenue | O6: Grid_Charge | P6: Fuel_Cost | Q6: CO2_Cost | R6: Profit | S6: Wood_Thermal_GJ | T6: SO2_tonnes | U6: Biomass_share | V6: Thermal_Input_GJ*0.1 | W6: Coal fule | Y6: Wood_Chips_Constraint
A7: June - Weekday Peak | B7: 264 | C7: =B7*1000 -> 264000 | D7: 94687.552 | E7: 0 | F7: 0 | G7: 0 | H7: 15085.714 | I7: =SUMPRODUCT(D7:H7, N$31:R$31) -> 2715428.6 | J7: =(SUMPRODUCT(D7:H7, N$31:R$31)*0.35)/3.6 -> 264000 | K7: =($R$31*H7*0.35)/3.6 -> 26400 | L7: =VLOOKUP(A7,F29:G49,2,FALSE) -> 36 | M7: =L7*J7 -> 9504000 | N7: =45*($R$31*H7*0.35)/3.6 -> 1188000 | O7: =SUMPRODUCT(D7:H7, N$31:R$31)*0.35*0.65/3.6 -> 171600 | P7: =SUMPRODUCT(D7:H7, N$30:R$30) -> 5142775.4 | Q7: =J7*0.8*0.87*15 -> 2756160 | R7: =IFERROR(M7+N7-O7-P7-Q7,0) -> 2621464.6 | S7: =H7*$R$31 -> 271542.86 | T7: =SUMPRODUCT(D7:H7, N$32:R$32)*0.01 -> 1308.1968 | U7: =IFERROR(S7/I7,0) -> 0.1 | V7: =0.1*I7 -> 271542.86 | W7: =SUMPRODUCT($N$31:$Q$31,D7:G7) -> 2443885.7 | Y7: =K7-0.1*J7 -> 0
A8: June - Weekday Off-peak | B8: 264 | C8: =B8*1000 -> 264000 | D8: 0 | E8: 0 | F8: 0 | G8: 0 | H8: 0 | I8: =SUMPRODUCT(D8:H8, N$31:R$31) -> 0 | J8: =(SUMPRODUCT(D8:H8, N$31:R$31)*0.35)/3.6 -> 0 | K8: =($R$31*H8*0.35)/3.6 -> 0 | L8: =VLOOKUP(A8,F30:G51,2,FALSE) -> 27 | M8: =L8*J8 -> 0 | N8: =45*($R$31*H8*0.35)/3.6 -> 0 | O8: =SUMPRODUCT(D8:H8, N$31:R$31)*0.35*0.65/3.6 -> 0 | P8: =SUMPRODUCT(D8:H8, N$30:R$30) -> 0 | Q8: =J8*0.8*0.87*15 -> 0 | R8: =IFERROR(M8+N8-O8-P8-Q8,0) -> 0 | S8: =H8*$R$31 -> 0 | T8: =SUMPRODUCT(D8:H8, N$32:R$32)*0.01 -> 0 | U8: =IFERROR(S8/I8,0) -> 0 | V8: =0.1*I8 -> 0 | W8: =SUMPRODUCT($N$31:$Q$31,D8:G8) -> 0 | Y8: =K8-0.1*J8 -> 0
A9: June - Weekend Peak | B9: 96 | C9: =B9*1000 -> 96000 | D9: 34431.837 | E9: 0 | F9: 0 | G9: 0 | H9: 5485.7143 | I9: =SUMPRODUCT(D9:H9, N$31:R$31) -> 987428.57 | J9: =(SUMPRODUCT(D9:H9, N$31:R$31)*0.35)/3.6 -> 96000 | K9: =($R$31*H9*0.35)/3.6 -> 9600 | L9: =VLOOKUP(A9,F31:G52,2,FALSE) -> 33.5 | M9: =L9*J9 -> 3216000 | N9: =45*($R$31*H9*0.35)/3.6 -> 432000 | O9: =SUMPRODUCT(D9:H9, N$31:R$31)*0.35*0.65/3.6 -> 62400 | P9: =SUMPRODUCT(D9:H9, N$30:R$30) -> 1870100.1 | Q9: =J9*0.8*0.87*15 -> 1002240 | R9: =IFERROR(M9+N9-O9-P9-Q9,0) -> 713259.87 | S9: =H9*$R$31 -> 98742.857 | T9: =SUMPRODUCT(D9:H9, N$32:R$32)*0.01 -> 475.70792 | U9: =IFERROR(S9/I9,0) -> 0.1 | V9: =0.1*I9 -> 98742.857 | W9: =SUMPRODUCT($N$31:$Q$31,D9:G9) -> 888685.71 | Y9: =K9-0.1*J9 -> 0
A10: June - Weekend Off-peak | B10: 96 | C10: =B10*1000 -> 96000 | D10: 0 | E10: 0 | F10: 0 | G10: 0 | H10: 0 | I10: =SUMPRODUCT(D10:H10, N$31:R$31) -> 0 | J10: =(SUMPRODUCT(D10:H10, N$31:R$31)*0.35)/3.6 -> 0 | K10: =($R$31*H10*0.35)/3.6 -> 0 | L10: =VLOOKUP(A10,F32:G53,2,FALSE) -> 26.2 | M10: =L10*J10 -> 0 | N10: =45*($R$31*H10*0.35)/3.6 -> 0 | O10: =SUMPRODUCT(D10:H10, N$31:R$31)*0.35*0.65/3.6 -> 0 | P10: =SUMPRODUCT(D10:H10, N$30:R$30) -> 0 | Q10: =J10*0.8*0.87*15 -> 0 | R10: =IFERROR(M10+N10-O10-P10-Q10,0) -> 0 | S10: =H10*$R$31 -> 0 | T10: =SUMPRODUCT(D10:H10, N$32:R$32)*0.01 -> 0 | U10: =IFERROR(S10/I10,0) -> 0 | V10: =0.1*I10 -> 0 | W10: =SUMPRODUCT($N$31:$Q$31,D10:G10) -> 0 | Y10: =K10-0.1*J10 -> 0
A11: July - Weekday Peak | B11: 264 | C11: =B11*1000 -> 264000 | D11: 94687.552 | E11: 0 | F11: 0 | G11: 0 | H11: 15085.714 | I11: =SUMPRODUCT(D11:H11, N$31:R$31) -> 2715428.6 | J11: =(SUMPRODUCT(D11:H11, N$31:R$31)*0.35)/3.6 -> 264000 | K11: =($R$31*H11*0.35)/3.6 -> 26400 | L11: =VLOOKUP(A11,F33:G54,2,FALSE) -> 36.35 | M11: =L11*J11 -> 9596400 | N11: =45*($R$31*H11*0.35)/3.6 -> 1188000 | O11: =SUMPRODUCT(D11:H11, N$31:R$31)*0.35*0.65/3.6 -> 171600 | P11: =SUMPRODUCT(D11:H11, N$30:R$30) -> 5142775.4 | Q11: =J11*0.8*0.87*15 -> 2756160 | R11: =IFERROR(M11+N11-O11-P11-Q11,0) -> 2713864.6 | S11: =H11*$R$31 -> 271542.86 | T11: =SUMPRODUCT(D11:H11, N$32:R$32)*0.01 -> 1308.1968 | U11: =IFERROR(S11/I11,0) -> 0.1 | V11: =0.1*I11 -> 271542.86 | W11: =SUMPRODUCT($N$31:$Q$31,D11:G11) -> 2443885.7 | Y11: =K11-0.1*J11 -> 0
A12: July - Weekday Off-peak | B12: 264 | C12: =B12*1000 -> 264000 | D12: 0 | E12: 0 | F12: 0 | G12: 0 | H12: 0 | I12: =SUMPRODUCT(D12:H12, N$31:R$31) -> 0 | J12: =(SUMPRODUCT(D12:H12, N$31:R$31)*0.35)/3.6 -> 0 | K12: =($R$31*H12*0.35)/3.6 -> 0 | L12: =VLOOKUP(A12,F34:G55,2,FALSE) -> 27 | M12: =L12*J12 -> 0 | N12: =45*($R$31*H12*0.35)/3.6 -> 0 | O12: =SUMPRODUCT(D12:H12, N$31:R$31)*0.35*0.65/3.6 -> 0 | P12: =SUMPRODUCT(D12:H12, N$30:R$30) -> 0 | Q12: =J12*0.8*0.87*15 -> 0 | R12: =IFERROR(M12+N12-O12-P12-Q12,0) -> 0 | S12: =H12*$R$31 -> 0 | T12: =SUMPRODUCT(D12:H12, N$32:R$32)*0.01 -> 0 | U12: =IFERROR(S12/I12,0) -> 0 | V12: =0.1*I12 -> 0 | W12: =SUMPRODUCT($N$31:$Q$31,D12:G12) -> 0 | Y12: =K12-0.1*J12 -> 0
A13: July - Weekend Peak | B13: 108 | C13: =B13*1000 -> 108000 | D13: 38735.817 | E13: 0 | F13: 0 | G13: 0 | H13: 6171.4286 | I13: =SUMPRODUCT(D13:H13, N$31:R$31) -> 1110857.1 | J13: =(SUMPRODUCT(D13:H13, N$31:R$31)*0.35)/3.6 -> 108000 | K13: =($R$31*H13*0.35)/3.6 -> 10800 | L13: =VLOOKUP(A13,F35:G56,2,FALSE) -> 34.3 | M13: =L13*J13 -> 3704400 | N13: =45*($R$31*H13*0.35)/3.6 -> 486000 | O13: =SUMPRODUCT(D13:H13, N$31:R$31)*0.35*0.65/3.6 -> 70200 | P13: =SUMPRODUCT(D13:H13, N$30:R$30) -> 2103862.6 | Q13: =J13*0.8*0.87*15 -> 1127520 | R13: =IFERROR(M13+N13-O13-P13-Q13,0) -> 888817.36 | S13: =H13*$R$31 -> 111085.71 | T13: =SUMPRODUCT(D13:H13, N$32:R$32)*0.01 -> 535.17141 | U13: =IFERROR(S13/I13,0) -> 0.1 | V13: =0.1*I13 -> 111085.71 | W13: =SUMPRODUCT($N$31:$Q$31,D13:G13) -> 999771.43 | Y13: =K13-0.1*J13 -> 0
A14: July - Weekend Off-peak | B14: 108 | C14: =B14*1000 -> 108000 | D14: 0 | E14: 0 | F14: 0 | G14: 0 | H14: 0 | I14: =SUMPRODUCT(D14:H14, N$31:R$31) -> 0 | J14: =(SUMPRODUCT(D14:H14, N$31:R$31)*0.35)/3.6 -> 0 | K14: =($R$31*H14*0.35)/3.6 -> 0 | L14: =VLOOKUP(A14,F36:G57,2,FALSE) -> 26.3 | M14: =L14*J14 -> 0 | N14: =45*($R$31*H14*0.35)/3.6 -> 0 | O14: =SUMPRODUCT(D14:H14, N$31:R$31)*0.35*0.65/3.6 -> 0 | P14: =SUMPRODUCT(D14:H14, N$30:R$30) -> 0 | Q14: =J14*0.8*0.87*15 -> 0 | R14: =IFERROR(M14+N14-O14-P14-Q14,0) -> 0 | S14: =H14*$R$31 -> 0 | T14: =SUMPRODUCT(D14:H14, N$32:R$32)*0.01 -> 0 | U14: =IFERROR(S14/I14,0) -> 0 | V14: =0.1*I14 -> 0 | W14: =SUMPRODUCT($N$31:$Q$31,D14:G14) -> 0 | Y14: =K14-0.1*J14 -> 0
A15: August - Weekday Peak | B15: 264 | C15: =B15*1000 -> 264000 | D15: 94687.552 | E15: 0 | F15: 0 | G15: 0 | H15: 15085.714 | I15: =SUMPRODUCT(D15:H15, N$31:R$31) -> 2715428.6 | J15: =(SUMPRODUCT(D15:H15, N$31:R$31)*0.35)/3.6 -> 264000 | K15: =($R$31*H15*0.35)/3.6 -> 26400 | L15: =VLOOKUP(A15,F37:G58,2,FALSE) -> 37.65 | M15: =L15*J15 -> 9939600 | N15: =45*($R$31*H15*0.35)/3.6 -> 1188000 | O15: =SUMPRODUCT(D15:H15, N$31:R$31)*0.35*0.65/3.6 -> 171600 | P15: =SUMPRODUCT(D15:H15, N$30:R$30) -> 5142775.4 | Q15: =J15*0.8*0.87*15 -> 2756160 | R15: =IFERROR(M15+N15-O15-P15-Q15,0) -> 3057064.6 | S15: =H15*$R$31 -> 271542.86 | T15: =SUMPRODUCT(D15:H15, N$32:R$32)*0.01 -> 1308.1968 | U15: =IFERROR(S15/I15,0) -> 0.1 | V15: =0.1*I15 -> 271542.86 | W15: =SUMPRODUCT($N$31:$Q$31,D15:G15) -> 2443885.7 | Y15: =K15-0.1*J15 -> 0
A16: August - Weekday Off-peak | B16: 264 | C16: =B16*1000 -> 264000 | D16: 94687.552 | E16: 0 | F16: 0 | G16: 0 | H16: 15085.714 | I16: =SUMPRODUCT(D16:H16, N$31:R$31) -> 2715428.6 | J16: =(SUMPRODUCT(D16:H16, N$31:R$31)*0.35)/3.6 -> 264000 | K16: =($R$31*H16*0.35)/3.6 -> 26400 | L16: =VLOOKUP(A16,F38:G59,2,FALSE) -> 28.2 | M16: =L16*J16 -> 7444800 | N16: =45*($R$31*H16*0.35)/3.6 -> 1188000 | O16: =SUMPRODUCT(D16:H16, N$31:R$31)*0.35*0.65/3.6 -> 171600 | P16: =SUMPRODUCT(D16:H16, N$30:R$30) -> 5142775.4 | Q16: =J16*0.8*0.87*15 -> 2756160 | R16: =IFERROR(M16+N16-O16-P16-Q16,0) -> 562264.65 | S16: =H16*$R$31 -> 271542.86 | T16: =SUMPRODUCT(D16:H16, N$32:R$32)*0.01 -> 1308.1968 | U16: =IFERROR(S16/I16,0) -> 0.1 | V16: =0.1*I16 -> 271542.86 | W16: =SUMPRODUCT($N$31:$Q$31,D16:G16) -> 2443885.7 | Y16: =K16-0.1*J16 -> 0
A17: August - Weekend Peak | B17: 108 | C17: =B17*1000 -> 108000 | D17: 38735.817 | E17: 0 | F17: 0 | G17: 0 | H17: 6171.4286 | I17: =SUMPRODUCT(D17:H17, N$31:R$31) -> 1110857.1 | J17: =(SUMPRODUCT(D17:H17, N$31:R$31)*0.35)/3.6 -> 108000 | K17: =($R$31*H17*0.35)/3.6 -> 10800 | L17: =VLOOKUP(A17,F39:G60,2,FALSE) -> 35.65 | M17: =L17*J17 -> 3850200 | N17: =45*($R$31*H17*0.35)/3.6 -> 486000 | O17: =SUMPRODUCT(D17:H17, N$31:R$31)*0.35*0.65/3.6 -> 70200 | P17: =SUMPRODUCT(D17:H17, N$30:R$30) -> 2103862.6 | Q17: =J17*0.8*0.87*15 -> 1127520 | R17: =IFERROR(M17+N17-O17-P17-Q17,0) -> 1034617.4 | S17: =H17*$R$31 -> 111085.71 | T17: =SUMPRODUCT(D17:H17, N$32:R$32)*0.01 -> 535.17141 | U17: =IFERROR(S17/I17,0) -> 0.1 | V17: =0.1*I17 -> 111085.71 | W17: =SUMPRODUCT($N$31:$Q$31,D17:G17) -> 999771.43 | Y17: =K17-0.1*J17 -> 0
A18: August - Weekend Off-peak | B18: 108 | C18: =B18*1000 -> 108000 | D18: 0 | E18: 0 | F18: 0 | G18: 0 | H18: 0 | I18: =SUMPRODUCT(D18:H18, N$31:R$31) -> 0 | J18: =(SUMPRODUCT(D18:H18, N$31:R$31)*0.35)/3.6 -> 0 | K18: =($R$31*H18*0.35)/3.6 -> 0 | L18: =VLOOKUP(A18,F40:G61,2,FALSE) -> 27.5 | M18: =L18*J18 -> 0 | N18: =45*($R$31*H18*0.35)/3.6 -> 0 | O18: =SUMPRODUCT(D18:H18, N$31:R$31)*0.35*0.65/3.6 -> 0 | P18: =SUMPRODUCT(D18:H18, N$30:R$30) -> 0 | Q18: =J18*0.8*0.87*15 -> 0 | R18: =IFERROR(M18+N18-O18-P18-Q18,0) -> 0 | S18: =H18*$R$31 -> 0 | T18: =SUMPRODUCT(D18:H18, N$32:R$32)*0.01 -> 0 | U18: =IFERROR(S18/I18,0) -> 0 | V18: =0.1*I18 -> 0 | W18: =SUMPRODUCT($N$31:$Q$31,D18:G18) -> 0 | Y18: =K18-0.1*J18 -> 0
A19: September - Weekday Peak | B19: 264 | C19: =B19*1000 -> 264000 | D19: 0 | E19: 0 | F19: 67627.445 | G19: 30038.676 | H19: 15085.714 | I19: =SUMPRODUCT(D19:H19, N$31:R$31) -> 2715428.6 | J19: =(SUMPRODUCT(D19:H19, N$31:R$31)*0.35)/3.6 -> 264000 | K19: =($R$31*H19*0.35)/3.6 -> 26400 | L19: =VLOOKUP(A19,F41:G62,2,FALSE) -> 38.35 | M19: =L19*J19 -> 10124400 | N19: =45*($R$31*H19*0.35)/3.6 -> 1188000 | O19: =SUMPRODUCT(D19:H19, N$31:R$31)*0.35*0.65/3.6 -> 171600 | P19: =SUMPRODUCT(D19:H19, N$30:R$30) -> 5336579.6 | Q19: =J19*0.8*0.87*15 -> 2756160 | R19: =IFERROR(M19+N19-O19-P19-Q19,0) -> 3048060.4 | S19: =H19*$R$31 -> 271542.86 | T19: =SUMPRODUCT(D19:H19, N$32:R$32)*0.01 -> 754.86986 | U19: =IFERROR(S19/I19,0) -> 0.1 | V19: =0.1*I19 -> 271542.86 | W19: =SUMPRODUCT($N$31:$Q$31,D19:G19) -> 2443885.7 | Y19: =K19-0.1*J19 -> 0
... A26: October - Weekend Off-peak | B26: 120 | C26: =B26*1000 -> 120000 | D26: 0 | E26: 0 | F26: 45341.108 | G26: 0 | H26: 6857.1429 | I26: =SUMPRODUCT(D26:H26, N$31:R$31) -> 1234285.7 | J26: =(SUMPRODUCT(D26:H26, N$31:R$31)*0.35)/3.6 -> 120000 | K26: =($R$31*H26*0.35)/3.6 -> 12000 | L26: =VLOOKUP(A26,F48:G69,2,FALSE) -> 30.1 | M26: =L26*J26 -> 3612000 | N26: =45*($R$31*H26*0.35)/3.6 -> 540000 | O26: =SUMPRODUCT(D26:H26, N$31:R$31)*0.35*0.65/3.6 -> 78000 | P26: =SUMPRODUCT(D26:H26, N$30:R$30) -> 2491792 | Q26: =J26*0.8*0.87*15 -> 1252800 | R26: =IFERROR(M26+N26-O26-P26-Q26,0) -> 329408.05 | S26: =H26*$R$31 -> 123428.57 | T26: =SUMPRODUCT(D26:H26, N$32:R$32)*0.01 -> 159.37959 | U26: =IFERROR(S26/I26,0) -> 0.1 | V26: =0.1*I26 -> 123428.57 | W26: =SUMPRODUCT($N$31:$Q$31,D26:G26) -> 1110857.1 | Y26: =K26-0.1*J26 -> 0
A27: Total | C27: =SUM(C7:C26) -> 3672000 | D27: =SUM(D7:D26) -> 490653.68 | E27: =SUM(E7:E26) -> 0 | F27: =SUM(F7:F26) -> 484765.64 | G27: =SUM(G7:G26) -> 30038.676 | H27: =SUM(H7:H26) -> 156342.86 | J27: =SUM(J7:J26) -> 2736000 | K27: =SUM(K7:K26) -> 273600 | L27: =SUM(L7:L26) -> 650.15 | M27: =SUM(M7:M26) -> 95597400 | N27: =SUM(N7:N26) -> 12312000 | O27: =SUM(O7:O26) -> 1778400 | P27: =SUM(P7:P26) -> 54909992 | Q27: =SUM(Q7:Q26) -> 28563840 | ... T27: =SUM(T7:T26) -> 9000 | V27: =SUM(V7:V26) -> 2814171.4 | W27: =SUMPRODUCT($N$31:$Q$31,D27:G27) -> 25327543
F29: Period | G29: Electricity_Forward_Price | J29: Scalars | K29: Value | M29: Fuel | N29: Stockpile coal | O29: Colombian coal | P29: Russian coal | Q29: Scottish coal | R29: Wood chips
F30: June - Weekday Peak | G30: 36 | J30: Efficiency | K30: 0.35 | M30: Price_per_t | N30: 42.56 | O30: 43.93 | P30: 43.8 | Q30: 42 | R30: 73.77
F31: June - Weekday Off-peak | G31: 27 | J31: Plant_Capacity_MW | K31: 1000 | M31: CV_GJ_per_t | N31: 25.81 | O31: 25.12 | P31: 24.5 | Q31: 26.2 | R31: 18
F32: June - Weekend Peak | G32: 33.5 | J32: Grid_Charge_per_MWh | K32: 0.65 | M32: SO2_percent | N32: 1.38 | O32: 0.7 | P32: 0.35 | Q32: 1.72 | R32: 0.01
F33: June - Weekend Off-peak | G33: 26.2 | J33: CO2_Intensity_t_per_MWh | K33: 0.8
F34: July - Weekday Peak | G34: 36.35 | J34: CO2_Cost_EUR_per_t | K34: 15
F35: July - Weekday Off-peak | G35: 27 | J35: FX_EUR_per_GBP | K35: 0.87
F36: July - Weekend Peak | G36: 34.3 | J36: ROC_per_MWh | K36: 45
F37: July - Weekend Off-peak | G37: 26.3 | J37: Sulphur_Allowance_t | K37: 9000
F38: August - Weekday Peak | G38: 37.65 | J38: Stockpile_Tonnes | K38: 600000
F39: August - Weekday Off-peak | G39: 28.2 | J39: Biomass_Share_Max | K39: 0.1
F40: August - Weekend Peak | G40: 35.65 | J40: Hours_Peak_per_Day | K40: 12
F41: August - Weekend Off-peak | G41: 27.5 | J41: Hours_Offpeak_per_Day | K41: 12
F42: September - Weekday Peak | G42: 38.35 | J42: P_Colombian_t | K42: 0
F43: September - Weekday Off-peak | G43: 28.5 | J43: P_Russian_t | K43: 0
F44: September - Weekend Peak | G44: 35.8 | J44: P_Scottish_t | K44: 0
F45: September - Weekend Off-peak | G45: 27.65
F46: October - Weekday Peak | G46: 43.7
F47: October - Weekday Off-peak | G47: 31.7
F48: October - Weekend Peak | G48: 38.7
F49: October - Weekend Off-peak | G49: 30.1

Sheet Sensitivity Report 1
A1: Microsoft Excel 16.102 Sensitivity Report
A2: Worksheet: [GROUP_I_IC.xlsx]Final
A3: Report Created: 11/13/25 22:52:19
A6: Variable Cells
D7: Final | E7: Reduced | F7: Objective | G7: Allowable | H7: Allowable
B8: Cell | C8: Name | D8: Value | E8: Cost | F8: Coefficient | G8: Increase | H8: Decrease
B9: $D$7 | C9: June - Weekday Peak X_Stockpile_t | D9: 94687.552 | E9: 0 | F9: 19.946801 | G9: 54.611679 | H9: 0.054620564
B10: $E$7 | C10: June - Weekday Peak X_Colombian_t | D10: 0 | E10: -0.19517996 | F10: 16.905756 | G10: 0.19517996 | H10: 1e+30
B11: $F$7 | C11: June - Weekday Peak X_Russian_t | D11: 0 | E11: 0.051848269 | F11: 15.534236 | G11: 0.051848269 | H11: 1e+30
B12: $G$7 | C12: June - Weekday Peak X_Scottish_t | D12: 0 | E12: 0.055445904 | F12: 21.451306 | G12: 0.055445904 | H12: 1e+30
B13: $H$7 | C13: June - Weekday Peak X_Wood_t | D13: 15085.714 | E13: 0 | F13: 48.5725 | G13: 1e+30 | H13: 38.086409
B14: $D$8 | C14: June - Weekday Off-peak X_Stockpile_t | D14: 0 | E14: -2.3758396 | F14: -2.6369486 | G14: 2.3758396 | H14: 1e+30
B15: $E$8 | C15: June - Weekday Off-peak X_Colombian_t | D15: 0 | E15: -2.5075043 | F15: -5.0742444 | G15: 2.5075043 | H15: 1e+30
B16: $F$8 | C16: June - Weekday Off-peak X_Russian_t | D16: 0 | E16: -2.2034044 | F16: -5.9032639 | G16: 2.2034044 | H16: 1e+30
B17: $G$8 | C17: June - Weekday Off-peak X_Scottish_t | D17: 0 | E17: -2.3562937 | F17: -1.4736944 | G17: 2.3562937 | H17: 1e+30
B18: $H$8 | C18: June - Weekday Off-peak X_Wood_t | D18: 0 | E18: 0 | F18: 32.8225 | G18: 14.569449 | H18: 32.78654
B19: $D$9 | C19: June - Weekend Peak X_Stockpile_t | D19: 34431.837 | E19: 0 | F19: 13.673537 | G19: 54.611679 | H19: 0.054620564
B20: $E$9 | C20: June - Weekend Peak X_Colombian_t | D20: 0 | E20: -0.19517996 | F20: 10.8002 | G20: 0.19517996 | H20: 1e+30
... B108: $H$26 | C108: October - Weekend Off-peak X_Wood_t | D108: 6857.1429 | E108: 0 | F108: 38.2475 | G108: 1e+30 | H108: 38.048317
A110: Constraints
D111: Final | E111: Shadow | F111: Constraint | G111: Allowable | H111: Allowable
B112: Cell | C112: Name | D112: Value | E112: Price | F112: R.H. Side | G112: Increase | H112: Decrease
B113: $D$27 | C113: Total X_Stockpile_t | D113: 490653.68 | E113: 0 | F113: 600000 | G113: 1e+30 | H113: 109346.32
B114: $J$7 | C114: June - Weekday Peak Total_MWh | D114: 264000 | E114: 8.1478695 | F114: 264000 | G114: 81576.393 | H114: 171740.01
B115: $J$8 | C115: June - Weekday Off-peak Total_MWh | D115: 0 | E115: 0 | F115: 264000 | G115: 1e+30 | H115: 264000
B116: $J$9 | C116: June - Weekend Peak Total_MWh | D116: 96000 | E116: 5.6478695 | F116: 96000 | G116: 81576.393 | H116: 96000
B117: $J$10 | C117: June - Weekend Off-peak Total_MWh | D117: 0 | E117: 0 | F117: 96000 | G117: 1e+30 | H117: 96000
B118: $J$11 | C118: July - Weekday Peak Total_MWh | D118: 264000 | E118: 8.4978695 | F118: 264000 | G118: 81576.393 | H118: 171740.01
B119: $J$12 | C119: July - Weekday Off-peak Total_MWh | D119: 0 | E119: 0 | F119: 264000 | G119: 1e+30 | H119: 264000
B120: $J$13 | C120: July - Weekend Peak Total_MWh | D120: 108000 | E120: 6.4478695 | F120: 108000 | G120: 81576.393 | H120: 108000
B121: $J$14 | C121: July - Weekend Off-peak Total_MWh | D121: 0 | E121: 0 | F121: 108000 | G121: 1e+30 | H121: 108000
B122: $J$15 | C122: August - Weekday Peak Total_MWh | D122: 264000 | E122: 9.7978695 | F122: 264000 | G122: 81576.393 | H122: 171740.01
B123: $J$16 | C123: August - Weekday Off-peak Total_MWh | D123: 264000 | E123: 0.34786955 | F123: 264000 | G123: 81576.393 | H123: 171740.01
B124: $J$17 | C124: August - Weekend Peak Total_MWh | D124: 108000 | E124: 7.7978695 | F124: 108000 | G124: 81576.393 | H124: 108000
... B154: $Y$26 | C154: October - Weekend Off-peak Wood_Chips_Constraint | D154: 0 | E154: 21.741895 | F154: 0 | G154: 108000 | H154: 12000

Sheet Answer Report 1
A1: Microsoft Excel 16.102 Answer Report
A2: Worksheet: [GROUP_I_IC.xlsx]Final
A3: Report Created: 11/13/25 22:52:17
A4: Result: Solver found a solution. All constraints and optimality conditions are satisfied.
A5: Solver Engine
B6: Engine: Simplex LP
B7: Solution Time: 38655078.443 Seconds.
B8: Iterations: 39 Subproblems: 0
A9: Solver Options
B10: Max Time Unlimited, Iterations Unlimited, Precision 0.000001
B11: Max Subproblems Unlimited, Max Integer Sols Unlimited, Integer Tolerance 1%, Solve Without Integer Constraints, Assume NonNegative
A14: Objective Cell (Max)
B15: Cell | C15: Name | D15: Original Value | E15: Final Value
B16: $R$27 | C16: Total Profit | D16: 22657168 | E16: 22657168
A19: Variable Cells
B20: Cell | C20: Name | D20: Original Value | E20: Final Value | F20: Integer
B21: $D$7 | C21: June - Weekday Peak X_Stockpile_t | D21: 94687.552 | E21: 94687.552 | F21: Contin
B22: $E$7 | C22: June - Weekday Peak X_Colombian_t | D22: 0 | E22: 0 | F22: Contin
B23: $F$7 | C23: June - Weekday Peak X_Russian_t | D23: 0 | E23: 0 | F23: Contin
B24: $G$7 | C24: June - Weekday Peak X_Scottish_t | D24: 0 | E24: 0 | F24: Contin
B25: $H$7 | C25: June - Weekday Peak X_Wood_t | D25: 15085.714 | E25: 15085.714 | F25: Contin
B26: $D$8 | C26: June - Weekday Off-peak X_Stockpile_t | D26: 0 | E26: 0 | F26: Contin
B27: $E$8 | C27: June - Weekday Off-peak X_Colombian_t | D27: 0 | E27: 0 | F27: Contin
B28: $F$8 | C28: June - Weekday Off-peak X_Russian_t | D28: 0 | E28: 0 | F28: Contin
B29: $G$8 | C29: June - Weekday Off-peak X_Scottish_t | D29: 0 | E29: 0 | F29: Contin
B30: $H$8 | C30: June - Weekday Off-peak X_Wood_t | D30: 0 | E30: 0 | F30: Contin
B31: $D$9 | C31: June - Weekend Peak X_Stockpile_t | D31: 34431.837 | E31: 34431.837 | F31: Contin
B32: $E$9 | C32: June - Weekend Peak X_Colombian_t | D32: 0 | E32: 0 | F32: Contin
... B120: $H$26 | C120: October - Weekend Off-peak X_Wood_t | D120: 6857.1429 | E120: 6857.1429 | F120: Contin
A123: Constraints
B124: Cell | C124: Name | D124: Cell Value | E124: Formula | F124: Status | G124: Slack
B125: $D$27 | C125: Total X_Stockpile_t | D125: 490653.68 | E125: $D$27<=$K$38 | F125: Not Binding | G125: 109346.32
B126: $J$7 | C126: June - Weekday Peak Total_MWh | D126: 264000 | E126: $J$7<=$C$7 | F126: Binding | G126: 0
B127: $J$8 | C127: June - Weekday Off-peak Total_MWh | D127: 0 | E127: $J$8<=$C$8 | F127: Not Binding | G127: 264000
B128: $J$9 | C128: June - Weekend Peak Total_MWh | D128: 96000 | E128: $J$9<=$C$9 | F128: Binding | G128: 0
B129: $J$10 | C129: June - Weekend Off-peak Total_MWh | D129: 0 | E129: $J$10<=$C$10 | F129: Not Binding | G129: 96000
B130: $J$11 | C130: July - Weekday Peak Total_MWh | D130: 264000 | E130: $J$11<=$C$11 | F130: Binding | G130: 0
B131: $J$12 | C131: July - Weekday Off-peak Total_MWh | D131: 0 | E131: $J$12<=$C$12 | F131: Not Binding | G131: 264000
B132: $J$13 | C132: July - Weekend Peak Total_MWh | D132: 108000 | E132: $J$13<=$C$13 | F132: Binding | G132: 0
B133: $J$14 | C133: July - Weekend Off-peak Total_MWh | D133: 0 | E133: $J$14<=$C$14 | F133: Not Binding | G133: 108000
B134: $J$15 | C134: August - Weekday Peak Total_MWh | D134: 264000 | E134: $J$15<=$C$15 | F134: Binding | G134: 0
B135: $J$16 | C135: August - Weekday Off-peak Total_MWh | D135: 264000 | E135: $J$16<=$C$16 | F135: Binding | G135: 0
B136: $J$17 | C136: August - Weekend Peak Total_MWh | D136: 108000 | E136: $J$17<=$C$17 | F136: Binding | G136: 0
... B202: $G$18 | C202: August - Weekend Off-peak X_Scottish_t | D202: 0 | E202: $G$18=0 | F202: Binding | G202: 0

Sheet CO2 20€
A6: Month | B6: Hours | C6: Max_Capacity | D6: X_Stockpile_t | E6: X_Colombian_t | F6: X_Russian_t | G6: X_Scottish_t | H6: X_Wood_t | I6: Thermal_Input_GJ | J6: Total_MWh | K6: Wood_Chips_MWh | L6: Price_per MWh | M6: Revenue | N6: ROC_Revenue | O6: Grid_Charge | P6: Fuel_Cost | Q6: CO2_Cost | R6: Profit | S6: Wood_Thermal_GJ | T6: SO2_tonnes | U6: Biomass_share | V6: Thermal_Input_GJ*0.1 | W6: Coal fule | Y6: Wood_Chips_Constraint
A7: June - Weekday Peak | B7: 264 | C7: =B7*1000 -> 264000 | D7: 94687.552 | E7: 0 | F7: 0 | G7: 0 | H7: 15085.714 | I7: =SUMPRODUCT(D7:H7, N$31:R$31) -> 2715428.6 | J7: =(SUMPRODUCT(D7:H7, N$31:R$31)*0.35)/3.6 -> 264000 | K7: =($R$31*H7*0.35)/3.6 -> 26400 | L7: =VLOOKUP(A7,F29:G49,2,FALSE) -> 36 | M7: =L7*J7 -> 9504000 | N7: =45*($R$31*H7*0.35)/3.6 -> 1188000 | O7: =SUMPRODUCT(D7:H7, N$31:R$31)*0.35*0.65/3.6 -> 171600 | P7: =SUMPRODUCT(D7:H7, N$30:R$30) -> 5142775.4 | Q7: =J7*0.8*0.87*20 -> 3674880 | R7: =IFERROR(M7+N7-O7-P7-Q7,0) -> 1702744.6 | S7: =H7*$R$31 -> 271542.86 | T7: =SUMPRODUCT(D7:H7, N$32:R$32)*0.01 -> 1308.1968 | U7: =IFERROR(S7/I7,0) -> 0.1 | V7: =0.1*I7 -> 271542.86 | W7: =SUMPRODUCT($N$31:$Q$31,D7:G7) -> 2443885.7 | Y7: =K7-0.1*J7 -> 0
A8: June - Weekday Off-peak | B8: 264 | C8: =B8*1000 -> 264000 | D8: 0 | E8: 0 | F8: 0 | G8: 0 | H8: 0 | I8: =SUMPRODUCT(D8:H8, N$31:R$31) -> 0 | J8: =(SUMPRODUCT(D8:H8, N$31:R$31)*0.35)/3.6 -> 0 | K8: =($R$31*H8*0.35)/3.6 -> 0 | L8: =VLOOKUP(A8,F30:G51,2,FALSE) -> 27 | M8: =L8*J8 -> 0 | N8: =45*($R$31*H8*0.35)/3.6 -> 0 | O8: =SUMPRODUCT(D8:H8, N$31:R$31)*0.35*0.65/3.6 -> 0 | P8: =SUMPRODUCT(D8:H8, N$30:R$30) -> 0 | Q8: =J8*0.8*0.87*20 -> 0 | R8: =IFERROR(M8+N8-O8-P8-Q8,0) -> 0 | S8: =H8*$R$31 -> 0 | T8: =SUMPRODUCT(D8:H8, N$32:R$32)*0.01 -> 0 | U8: =IFERROR(S8/I8,0) -> 0 | V8: =0.1*I8 -> 0 | W8: =SUMPRODUCT($N$31:$Q$31,D8:G8) -> 0 | Y8: =K8-0.1*J8 -> 0
A9: June - Weekend Peak | B9: 96 | C9: =B9*1000 -> 96000 | D9: 34431.837 | E9: 0 | F9: 0 | G9: 0 | H9: 5485.7143 | I9: =SUMPRODUCT(D9:H9, N$31:R$31) -> 987428.57 | J9: =(SUMPRODUCT(D9:H9, N$31:R$31)*0.35)/3.6 -> 96000 | K9: =($R$31*H9*0.35)/3.6 -> 9600 | L9: =VLOOKUP(A9,F31:G52,2,FALSE) -> 33.5 | M9: =L9*J9 -> 3216000 | N9: =45*($R$31*H9*0.35)/3.6 -> 432000 | O9: =SUMPRODUCT(D9:H9, N$31:R$31)*0.35*0.65/3.6 -> 62400 | P9: =SUMPRODUCT(D9:H9, N$30:R$30) -> 1870100.1 | Q9: =J9*0.8*0.87*20 -> 1336320 | R9: =IFERROR(M9+N9-O9-P9-Q9,0) -> 379179.87 | S9: =H9*$R$31 -> 98742.857 | T9: =SUMPRODUCT(D9:H9, N$32:R$32)*0.01 -> 475.70792 | U9: =IFERROR(S9/I9,0) -> 0.1 | V9: =0.1*I9 -> 98742.857 | W9: =SUMPRODUCT($N$31:$Q$31,D9:G9) -> 888685.71 | Y9: =K9-0.1*J9 -> 0
A10: June - Weekend Off-peak | B10: 96 | C10: =B10*1000 -> 96000 | D10: 0 | E10: 0 | F10: 0 | G10: 0 | H10: 0 | I10: =SUMPRODUCT(D10:H10, N$31:R$31) -> 0 | J10: =(SUMPRODUCT(D10:H10, N$31:R$31)*0.35)/3.6 -> 0 | K10: =($R$31*H10*0.35)/3.6 -> 0 | L10: =VLOOKUP(A10,F32:G53,2,FALSE) -> 26.2 | M10: =L10*J10 -> 0 | N10: =45*($R$31*H10*0.35)/3.6 -> 0 | O10: =SUMPRODUCT(D10:H10, N$31:R$31)*0.35*0.65/3.6 -> 0 | P10: =SUMPRODUCT(D10:H10, N$30:R$30) -> 0 | Q10: =J10*0.8*0.87*20 -> 0 | R10: =IFERROR(M10+N10-O10-P10-Q10,0) -> 0 | S10: =H10*$R$31 -> 0 | T10: =SUMPRODUCT(D10:H10, N$32:R$32)*0.01 -> 0 | U10: =IFERROR(S10/I10,0) -> 0 | V10: =0.1*I10 -> 0 | W10: =SUMPRODUCT($N$31:$Q$31,D10:G10) -> 0 | Y10: =K10-0.1*J10 -> 0
A11: July - Weekday Peak | B11: 264 | C11: =B11*1000 -> 264000 | D11: 94687.552 | E11: 0 | F11: 0 | G11: 0 | H11: 15085.714 | I11: =SUMPRODUCT(D11:H11, N$31:R$31) -> 2715428.6 | J11: =(SUMPRODUCT(D11:H11, N$31:R$31)*0.35)/3.6 -> 264000 | K11: =($R$31*H11*0.35)/3.6 -> 26400 | L11: =VLOOKUP(A11,F33:G54,2,FALSE) -> 36.35 | M11: =L11*J11 -> 9596400 | N11: =45*($R$31*H11*0.35)/3.6 -> 1188000 | O11: =SUMPRODUCT(D11:H11, N$31:R$31)*0.35*0.65/3.6 -> 171600 | P11: =SUMPRODUCT(D11:H11, N$30:R$30) -> 5142775.4 | Q11: =J11*0.8*0.87*20 -> 3674880 | R11: =IFERROR(M11+N11-O11-P11-Q11,0) -> 1795144.6 | S11: =H11*$R$31 -> 271542.86 | T11: =SUMPRODUCT(D11:H11, N$32:R$32)*0.01 -> 1308.1968 | U11: =IFERROR(S11/I11,0) -> 0.1 | V11: =0.1*I11 -> 271542.86 | W11: =SUMPRODUCT($N$31:$Q$31,D11:G11) -> 2443885.7 | Y11: =K11-0.1*J11 -> 0
A12: July - Weekday Off-peak | B12: 264 | C12: =B12*1000 -> 264000 | D12: 0 | E12: 0 | F12: 0 | G12: 0 | H12: 0 | I12: =SUMPRODUCT(D12:H12, N$31:R$31) -> 0 | J12: =(SUMPRODUCT(D12:H12, N$31:R$31)*0.35)/3.6 -> 0 | K12: =($R$31*H12*0.35)/3.6 -> 0 | L12: =VLOOKUP(A12,F34:G55,2,FALSE) -> 27 | M12: =L12*J12 -> 0 | N12: =45*($R$31*H12*0.35)/3.6 -> 0 | O12: =SUMPRODUCT(D12:H12, N$31:R$31)*0.35*0.65/3.6 -> 0 | P12: =SUMPRODUCT(D12:H12, N$30:R$30) -> 0 | Q12: =J12*0.8*0.87*20 -> 0 | R12: =IFERROR(M12+N12-O12-P12-Q12,0) -> 0 | S12: =H12*$R$31 -> 0 | T12: =SUMPRODUCT(D12:H12, N$32:R$32)*0.01 -> 0 | U12: =IFERROR(S12/I12,0) -> 0 | V12: =0.1*I12 -> 0 | W12: =SUMPRODUCT($N$31:$Q$31,D12:G12) -> 0 | Y12: =K12-0.1*J12 -> 0
A13: July - Weekend Peak | B13: 108 | C13: =B13*1000 -> 108000 | D13: 38735.817 | E13: 0 | F13: 0 | G13: 0 | H13: 6171.4286 | I13: =SUMPRODUCT(D13:H13, N$31:R$31) -> 1110857.1 | J13: =(SUMPRODUCT(D13:H13, N$31:R$31)*0.35)/3.6 -> 108000 | K13: =($R$31*H13*0.35)/3.6 -> 10800 | L13: =VLOOKUP(A13,F35:G56,2,FALSE) -> 34.3 | M13: =L13*J13 -> 3704400 | N13: =45*($R$31*H13*0.35)/3.6 -> 486000 | O13: =SUMPRODUCT(D13:H13, N$31:R$31)*0.35*0.65/3.6 -> 70200 | P13: =SUMPRODUCT(D13:H13, N$30:R$30) -> 2103862.6 | Q13: =J13*0.8*0.87*20 -> 1503360 | R13: =IFERROR(M13+N13-O13-P13-Q13,0) -> 512977.36 | S13: =H13*$R$31 -> 111085.71 | T13: =SUMPRODUCT(D13:H13, N$32:R$32)*0.01 -> 535.17141 | U13: =IFERROR(S13/I13,0) -> 0.1 | V13: =0.1*I13 -> 111085.71 | W13: =SUMPRODUCT($N$31:$Q$31,D13:G13) -> 999771.43 | Y13: =K13-0.1*J13 -> 0
A14: July - Weekend Off-peak | B14: 108 | C14: =B14*1000 -> 108000 | D14: 0 | E14: 0 | F14: 0 | G14: 0 | H14: 0 | I14: =SUMPRODUCT(D14:H14, N$31:R$31) -> 0 | J14: =(SUMPRODUCT(D14:H14, N$31:R$31)*0.35)/3.6 -> 0 | K14: =($R$31*H14*0.35)/3.6 -> 0 | L14: =VLOOKUP(A14,F36:G57,2,FALSE) -> 26.3 | M14: =L14*J14 -> 0 | N14: =45*($R$31*H14*0.35)/3.6 -> 0 | O14: =SUMPRODUCT(D14:H14, N$31:R$31)*0.35*0.65/3.6 -> 0 | P14: =SUMPRODUCT(D14:H14, N$30:R$30) -> 0 | Q14: =J14*0.8*0.87*20 -> 0 | R14: =IFERROR(M14+N14-O14-P14-Q14,0) -> 0 | S14: =H14*$R$31 -> 0 | T14: =SUMPRODUCT(D14:H14, N$32:R$32)*0.01 -> 0 | U14: =IFERROR(S14/I14,0) -> 0 | V14: =0.1*I14 -> 0 | W14: =SUMPRODUCT($N$31:$Q$31,D14:G14) -> 0 | Y14: =K14-0.1*J14 -> 0
A15: August - Weekday Peak | B15: 264 | C15: =B15*1000 -> 264000 | D15: 94687.552 | E15: 0 | F15: 0 | G15: 0 | H15: 15085.714 | I15: =SUMPRODUCT(D15:H15, N$31:R$31) -> 2715428.6 | J15: =(SUMPRODUCT(D15:H15, N$31:R$31)*0.35)/3.6 -> 264000 | K15: =($R$31*H15*0.35)/3.6 -> 26400 | L15: =VLOOKUP(A15,F37:G58,2,FALSE) -> 37.65 | M15: =L15*J15 -> 9939600 | N15: =45*($R$31*H15*0.35)/3.6 -> 1188000 | O15: =SUMPRODUCT(D15:H15, N$31:R$31)*0.35*0.65/3.6 -> 171600 | P15: =SUMPRODUCT(D15:H15, N$30:R$30) -> 5142775.4 | Q15: =J15*0.8*0.87*20 -> 3674880 | R15: =IFERROR(M15+N15-O15-P15-Q15,0) -> 2138344.6 | S15: =H15*$R$31 -> 271542.86 | T15: =SUMPRODUCT(D15:H15, N$32:R$32)*0.01 -> 1308.1968 | U15: =IFERROR(S15/I15,0) -> 0.1 | V15: =0.1*I15 -> 271542.86 | W15: =SUMPRODUCT($N$31:$Q$31,D15:G15) -> 2443885.7 | Y15: =K15-0.1*J15 -> 0
A16: August - Weekday Off-peak | B16: 264 | C16: =B16*1000 -> 264000 | D16: 0 | E16: 0 | F16: 0 | G16: 0 | H16: 0 | I16: =SUMPRODUCT(D16:H16, N$31:R$31) -> 0 | J16: =(SUMPRODUCT(D16:H16, N$31:R$31)*0.35)/3.6 -> 0 | K16: =($R$31*H16*0.35)/3.6 -> 0 | L16: =VLOOKUP(A16,F38:G59,2,FALSE) -> 28.2 | M16: =L16*J16 -> 0 | N16: =45*($R$31*H16*0.35)/3.6 -> 0 | O16: =SUMPRODUCT(D16:H16, N$31:R$31)*0.35*0.65/3.6 -> 0 | P16: =SUMPRODUCT(D16:H16, N$30:R$30) -> 0 | Q16: =J16*0.8*0.87*20 -> 0 | R16: =IFERROR(M16+N16-O16-P16-Q16,0) -> 0 | S16: =H16*$R$31 -> 0 | T16: =SUMPRODUCT(D16:H16, N$32:R$32)*0.01 -> 0 | U16: =IFERROR(S16/I16,0) -> 0 | V16: =0.1*I16 -> 0 | W16: =SUMPRODUCT($N$31:$Q$31,D16:G16) -> 0 | Y16: =K16-0.1*J16 -> 0
A17: August - Weekend Peak | B17: 108 | C17: =B17*1000 -> 108000 | D17: 38735.817 | E17: 0 | F17: 0 | G17: 0 | H17: 6171.4286 | I17: =SUMPRODUCT(D17:H17, N$31:R$31) -> 1110857.1 | J17: =(SUMPRODUCT(D17:H17, N$31:R$31)*0.35)/3.6 -> 108000 | K17: =($R$31*H17*0.35)/3.6 -> 10800 | L17: =VLOOKUP(A17,F39:G60,2,FALSE) -> 35.65 | M17: =L17*J17 -> 3850200 | N17: =45*($R$31*H17*0.35)/3.6 -> 486000 | O17: =SUMPRODUCT(D17:H17, N$31:R$31)*0.35*0.65/3.6 -> 70200 | P17: =SUMPRODUCT(D17:H17, N$30:R$30) -> 2103862.6 | Q17: =J17*0.8*0.87*20 -> 1503360 | R17: =IFERROR(M17+N17-O17-P17-Q17,0) -> 658777.36 | S17: =H17*$R$31 -> 111085.71 | T17: =SUMPRODUCT(D17:H17, N$32:R$32)*0.01 -> 535.17141 | U17: =IFERROR(S17/I17,0) -> 0.1 | V17: =0.1*I17 -> 111085.71 | W17: =SUMPRODUCT($N$31:$Q$31,D17:G17) -> 999771.43 | Y17: =K17-0.1*J17 -> 0
A18: August - Weekend Off-peak | B18: 108 | C18: =B18*1000 -> 108000 | D18: 0 | E18: 0 | F18: 0 | G18: 0 | H18: 0 | I18: =SUMPRODUCT(D18:H18, N$31:R$31) -> 0 | J18: =(SUMPRODUCT(D18:H18, N$31:R$31)*0.35)/3.6 -> 0 | K18: =($R$31*H18*0.35)/3.6 -> 0 | L18: =VLOOKUP(A18,F40:G61,2,FALSE) -> 27.5 | M18: =L18*J18 -> 0 | N18: =45*($R$31*H18*0.35)/3.6 -> 0 | O18: =SUMPRODUCT(D18:H18, N$31:R$31)*0.35*0.65/3.6 -> 0 | P18: =SUMPRODUCT(D18:H18, N$30:R$30) -> 0 | Q18: =J18*0.8*0.87*20 -> 0 | R18: =IFERROR(M18+N18-O18-P18-Q18,0) -> 0 | S18: =H18*$R$31 -> 0 | T18: =SUMPRODUCT(D18:H18, N$32:R$32)*0.01 -> 0 | U18: =IFERROR(S18/I18,0) -> 0 | V18: =0.1*I18 -> 0 | W18: =SUMPRODUCT($N$31:$Q$31,D18:G18) -> 0 | Y18: =K18-0.1*J18 -> 0
A19: September - Weekday Peak | B19: 264 | C19: =B19*1000 -> 264000 | D19: 0 | E19: 0 | F19: 18357.448 | G19: 76111.765 | H19: 15085.714 | I19: =SUMPRODUCT(D19:H19, N$31:R$31) -> 2715428.6 | J19: =(SUMPRODUCT(D19:H19, N$31:R$31)*0.35)/3.6 -> 264000 | K19: =($R$31*H19*0.35)/3.6 -> 26400 | L19: =VLOOKUP(A19,F41:G62,2,FALSE) -> 38.35 | M19: =L19*J19 -> 10124400 | N19: =45*($R$31*H19*0.35)/3.6 -> 1188000 | O19: =SUMPRODUCT(D19:H19, N$31:R$31)*0.35*0.65/3.6 -> 171600 | P19: =SUMPRODUCT(D19:H19, N$30:R$30) -> 5113623.5 | Q19: =J19*0.8*0.87*20 -> 3674880 | R19: =IFERROR(M19+N19-O19-P19-Q19,0) -> 2352296.5 | S19: =H19*$R$31 -> 271542.86 | T19: =SUMPRODUCT(D19:H19, N$32:R$32)*0.01 -> 1374.882 | U19: =IFERROR(S19/I19,0) -> 0.1 | V19: =0.1*I19 -> 271542.86 | W19: =SUMPRODUCT($N$31:$Q$31,D19:G19) -> 2443885.7 | Y19: =K19-0.1*J19 -> 0
... A26: October - Weekend Off-peak | B26: 120 | C26: =B26*1000 -> 120000 | D26: 0 | E26: 0 | F26: 0 | G26: 0 | H26: 0 | I26: =SUMPRODUCT(D26:H26, N$31:R$31) -> 0 | J26: =(SUMPRODUCT(D26:H26, N$31:R$31)*0.35)/3.6 -> 0 | K26: =($R$31*H26*0.35)/3.6 -> 0 | L26: =VLOOKUP(A26,F48:G69,2,FALSE) -> 30.1 | M26: =L26*J26 -> 0 | N26: =45*($R$31*H26*0.35)/3.6 -> 0 | O26: =SUMPRODUCT(D26:H26, N$31:R$31)*0.35*0.65/3.6 -> 0 | P26: =SUMPRODUCT(D26:H26, N$30:R$30) -> 0 | Q26: =J26*0.8*0.87*20 -> 0 | R26: =IFERROR(M26+N26-O26-P26-Q26,0) -> 0 | S26: =H26*$R$31 -> 0 | T26: =SUMPRODUCT(D26:H26, N$32:R$32)*0.01 -> 0 | U26: =IFERROR(S26/I26,0) -> 0 | V26: =0.1*I26 -> 0 | W26: =SUMPRODUCT($N$31:$Q$31,D26:G26) -> 0 | Y26: =K26-0.1*J26 -> 0
A27: Total | C27: =SUM(C7:C26) -> 3672000 | D27: =SUM(D7:D26) -> 395966.13 | E27: =SUM(E7:E26) -> 0 | F27: =SUM(F7:F26) -> 195187.77 | G27: =SUM(G7:G26) -> 165149.93 | H27: =SUM(H7:H26) -> 119314.29 | J27: =SUM(J7:J26) -> 2088000 | K27: =SUM(K7:K26) -> 208800 | L27: =SUM(L7:L26) -> 650.15 | M27: =SUM(M7:M26) -> 77016600 | N27: =SUM(N7:N26) -> 9396000 | O27: =SUM(O7:O26) -> 1357200 | P27: =SUM(P7:P26) -> 41139655 | Q27: =SUM(Q7:Q26) -> 29064960 | ... T27: =SUM(T7:T26) -> 9000 | V27: =SUM(V7:V26) -> 2147657.1 | W27: =SUMPRODUCT($N$31:$Q$31,D27:G27) -> 19328914
F29: Period | G29: Electricity_Forward_Price | J29: Scalars | K29: Value | M29: Fuel | N29: Stockpile coal | O29: Colombian coal | P29: Russian coal | Q29: Scottish coal | R29: Wood chips
F30: June - Weekday Peak | G30: 36 | J30: Efficiency | K30: 0.35 | M30: Price_per_t | N30: 42.56 | O30: 43.93 | P30: 43.8 | Q30: 42 | R30: 73.77
F31: June - Weekday Off-peak | G31: 27 | J31: Plant_Capacity_MW | K31: 1000 | M31: CV_GJ_per_t | N31: 25.81 | O31: 25.12 | P31: 24.5 | Q31: 26.2 | R31: 18
F32: June - Weekend Peak | G32: 33.5 | J32: Grid_Charge_per_MWh | K32: 0.65 | M32: SO2_percent | N32: 1.38 | O32: 0.7 | P32: 0.35 | Q32: 1.72 | R32: 0.01
F33: June - Weekend Off-peak | G33: 26.2 | J33: CO2_Intensity_t_per_MWh | K33: 0.8
F34: July - Weekday Peak | G34: 36.35 | J34: CO2_Cost_EUR_per_t | K34: 15
F35: July - Weekday Off-peak | G35: 27 | J35: FX_EUR_per_GBP | K35: 0.87
F36: July - Weekend Peak | G36: 34.3 | J36: ROC_per_MWh | K36: 45
F37: July - Weekend Off-peak | G37: 26.3 | J37: Sulphur_Allowance_t | K37: 9000
F38: August - Weekday Peak | G38: 37.65 | J38: Stockpile_Tonnes | K38: 600000
F39: August - Weekday Off-peak | G39: 28.2 | J39: Biomass_Share_Max | K39: 0.1
F40: August - Weekend Peak | G40: 35.65 | J40: Hours_Peak_per_Day | K40: 12
F41: August - Weekend Off-peak | G41: 27.5 | J41: Hours_Offpeak_per_Day | K41: 12
F42: September - Weekday Peak | G42: 38.35 | J42: P_Colombian_t | K42: 0
F43: September - Weekday Off-peak | G43: 28.5 | J43: P_Russian_t | K43: 0
F44: September - Weekend Peak | G44: 35.8 | J44: P_Scottish_t | K44: 0
F45: September - Weekend Off-peak | G45: 27.65
F46: October - Weekday Peak | G46: 43.7
F47: October - Weekday Off-peak | G47: 31.7
F48: October - Weekend Peak | G48: 38.7
F49: October - Weekend Off-peak | G49: 30.1

Sheet CO2 30€
A6: Month | B6: Hours | C6: Max_Capacity | D6: X_Stockpile_t | E6: X_Colombian_t | F6: X_Russian_t | G6: X_Scottish_t | H6: X_Wood_t | I6: Thermal_Input_GJ | J6: Total_MWh | K6: Wood_Chips_MWh | L6: Price_per MWh | M6: Revenue | N6: ROC_Revenue | O6: Grid_Charge | P6: Fuel_Cost | Q6: CO2_Cost | R6: Profit | S6: Wood_Thermal_GJ | T6: SO2_tonnes | U6: Biomass_share | V6: Thermal_Input_GJ*0.1 | W6: Coal fule | Y6: Wood_Chips_Constraint
A7: June - Weekday Peak | B7: 264 | C7: =B7*1000 -> 264000 | D7: 0 | E7: 0 | F7: 0 | G7: 0 | H7: 0 | I7: =SUMPRODUCT(D7:H7, N$31:R$31) -> 0 | J7: =(SUMPRODUCT(D7:H7, N$31:R$31)*0.35)/3.6 -> 0 | K7: =($R$31*H7*0.35)/3.6 -> 0 | L7: =VLOOKUP(A7,F29:G49,2,FALSE) -> 36 | M7: =L7*J7 -> 0 | N7: =45*($R$31*H7*0.35)/3.6 -> 0 | O7: =SUMPRODUCT(D7:H7, N$31:R$31)*0.35*0.65/3.6 -> 0 | P7: =SUMPRODUCT(D7:H7, N$30:R$30) -> 0 | Q7: =J7*0.8*0.87*30 -> 0 | R7: =IFERROR(M7+N7-O7-P7-Q7,0) -> 0 | S7: =H7*$R$31 -> 0 | T7: =SUMPRODUCT(D7:H7, N$32:R$32)*0.01 -> 0 | U7: =IFERROR(S7/I7,0) -> 0 | V7: =0.1*I7 -> 0 | W7: =SUMPRODUCT($N$31:$Q$31,D7:G7) -> 0 | Y7: =K7-0.1*J7 -> 0
A8: June - Weekday Off-peak | B8: 264 | C8: =B8*1000 -> 264000 | D8: 0 | E8: 0 | F8: 0 | G8: 0 | H8: 0 | I8: =SUMPRODUCT(D8:H8, N$31:R$31) -> 0 | J8: =(SUMPRODUCT(D8:H8, N$31:R$31)*0.35)/3.6 -> 0 | K8: =($R$31*H8*0.35)/3.6 -> 0 | L8: =VLOOKUP(A8,F30:G51,2,FALSE) -> 27 | M8: =L8*J8 -> 0 | N8: =45*($R$31*H8*0.35)/3.6 -> 0 | O8: =SUMPRODUCT(D8:H8, N$31:R$31)*0.35*0.65/3.6 -> 0 | P8: =SUMPRODUCT(D8:H8, N$30:R$30) -> 0 | Q8: =J8*0.8*0.87*30 -> 0 | R8: =IFERROR(M8+N8-O8-P8-Q8,0) -> 0 | S8: =H8*$R$31 -> 0 | T8: =SUMPRODUCT(D8:H8, N$32:R$32)*0.01 -> 0 | U8: =IFERROR(S8/I8,0) -> 0 | V8: =0.1*I8 -> 0 | W8: =SUMPRODUCT($N$31:$Q$31,D8:G8) -> 0 | Y8: =K8-0.1*J8 -> 0
A9: June - Weekend Peak | B9: 96 | C9: =B9*1000 -> 96000 | D9: 0 | E9: 0 | F9: 0 | G9: 0 | H9: 0 | I9: =SUMPRODUCT(D9:H9, N$31:R$31) -> 0 | J9: =(SUMPRODUCT(D9:H9, N$31:R$31)*0.35)/3.6 -> 0 | K9: =($R$31*H9*0.35)/3.6 -> 0 | L9: =VLOOKUP(A9,F31:G52,2,FALSE) -> 33.5 | M9: =L9*J9 -> 0 | N9: =45*($R$31*H9*0.35)/3.6 -> 0 | O9: =SUMPRODUCT(D9:H9, N$31:R$31)*0.35*0.65/3.6 -> 0 | P9: =SUMPRODUCT(D9:H9, N$30:R$30) -> 0 | Q9: =J9*0.8*0.87*30 -> 0 | R9: =IFERROR(M9+N9-O9-P9-Q9,0) -> 0 | S9: =H9*$R$31 -> 0 | T9: =SUMPRODUCT(D9:H9, N$32:R$32)*0.01 -> 0 | U9: =IFERROR(S9/I9,0) -> 0 | V9: =0.1*I9 -> 0 | W9: =SUMPRODUCT($N$31:$Q$31,D9:G9) -> 0 | Y9: =K9-0.1*J9 -> 0
A10: June - Weekend Off-peak | B10: 96 | C10: =B10*1000 -> 96000 | D10: 0 | E10: 0 | F10: 0 | G10: 0 | H10: 0 | I10: =SUMPRODUCT(D10:H10, N$31:R$31) -> 0 | J10: =(SUMPRODUCT(D10:H10, N$31:R$31)*0.35)/3.6 -> 0 | K10: =($R$31*H10*0.35)/3.6 -> 0 | L10: =VLOOKUP(A10,F32:G53,2,FALSE) -> 26.2 | M10: =L10*J10 -> 0 | N10: =45*($R$31*H10*0.35)/3.6 -> 0 | O10: =SUMPRODUCT(D10:H10, N$31:R$31)*0.35*0.65/3.6 -> 0 | P10: =SUMPRODUCT(D10:H10, N$30:R$30) -> 0 | Q10: =J10*0.8*0.87*30 -> 0 | R10: =IFERROR(M10+N10-O10-P10-Q10,0) -> 0 | S10: =H10*$R$31 -> 0 | T10: =SUMPRODUCT(D10:H10, N$32:R$32)*0.01 -> 0 | U10: =IFERROR(S10/I10,0) -> 0 | V10: =0.1*I10 -> 0 | W10: =SUMPRODUCT($N$31:$Q$31,D10:G10) -> 0 | Y10: =K10-0.1*J10 -> 0
A11: July - Weekday Peak | B11: 264 | C11: =B11*1000 -> 264000 | D11: 0 | E11: 0 | F11: 0 | G11: 0 | H11: 0 | I11: =SUMPRODUCT(D11:H11, N$31:R$31) -> 0 | J11: =(SUMPRODUCT(D11:H11, N$31:R$31)*0.35)/3.6 -> 0 | K11: =($R$31*H11*0.35)/3.6 -> 0 | L11: =VLOOKUP(A11,F33:G54,2,FALSE) -> 36.35 | M11: =L11*J11 -> 0 | N11: =45*($R$31*H11*0.35)/3.6 -> 0 | O11: =SUMPRODUCT(D11:H11, N$31:R$31)*0.35*0.65/3.6 -> 0 | P11: =SUMPRODUCT(D11:H11, N$30:R$30) -> 0 | Q11: =J11*0.8*0.87*30 -> 0 | R11: =IFERROR(M11+N11-O11-P11-Q11,0) -> 0 | S11: =H11*$R$31 -> 0 | T11: =SUMPRODUCT(D11:H11, N$32:R$32)*0.01 -> 0 | U11: =IFERROR(S11/I11,0) -> 0 | V11: =0.1*I11 -> 0 | W11: =SUMPRODUCT($N$31:$Q$31,D11:G11) -> 0 | Y11: =K11-0.1*J11 -> 0
A12: July - Weekday Off-peak | B12: 264 | C12: =B12*1000 -> 264000 | D12: 0 | E12: 0 | F12: 0 | G12: 0 | H12: 0 | I12: =SUMPRODUCT(D12:H12, N$31:R$31) -> 0 | J12: =(SUMPRODUCT(D12:H12, N$31:R$31)*0.35)/3.6 -> 0 | K12: =($R$31*H12*0.35)/3.6 -> 0 | L12: =VLOOKUP(A12,F34:G55,2,FALSE) -> 27 | M12: =L12*J12 -> 0 | N12: =45*($R$31*H12*0.35)/3.6 -> 0 | O12: =SUMPRODUCT(D12:H12, N$31:R$31)*0.35*0.65/3.6 -> 0 | P12: =SUMPRODUCT(D12:H12, N$30:R$30) -> 0 | Q12: =J12*0.8*0.87*30 -> 0 | R12: =IFERROR(M12+N12-O12-P12-Q12,0) -> 0 | S12: =H12*$R$31 -> 0 | T12: =SUMPRODUCT(D12:H12, N$32:R$32)*0.01 -> 0 | U12: =IFERROR(S12/I12,0) -> 0 | V12: =0.1*I12 -> 0 | W12: =SUMPRODUCT($N$31:$Q$31,D12:G12) -> 0 | Y12: =K12-0.1*J12 -> 0
A13: July - Weekend Peak | B13: 108 | C13: =B13*1000 -> 108000 | D13: 0 | E13: 0 | F13: 0 | G13: 0 | H13: 0 | I13: =SUMPRODUCT(D13:H13, N$31:R$31) -> 0 | J13: =(SUMPRODUCT(D13:H13, N$31:R$31)*0.35)/3.6 -> 0 | K13: =($R$31*H13*0.35)/3.6 -> 0 | L13: =VLOOKUP(A13,F35:G56,2,FALSE) -> 34.3 | M13: =L13*J13 -> 0 | N13: =45*($R$31*H13*0.35)/3.6 -> 0 | O13: =SUMPRODUCT(D13:H13, N$31:R$31)*0.35*0.65/3.6 -> 0 | P13: =SUMPRODUCT(D13:H13, N$30:R$30) -> 0 | Q13: =J13*0.8*0.87*30 -> 0 | R13: =IFERROR(M13+N13-O13-P13-Q13,0) -> 0 | S13: =H13*$R$31 -> 0 | T13: =SUMPRODUCT(D13:H13, N$32:R$32)*0.01 -> 0 | U13: =IFERROR(S13/I13,0) -> 0 | V13: =0.1*I13 -> 0 | W13: =SUMPRODUCT($N$31:$Q$31,D13:G13) -> 0 | Y13: =K13-0.1*J13 -> 0
A14: July - Weekend Off-peak | B14: 108 | C14: =B14*1000 -> 108000 | D14: 0 | E14: 0 | F14: 0 | G14: 0 | H14: 0 | I14: =SUMPRODUCT(D14:H14, N$31:R$31) -> 0 | J14: =(SUMPRODUCT(D14:H14, N$31:R$31)*0.35)/3.6 -> 0 | K14: =($R$31*H14*0.35)/3.6 -> 0 | L14: =VLOOKUP(A14,F36:G57,2,FALSE) -> 26.3 | M14: =L14*J14 -> 0 | N14: =45*($R$31*H14*0.35)/3.6 -> 0 | O14: =SUMPRODUCT(D14:H14, N$31:R$31)*0.35*0.65/3.6 -> 0 | P14: =SUMPRODUCT(D14:H14, N$30:R$30) -> 0 | Q14: =J14*0.8*0.87*30 -> 0 | R14: =IFERROR(M14+N14-O14-P14-Q14,0) -> 0 | S14: =H14*$R$31 -> 0 | T14: =SUMPRODUCT(D14:H14, N$32:R$32)*0.01 -> 0 | U14: =IFERROR(S14/I14,0) -> 0 | V14: =0.1*I14 -> 0 | W14: =SUMPRODUCT($N$31:$Q$31,D14:G14) -> 0 | Y14: =K14-0.1*J14 -> 0
A15: August - Weekday Peak | B15: 264 | C15: =B15*1000 -> 264000 | D15: 94687.552 | E15: 0 | F15: 0 | G15: 0 | H15: 15085.714 | I15: =SUMPRODUCT(D15:H15, N$31:R$31) -> 2715428.6 | J15: =(SUMPRODUCT(D15:H15, N$31:R$31)*0.35)/3.6 -> 264000 | K15: =($R$31*H15*0.35)/3.6 -> 26400 | L15: =VLOOKUP(A15,F37:G58,2,FALSE) -> 37.65 | M15: =L15*J15 -> 9939600 | N15: =45*($R$31*H15*0.35)/3.6 -> 1188000 | O15: =SUMPRODUCT(D15:H15, N$31:R$31)*0.35*0.65/3.6 -> 171600 | P15: =SUMPRODUCT(D15:H15, N$30:R$30) -> 5142775.4 | Q15: =J15*0.8*0.87*30 -> 5512320 | R15: =IFERROR(M15+N15-O15-P15-Q15,0) -> 300904.65 | S15: =H15*$R$31 -> 271542.86 | T15: =SUMPRODUCT(D15:H15, N$32:R$32)*0.01 -> 1308.1968 | U15: =IFERROR(S15/I15,0) -> 0.1 | V15: =0.1*I15 -> 271542.86 | W15: =SUMPRODUCT($N$31:$Q$31,D15:G15) -> 2443885.7 | Y15: =K15-0.1*J15 -> 0
A16: August - Weekday Off-peak | B16: 264 | C16: =B16*1000 -> 264000 | D16: 0 | E16: 0 | F16: 0 | G16: 0 | H16: 0 | I16: =SUMPRODUCT(D16:H16, N$31:R$31) -> 0 | J16: =(SUMPRODUCT(D16:H16, N$31:R$31)*0.35)/3.6 -> 0 | K16: =($R$31*H16*0.35)/3.6 -> 0 | L16: =VLOOKUP(A16,F38:G59,2,FALSE) -> 28.2 | M16: =L16*J16 -> 0 | N16: =45*($R$31*H16*0.35)/3.6 -> 0 | O16: =SUMPRODUCT(D16:H16, N$31:R$31)*0.35*0.65/3.6 -> 0 | P16: =SUMPRODUCT(D16:H16, N$30:R$30) -> 0 | Q16: =J16*0.8*0.87*30 -> 0 | R16: =IFERROR(M16+N16-O16-P16-Q16,0) -> 0 | S16: =H16*$R$31 -> 0 | T16: =SUMPRODUCT(D16:H16, N$32:R$32)*0.01 -> 0 | U16: =IFERROR(S16/I16,0) -> 0 | V16: =0.1*I16 -> 0 | W16: =SUMPRODUCT($N$31:$Q$31,D16:G16) -> 0 | Y16: =K16-0.1*J16 -> 0
A17: August - Weekend Peak | B17: 108 | C17: =B17*1000 -> 108000 | D17: 0 | E17: 0 | F17: 0 | G17: 0 | H17: 0 | I17: =SUMPRODUCT(D17:H17, N$31:R$31) -> 0 | J17: =(SUMPRODUCT(D17:H17, N$31:R$31)*0.35)/3.6 -> 0 | K17: =($R$31*H17*0.35)/3.6 -> 0 | L17: =VLOOKUP(A17,F39:G60,2,FALSE) -> 35.65 | M17: =L17*J17 -> 0 | N17: =45*($R$31*H17*0.35)/3.6 -> 0 | O17: =SUMPRODUCT(D17:H17, N$31:R$31)*0.35*0.65/3.6 -> 0 | P17: =SUMPRODUCT(D17:H17, N$30:R$30) -> 0 | Q17: =J17*0.8*0.87*30 -> 0 | R17: =IFERROR(M17+N17-O17-P17-Q17,0) -> 0 | S17: =H17*$R$31 -> 0 | T17: =SUMPRODUCT(D17:H17, N$32:R$32)*0.01 -> 0 | U17: =IFERROR(S17/I17,0) -> 0 | V17: =0.1*I17 -> 0 | W17: =SUMPRODUCT($N$31:$Q$31,D17:G17) -> 0 | Y17: =K17-0.1*J17 -> 0
A18: August - Weekend Off-peak | B18: 108 | C18: =B18*1000 -> 108000 | D18: 0 | E18: 0 | F18: 0 | G18: 0 | H18: 0 | I18: =SUMPRODUCT(D18:H18, N$31:R$31) -> 0 | J18: =(SUMPRODUCT(D18:H18, N$31:R$31)*0.35)/3.6 -> 0 | K18: =($R$31*H18*0.35)/3.6 -> 0 | L18: =VLOOKUP(A18,F40:G61,2,FALSE) -> 27.5 | M18: =L18*J18 -> 0 | N18: =45*($R$31*H18*0.35)/3.6 -> 0 | O18: =SUMPRODUCT(D18:H18, N$31:R$31)*0.35*0.65/3.6 -> 0 | P18: =SUMPRODUCT(D18:H18, N$30:R$30) -> 0 | Q18: =J18*0.8*0.87*30 -> 0 | R18: =IFERROR(M18+N18-O18-P18-Q18,0) -> 0 | S18: =H18*$R$31 -> 0 | T18: =SUMPRODUCT(D18:H18, N$32:R$32)*0.01 -> 0 | U18: =IFERROR(S18/I18,0) -> 0 | V18: =0.1*I18 -> 0 | W18: =SUMPRODUCT($N$31:$Q$31,D18:G18) -> 0 | Y18: =K18-0.1*J18 -> 0
A19: September - Weekday Peak | B19: 264 | C19: =B19*1000 -> 264000 | D19: 0 | E19: 0 | F19: 0 | G19: 93278.081 | H19: 15085.714 | I19: =SUMPRODUCT(D19:H19, N$31:R$31) -> 2715428.6 | J19: =(SUMPRODUCT(D19:H19, N$31:R$31)*0.35)/3.6 -> 264000 | K19: =($R$31*H19*0.35)/3.6 -> 26400 | L19: =VLOOKUP(A19,F41:G62,2,FALSE) -> 38.35 | M19: =L19*J19 -> 10124400 | N19: =45*($R$31*H19*0.35)/3.6 -> 1188000 | O19: =SUMPRODUCT(D19:H19, N$31:R$31)*0.35*0.65/3.6 -> 171600 | P19: =SUMPRODUCT(D19:H19, N$30:R$30) -> 5030552.5 | Q19: =J19*0.8*0.87*30 -> 5512320 | R19: =IFERROR(M19+N19-O19-P19-Q19,0) -> 597927.47 | S19: =H19*$R$31 -> 271542.86 | T19: =SUMPRODUCT(D19:H19, N$32:R$32)*0.01 -> 1605.8916 | U19: =IFERROR(S19/I19,0) -> 0.1 | V19: =0.1*I19 -> 271542.86 | W19: =SUMPRODUCT($N$31:$Q$31,D19:G19) -> 2443885.7 | Y19: =K19-0.1*J19 -> 0
... A26: October - Weekend Off-peak | B26: 120 | C26: =B26*1000 -> 120000 | D26: 0 | E26: 0 | F26: 0 | G26: 0 | H26: 0 | I26: =SUMPRODUCT(D26:H26, N$31:R$31) -> 0 | J26: =(SUMPRODUCT(D26:H26, N$31:R$31)*0.35)/3.6 -> 0 | K26: =($R$31*H26*0.35)/3.6 -> 0 | L26: =VLOOKUP(A26,F48:G69,2,FALSE) -> 30.1 | M26: =L26*J26 -> 0 | N26: =45*($R$31*H26*0.35)/3.6 -> 0 | O26: =SUMPRODUCT(D26:H26, N$31:R$31)*0.35*0.65/3.6 -> 0 | P26: =SUMPRODUCT(D26:H26, N$30:R$30) -> 0 | Q26: =J26*0.8*0.87*30 -> 0 | R26: =IFERROR(M26+N26-O26-P26-Q26,0) -> 0 | S26: =H26*$R$31 -> 0 | T26: =SUMPRODUCT(D26:H26, N$32:R$32)*0.01 -> 0 | U26: =IFERROR(S26/I26,0) -> 0 | V26: =0.1*I26 -> 0 | W26: =SUMPRODUCT($N$31:$Q$31,D26:G26) -> 0 | Y26: =K26-0.1*J26 -> 0
A27: Total | C27: =SUM(C7:C26) -> 3672000 | D27: =SUM(D7:D26) -> 94687.552 | E27: =SUM(E7:E26) -> 0 | F27: =SUM(F7:F26) -> 0 | G27: =SUM(G7:G26) -> 224715.38 | H27: =SUM(H7:H26) -> 51428.571 | J27: =SUM(J7:J26) -> 900000 | K27: =SUM(K7:K26) -> 90000 | L27: =SUM(L7:L26) -> 650.15 | M27: =SUM(M7:M26) -> 35720400 | N27: =SUM(N7:N26) -> 4050000 | O27: =SUM(O7:O26) -> 585000 | P27: =SUM(P7:P26) -> 17261834 | Q27: =SUM(Q7:Q26) -> 18792000 | ... T27: =SUM(T7:T26) -> 5176.9355 | V27: =SUM(V7:V26) -> 925714.29 | W27: =SUMPRODUCT($N$31:$Q$31,D27:G27) -> 8331428.6
F29: Period | G29: Electricity_Forward_Price | J29: Scalars | K29: Value | M29: Fuel | N29: Stockpile coal | O29: Colombian coal | P29: Russian coal | Q29: Scottish coal | R29: Wood chips
F30: June - Weekday Peak | G30: 36 | J30: Efficiency | K30: 0.35 | M30: Price_per_t | N30: 42.56 | O30: 43.93 | P30: 43.8 | Q30: 42 | R30: 73.77
F31: June - Weekday Off-peak | G31: 27 | J31: Plant_Capacity_MW | K31: 1000 | M31: CV_GJ_per_t | N31: 25.81 | O31: 25.12 | P31: 24.5 | Q31: 26.2 | R31: 18
F32: June - Weekend Peak | G32: 33.5 | J32: Grid_Charge_per_MWh | K32: 0.65 | M32: SO2_percent | N32: 1.38 | O32: 0.7 | P32: 0.35 | Q32: 1.72 | R32: 0.01
F33: June - Weekend Off-peak | G33: 26.2 | J33: CO2_Intensity_t_per_MWh | K33: 0.8
F34: July - Weekday Peak | G34: 36.35 | J34: CO2_Cost_EUR_per_t | K34: 15
F35: July - Weekday Off-peak | G35: 27 | J35: FX_EUR_per_GBP | K35: 0.87
F36: July - Weekend Peak | G36: 34.3 | J36: ROC_per_MWh | K36: 45
F37: July - Weekend Off-peak | G37: 26.3 | J37: Sulphur_Allowance_t | K37: 9000
F38: August - Weekday Peak | G38: 37.65 | J38: Stockpile_Tonnes | K38: 600000
F39: August - Weekday Off-peak | G39: 28.2 | J39: Biomass_Share_Max | K39: 0.1
F40: August - Weekend Peak | G40: 35.65 | J40: Hours_Peak_per_Day | K40: 12
F41: August - Weekend Off-peak | G41: 27.5 | J41: Hours_Offpeak_per_Day | K41: 12
F42: September - Weekday Peak | G42: 38.35 | J42: P_Colombian_t | K42: 0
F43: September - Weekday Off-peak | G43: 28.5 | J43: P_Russian_t | K43: 0
F44: September - Weekend Peak | G44: 35.8 | J44: P_Scottish_t | K44: 0
F45: September - Weekend Off-peak | G45: 27.65
F46: October - Weekday Peak | G46: 43.7
F47: October - Weekday Off-peak | G47: 31.7
F48: October - Weekend Peak | G48: 38.7
F49: October - Weekend Off-peak | G49: 30.1

Sheet SO2 30£
A6: Month | B6: Hours | C6: Max_Capacity | D6: X_Stockpile_t | E6: X_Colombian_t | F6: X_Russian_t | G6: X_Scottish_t | H6: X_Wood_t | I6: Thermal_Input_GJ | J6: Total_MWh | K6: Wood_Chips_MWh | L6: Price_per MWh | M6: Revenue | N6: ROC_Revenue | O6: Grid_Charge | P6: Fuel_Cost | Q6: CO2_Cost | R6: Profit | S6: Wood_Thermal_GJ | T6: SO2_tonnes | U6: Biomass_share | V6: Thermal_Input_GJ*0.1 | W6: Coal fule | Y6: Wood_Chips_Constraint
A7: June - Weekday Peak | B7: 264 | C7: =B7*1000 -> 264000 | D7: 94687.552 | E7: 0 | F7: 0 | G7: 0 | H7: 15085.714 | I7: =SUMPRODUCT(D7:H7, N$31:R$31) -> 2715428.6 | J7: =(SUMPRODUCT(D7:H7, N$31:R$31)*0.35)/3.6 -> 264000 | K7: =($R$31*H7*0.35)/3.6 -> 26400 | L7: =VLOOKUP(A7,F29:G49,2,FALSE) -> 36 | M7: =L7*J7 -> 9504000 | N7: =45*($R$31*H7*0.35)/3.6 -> 1188000 | O7: =SUMPRODUCT(D7:H7, N$31:R$31)*0.35*0.65/3.6 -> 171600 | P7: =SUMPRODUCT(D7:H7, N$30:R$30) -> 5142775.4 | Q7: =J7*0.8*0.87*15 -> 2756160 | R7: =IFERROR(M7+N7-O7-P7-Q7,0) -> 2621464.6 | S7: =H7*$R$31 -> 271542.86 | T7: =SUMPRODUCT(D7:H7, N$32:R$32)*0.01 -> 1308.1968 | U7: =IFERROR(S7/I7,0) -> 0.1 | V7: =0.1*I7 -> 271542.86 | W7: =SUMPRODUCT($N$31:$Q$31,D7:G7) -> 2443885.7 | Y7: =K7-0.1*J7 -> 0
A8: June - Weekday Off-peak | B8: 264 | C8: =B8*1000 -> 264000 | D8: 0 | E8: 0 | F8: 0 | G8: 0 | H8: 0 | I8: =SUMPRODUCT(D8:H8, N$31:R$31) -> 0 | J8: =(SUMPRODUCT(D8:H8, N$31:R$31)*0.35)/3.6 -> 0 | K8: =($R$31*H8*0.35)/3.6 -> 0 | L8: =VLOOKUP(A8,F30:G51,2,FALSE) -> 27 | M8: =L8*J8 -> 0 | N8: =45*($R$31*H8*0.35)/3.6 -> 0 | O8: =SUMPRODUCT(D8:H8, N$31:R$31)*0.35*0.65/3.6 -> 0 | P8: =SUMPRODUCT(D8:H8, N$30:R$30) -> 0 | Q8: =J8*0.8*0.87*15 -> 0 | R8: =IFERROR(M8+N8-O8-P8-Q8,0) -> 0 | S8: =H8*$R$31 -> 0 | T8: =SUMPRODUCT(D8:H8, N$32:R$32)*0.01 -> 0 | U8: =IFERROR(S8/I8,0) -> 0 | V8: =0.1*I8 -> 0 | W8: =SUMPRODUCT($N$31:$Q$31,D8:G8) -> 0 | Y8: =K8-0.1*J8 -> 0
A9: June - Weekend Peak | B9: 96 | C9: =B9*1000 -> 96000 | D9: 34431.837 | E9: 0 | F9: 0 | G9: 0 | H9: 5485.7143 | I9: =SUMPRODUCT(D9:H9, N$31:R$31) -> 987428.57 | J9: =(SUMPRODUCT(D9:H9, N$31:R$31)*0.35)/3.6 -> 96000 | K9: =($R$31*H9*0.35)/3.6 -> 9600 | L9: =VLOOKUP(A9,F31:G52,2,FALSE) -> 33.5 | M9: =L9*J9 -> 3216000 | N9: =45*($R$31*H9*0.35)/3.6 -> 432000 | O9: =SUMPRODUCT(D9:H9, N$31:R$31)*0.35*0.65/3.6 -> 62400 | P9: =SUMPRODUCT(D9:H9, N$30:R$30) -> 1870100.1 | Q9: =J9*0.8*0.87*15 -> 1002240 | R9: =IFERROR(M9+N9-O9-P9-Q9,0) -> 713259.87 | S9: =H9*$R$31 -> 98742.857 | T9: =SUMPRODUCT(D9:H9, N$32:R$32)*0.01 -> 475.70792 | U9: =IFERROR(S9/I9,0) -> 0.1 | V9: =0.1*I9 -> 98742.857 | W9: =SUMPRODUCT($N$31:$Q$31,D9:G9) -> 888685.71 | Y9: =K9-0.1*J9 -> 0
A10: June - Weekend Off-peak | B10: 96 | C10: =B10*1000 -> 96000 | D10: 0 | E10: 0 | F10: 0 | G10: 0 | H10: 0 | I10: =SUMPRODUCT(D10:H10, N$31:R$31) -> 0 | J10: =(SUMPRODUCT(D10:H10, N$31:R$31)*0.35)/3.6 -> 0 | K10: =($R$31*H10*0.35)/3.6 -> 0 | L10: =VLOOKUP(A10,F32:G53,2,FALSE) -> 26.2 | M10: =L10*J10 -> 0 | N10: =45*($R$31*H10*0.35)/3.6 -> 0 | O10: =SUMPRODUCT(D10:H10, N$31:R$31)*0.35*0.65/3.6 -> 0 | P10: =SUMPRODUCT(D10:H10, N$30:R$30) -> 0 | Q10: =J10*0.8*0.87*15 -> 0 | R10: =IFERROR(M10+N10-O10-P10-Q10,0) -> 0 | S10: =H10*$R$31 -> 0 | T10: =SUMPRODUCT(D10:H10, N$32:R$32)*0.01 -> 0 | U10: =IFERROR(S10/I10,0) -> 0 | V10: =0.1*I10 -> 0 | W10: =SUMPRODUCT($N$31:$Q$31,D10:G10) -> 0 | Y10: =K10-0.1*J10 -> 0
A11: July - Weekday Peak | B11: 264 | C11: =B11*1000 -> 264000 | D11: 94687.552 | E11: 0 | F11: 0 | G11: 0 | H11: 15085.714 | I11: =SUMPRODUCT(D11:H11, N$31:R$31) -> 2715428.6 | J11: =(SUMPRODUCT(D11:H11, N$31:R$31)*0.35)/3.6 -> 264000 | K11: =($R$31*H11*0.35)/3.6 -> 26400 | L11: =VLOOKUP(A11,F33:G54,2,FALSE) -> 36.35 | M11: =L11*J11 -> 9596400 | N11: =45*($R$31*H11*0.35)/3.6 -> 1188000 | O11: =SUMPRODUCT(D11:H11, N$31:R$31)*0.35*0.65/3.6 -> 171600 | P11: =SUMPRODUCT(D11:H11, N$30:R$30) -> 5142775.4 | Q11: =J11*0.8*0.87*15 -> 2756160 | R11: =IFERROR(M11+N11-O11-P11-Q11,0) -> 2713864.6 | S11: =H11*$R$31 -> 271542.86 | T11: =SUMPRODUCT(D11:H11, N$32:R$32)*0.01 -> 1308.1968 | U11: =IFERROR(S11/I11,0) -> 0.1 | V11: =0.1*I11 -> 271542.86 | W11: =SUMPRODUCT($N$31:$Q$31,D11:G11) -> 2443885.7 | Y11: =K11-0.1*J11 -> 0
A12: July - Weekday Off-peak | B12: 264 | C12: =B12*1000 -> 264000 | D12: 70610.505 | E12: 0 | F12: 0 | G12: 0 | H12: 11249.735 | I12: =SUMPRODUCT(D12:H12, N$31:R$31) -> 2024952.4 | J12: =(SUMPRODUCT(D12:H12, N$31:R$31)*0.35)/3.6 -> 196870.37 | K12: =($R$31*H12*0.35)/3.6 -> 19687.037 | L12: =VLOOKUP(A12,F34:G55,2,FALSE) -> 27 | M12: =L12*J12 -> 5315500 | N12: =45*($R$31*H12*0.35)/3.6 -> 885916.67 | O12: =SUMPRODUCT(D12:H12, N$31:R$31)*0.35*0.65/3.6 -> 127965.74 | P12: =SUMPRODUCT(D12:H12, N$30:R$30) -> 3835076.1 | Q12: =J12*0.8*0.87*15 -> 2055326.7 | R12: =IFERROR(M12+N12-O12-P12-Q12,0) -> 183048.17 | S12: =H12*$R$31 -> 202495.24 | T12: =SUMPRODUCT(D12:H12, N$32:R$32)*0.01 -> 975.54995 | U12: =IFERROR(S12/I12,0) -> 0.1 | V12: =0.1*I12 -> 202495.24 | W12: =SUMPRODUCT($N$31:$Q$31,D12:G12) -> 1822457.1 | Y12: =K12-0.1*J12 -> 0
A13: July - Weekend Peak | B13: 108 | C13: =B13*1000 -> 108000 | D13: 38735.817 | E13: 0 | F13: 0 | G13: 0 | H13: 6171.4286 | I13: =SUMPRODUCT(D13:H13, N$31:R$31) -> 1110857.1 | J13: =(SUMPRODUCT(D13:H13, N$31:R$31)*0.35)/3.6 -> 108000 | K13: =($R$31*H13*0.35)/3.6 -> 10800 | L13: =VLOOKUP(A13,F35:G56,2,FALSE) -> 34.3 | M13: =L13*J13 -> 3704400 | N13: =45*($R$31*H13*0.35)/3.6 -> 486000 | O13: =SUMPRODUCT(D13:H13, N$31:R$31)*0.35*0.65/3.6 -> 70200 | P13: =SUMPRODUCT(D13:H13, N$30:R$30) -> 2103862.6 | Q13: =J13*0.8*0.87*15 -> 1127520 | R13: =IFERROR(M13+N13-O13-P13-Q13,0) -> 888817.36 | S13: =H13*$R$31 -> 111085.71 | T13: =SUMPRODUCT(D13:H13, N$32:R$32)*0.01 -> 535.17141 | U13: =IFERROR(S13/I13,0) -> 0.1 | V13: =0.1*I13 -> 111085.71 | W13: =SUMPRODUCT($N$31:$Q$31,D13:G13) -> 999771.43 | Y13: =K13-0.1*J13 -> 0
A14: July - Weekend Off-peak | B14: 108 | C14: =B14*1000 -> 108000 | D14: 0 | E14: 0 | F14: 0 | G14: 0 | H14: 0 | I14: =SUMPRODUCT(D14:H14, N$31:R$31) -> 0 | J14: =(SUMPRODUCT(D14:H14, N$31:R$31)*0.35)/3.6 -> 0 | K14: =($R$31*H14*0.35)/3.6 -> 0 | L14: =VLOOKUP(A14,F36:G57,2,FALSE) -> 26.3 | M14: =L14*J14 -> 0 | N14: =45*($R$31*H14*0.35)/3.6 -> 0 | O14: =SUMPRODUCT(D14:H14, N$31:R$31)*0.35*0.65/3.6 -> 0 | P14: =SUMPRODUCT(D14:H14, N$30:R$30) -> 0 | Q14: =J14*0.8*0.87*15 -> 0 | R14: =IFERROR(M14+N14-O14-P14-Q14,0) -> 0 | S14: =H14*$R$31 -> 0 | T14: =SUMPRODUCT(D14:H14, N$32:R$32)*0.01 -> 0 | U14: =IFERROR(S14/I14,0) -> 0 | V14: =0.1*I14 -> 0 | W14: =SUMPRODUCT($N$31:$Q$31,D14:G14) -> 0 | Y14: =K14-0.1*J14 -> 0
A15: August - Weekday Peak | B15: 264 | C15: =B15*1000 -> 264000 | D15: 94687.552 | E15: 0 | F15: 0 | G15: 0 | H15: 15085.714 | I15: =SUMPRODUCT(D15:H15, N$31:R$31) -> 2715428.6 | J15: =(SUMPRODUCT(D15:H15, N$31:R$31)*0.35)/3.6 -> 264000 | K15: =($R$31*H15*0.35)/3.6 -> 26400 | L15: =VLOOKUP(A15,F37:G58,2,FALSE) -> 37.65 | M15: =L15*J15 -> 9939600 | N15: =45*($R$31*H15*0.35)/3.6 -> 1188000 | O15: =SUMPRODUCT(D15:H15, N$31:R$31)*0.35*0.65/3.6 -> 171600 | P15: =SUMPRODUCT(D15:H15, N$30:R$30) -> 5142775.4 | Q15: =J15*0.8*0.87*15 -> 2756160 | R15: =IFERROR(M15+N15-O15-P15-Q15,0) -> 3057064.6 | S15: =H15*$R$31 -> 271542.86 | T15: =SUMPRODUCT(D15:H15, N$32:R$32)*0.01 -> 1308.1968 | U15: =IFERROR(S15/I15,0) -> 0.1 | V15: =0.1*I15 -> 271542.86 | W15: =SUMPRODUCT($N$31:$Q$31,D15:G15) -> 2443885.7 | Y15: =K15-0.1*J15 -> 0
A16: August - Weekday Off-peak | B16: 264 | C16: =B16*1000 -> 264000 | D16: 94687.552 | E16: 0 | F16: 0 | G16: 0 | H16: 15085.714 | I16: =SUMPRODUCT(D16:H16, N$31:R$31) -> 2715428.6 | J16: =(SUMPRODUCT(D16:H16, N$31:R$31)*0.35)/3.6 -> 264000 | K16: =($R$31*H16*0.35)/3.6 -> 26400 | L16: =VLOOKUP(A16,F38:G59,2,FALSE) -> 28.2 | M16: =L16*J16 -> 7444800 | N16: =45*($R$31*H16*0.35)/3.6 -> 1188000 | O16: =SUMPRODUCT(D16:H16, N$31:R$31)*0.35*0.65/3.6 -> 171600 | P16: =SUMPRODUCT(D16:H16, N$30:R$30) -> 5142775.4 | Q16: =J16*0.8*0.87*15 -> 2756160 | R16: =IFERROR(M16+N16-O16-P16-Q16,0) -> 562264.65 | S16: =H16*$R$31 -> 271542.86 | T16: =SUMPRODUCT(D16:H16, N$32:R$32)*0.01 -> 1308.1968 | U16: =IFERROR(S16/I16,0) -> 0.1 | V16: =0.1*I16 -> 271542.86 | W16: =SUMPRODUCT($N$31:$Q$31,D16:G16) -> 2443885.7 | Y16: =K16-0.1*J16 -> 0
A17: August - Weekend Peak | B17: 108 | C17: =B17*1000 -> 108000 | D17: 38735.817 | E17: 0 | F17: 0 | G17: 0 | H17: 6171.4286 | I17: =SUMPRODUCT(D17:H17, N$31:R$31) -> 1110857.1 | J17: =(SUMPRODUCT(D17:H17, N$31:R$31)*0.35)/3.6 -> 108000 | K17: =($R$31*H17*0.35)/3.6 -> 10800 | L17: =VLOOKUP(A17,F39:G60,2,FALSE) -> 35.65 | M17: =L17*J17 -> 3850200 | N17: =45*($R$31*H17*0.35)/3.6 -> 486000 | O17: =SUMPRODUCT(D17:H17, N$31:R$31)*0.35*0.65/3.6 -> 70200 | P17: =SUMPRODUCT(D17:H17, N$30:R$30) -> 2103862.6 | Q17: =J17*0.8*0.87*15 -> 1127520 | R17: =IFERROR(M17+N17-O17-P17-Q17,0) -> 1034617.4 | S17: =H17*$R$31 -> 111085.71 | T17: =SUMPRODUCT(D17:H17, N$32:R$32)*0.01 -> 535.17141 | U17: =IFERROR(S17/I17,0) -> 0.1 | V17: =0.1*I17 -> 111085.71 | W17: =SUMPRODUCT($N$31:$Q$31,D17:G17) -> 999771.43 | Y17: =K17-0.1*J17 -> 0
A18: August - Weekend Off-peak | B18: 108 | C18: =B18*1000 -> 108000 | D18: 38735.817 | E18: 0 | F18: 0 | G18: 0 | H18: 6171.4286 | I18: =SUMPRODUCT(D18:H18, N$31:R$31) -> 1110857.1 | J18: =(SUMPRODUCT(D18:H18, N$31:R$31)*0.35)/3.6 -> 108000 | K18: =($R$31*H18*0.35)/3.6 -> 10800 | L18: =VLOOKUP(A18,F40:G61,2,FALSE) -> 27.5 | M18: =L18*J18 -> 2970000 | N18: =45*($R$31*H18*0.35)/3.6 -> 486000 | O18: =SUMPRODUCT(D18:H18, N$31:R$31)*0.35*0.65/3.6 -> 70200 | P18: =SUMPRODUCT(D18:H18, N$30:R$30) -> 2103862.6 | Q18: =J18*0.8*0.87*15 -> 1127520 | R18: =IFERROR(M18+N18-O18-P18-Q18,0) -> 154417.36 | S18: =H18*$R$31 -> 111085.71 | T18: =SUMPRODUCT(D18:H18, N$32:R$32)*0.01 -> 535.17141 | U18: =IFERROR(S18/I18,0) -> 0.1 | V18: =0.1*I18 -> 111085.71 | W18: =SUMPRODUCT($N$31:$Q$31,D18:G18) -> 999771.43 | Y18: =K18-0.1*J18 -> 0
A19: September - Weekday Peak | B19: 264 | C19: =B19*1000 -> 264000 | D19: 0 | E19: 0 | F19: 0 | G19: 93278.081 | H19: 15085.714 | I19: =SUMPRODUCT(D19:H19, N$31:R$31) -> 2715428.6 | J19: =(SUMPRODUCT(D19:H19, N$31:R$31)*0.35)/3.6 -> 264000 | K19: =($R$31*H19*0.35)/3.6 -> 26400 | L19: =VLOOKUP(A19,F41:G62,2,FALSE) -> 38.35 | M19: =L19*J19 -> 10124400 | N19: =45*($R$31*H19*0.35)/3.6 -> 1188000 | O19: =SUMPRODUCT(D19:H19, N$31:R$31)*0.35*0.65/3.6 -> 171600 | P19: =SUMPRODUCT(D19:H19, N$30:R$30) -> 5030552.5 | Q19: =J19*0.8*0.87*15 -> 2756160 | R19: =IFERROR(M19+N19-O19-P19-Q19,0) -> 3354087.5 | S19: =H19*$R$31 -> 271542.86 | T19: =SUMPRODUCT(D19:H19, N$32:R$32)*0.01 -> 1605.8916 | U19: =IFERROR(S19/I19,0) -> 0.1 | V19: =0.1*I19 -> 271542.86 | W19: =SUMPRODUCT($N$31:$Q$31,D19:G19) -> 2443885.7 | Y19: =K19-0.1*J19 -> 0
... A26: October - Weekend Off-peak | B26: 120 | C26: =B26*1000 -> 120000 | D26: 0 | E26: 0 | F26: 0 | G26: 42399.128 | H26: 6857.1429 | I26: =SUMPRODUCT(D26:H26, N$31:R$31) -> 1234285.7 | J26: =(SUMPRODUCT(D26:H26, N$31:R$31)*0.35)/3.6 -> 120000 | K26: =($R$31*H26*0.35)/3.6 -> 12000 | L26: =VLOOKUP(A26,F48:G69,2,FALSE) -> 30.1 | M26: =L26*J26 -> 3612000 | N26: =45*($R$31*H26*0.35)/3.6 -> 540000 | O26: =SUMPRODUCT(D26:H26, N$31:R$31)*0.35*0.65/3.6 -> 78000 | P26: =SUMPRODUCT(D26:H26, N$30:R$30) -> 2286614.8 | Q26: =J26*0.8*0.87*15 -> 1252800 | R26: =IFERROR(M26+N26-O26-P26-Q26,0) -> 534585.21 | S26: =H26*$R$31 -> 123428.57 | T26: =SUMPRODUCT(D26:H26, N$32:R$32)*0.01 -> 729.95071 | U26: =IFERROR(S26/I26,0) -> 0.1 | V26: =0.1*I26 -> 123428.57 | W26: =SUMPRODUCT($N$31:$Q$31,D26:G26) -> 1110857.1 | Y26: =K26-0.1*J26 -> 0
A27: Total | C27: =SUM(C7:C26) -> 3672000 | D27: =SUM(D7:D26) -> 600000 | E27: =SUM(E7:E26) -> 0 | F27: =SUM(F7:F26) -> 0 | G27: =SUM(G7:G26) -> 517269.36 | H27: =SUM(H7:H26) -> 179249.74 | J27: =SUM(J7:J26) -> 3136870.4 | K27: =SUM(K7:K26) -> 313687.04 | L27: =SUM(L7:L26) -> 650.15 | M27: =SUM(M7:M26) -> 1.065373e+08 | N27: =SUM(N7:N26) -> 14115917 | O27: =SUM(O7:O26) -> 2038965.7 | P27: =SUM(P7:P26) -> 60484566 | Q27: =SUM(Q7:Q26) -> 32748927 | R27: =SUM(R7:R26)-T27*30 -> 24864910 | S27: =SUM(S7:S26) -> 3226495.2 | T27: =SUM(T7:T26) -> 17194.958 | V27: =SUM(V7:V26) -> 3226495.2 | W27: =SUMPRODUCT($N$31:$Q$31,D27:G27) -> 29038457
F29: Period | G29: Electricity_Forward_Price | J29: Scalars | K29: Value | M29: Fuel | N29: Stockpile coal | O29: Colombian coal | P29: Russian coal | Q29: Scottish coal | R29: Wood chips
F30: June - Weekday Peak | G30: 36 | J30: Efficiency | K30: 0.35 | M30: Price_per_t | N30: 42.56 | O30: 43.93 | P30: 43.8 | Q30: 42 | R30: 73.77
F31: June - Weekday Off-peak | G31: 27 | J31: Plant_Capacity_MW | K31: 1000 | M31: CV_GJ_per_t | N31: 25.81 | O31: 25.12 | P31: 24.5 | Q31: 26.2 | R31: 18
F32: June - Weekend Peak | G32: 33.5 | J32: Grid_Charge_per_MWh | K32: 0.65 | M32: SO2_percent | N32: 1.38 | O32: 0.7 | P32: 0.35 | Q32: 1.72 | R32: 0.01
F33: June - Weekend Off-peak | G33: 26.2 | J33: CO2_Intensity_t_per_MWh | K33: 0.8
F34: July - Weekday Peak | G34: 36.35 | J34: CO2_Cost_EUR_per_t | K34: 15
F35: July - Weekday Off-peak | G35: 27 | J35: FX_EUR_per_GBP | K35: 0.87
F36: July - Weekend Peak | G36: 34.3 | J36: ROC_per_MWh | K36: 45
F37: July - Weekend Off-peak | G37: 26.3 | J37: Sulphur_Allowance_t | K37: 9000
F38: August - Weekday Peak | G38: 37.65 | J38: Stockpile_Tonnes | K38: 600000
F39: August - Weekday Off-peak | G39: 28.2 | J39: Biomass_Share_Max | K39: 0.1
F40: August - Weekend Peak | G40: 35.65 | J40: Hours_Peak_per_Day | K40: 12
F41: August - Weekend Off-peak | G41: 27.5 | J41: Hours_Offpeak_per_Day | K41: 12
F42: September - Weekday Peak | G42: 38.35 | J42: P_Colombian_t | K42: 0
F43: September - Weekday Off-peak | G43: 28.5 | J43: P_Russian_t | K43: 0
F44: September - Weekend Peak | G44: 35.8 | J44: P_Scottish_t | K44: 0
F45: September - Weekend Off-peak | G45: 27.65
F46: October - Weekday Peak | G46: 43.7
F47: October - Weekday Off-peak | G47: 31.7
F48: October - Weekend Peak | G48: 38.7
F49: October - Weekend Off-peak | G49: 30.1

Sheet SO2 40£
A6: Month | B6: Hours | C6: Max_Capacity | D6: X_Stockpile_t | E6: X_Colombian_t | F6: X_Russian_t | G6: X_Scottish_t | H6: X_Wood_t | I6: Thermal_Input_GJ | J6: Total_MWh | K6: Wood_Chips_MWh | L6: Price_per MWh | M6: Revenue | N6: ROC_Revenue | O6: Grid_Charge | P6: Fuel_Cost | Q6: CO2_Cost | R6: Profit | S6: Wood_Thermal_GJ | T6: SO2_tonnes | U6: Biomass_share | V6: Thermal_Input_GJ*0.1 | W6: Coal fule | Y6: Wood_Chips_Constraint
A7: June - Weekday Peak | B7: 264 | C7: =B7*1000 -> 264000 | D7: 94687.552 | E7: 0 | F7: 0 | G7: 0 | H7: 15085.714 | I7: =SUMPRODUCT(D7:H7, N$31:R$31) -> 2715428.6 | J7: =(SUMPRODUCT(D7:H7, N$31:R$31)*0.35)/3.6 -> 264000 | K7: =($R$31*H7*0.35)/3.6 -> 26400 | L7: =VLOOKUP(A7,F29:G49,2,FALSE) -> 36 | M7: =L7*J7 -> 9504000 | N7: =45*($R$31*H7*0.35)/3.6 -> 1188000 | O7: =SUMPRODUCT(D7:H7, N$31:R$31)*0.35*0.65/3.6 -> 171600 | P7: =SUMPRODUCT(D7:H7, N$30:R$30) -> 5142775.4 | Q7: =J7*0.8*0.87*15 -> 2756160 | R7: =IFERROR(M7+N7-O7-P7-Q7,0) -> 2621464.6 | S7: =H7*$R$31 -> 271542.86 | T7: =SUMPRODUCT(D7:H7, N$32:R$32)*0.01 -> 1308.1968 | U7: =IFERROR(S7/I7,0) -> 0.1 | V7: =0.1*I7 -> 271542.86 | W7: =SUMPRODUCT($N$31:$Q$31,D7:G7) -> 2443885.7 | Y7: =K7-0.1*J7 -> 0
A8: June - Weekday Off-peak | B8: 264 | C8: =B8*1000 -> 264000 | D8: 0 | E8: 0 | F8: 0 | G8: 0 | H8: 0 | I8: =SUMPRODUCT(D8:H8, N$31:R$31) -> 0 | J8: =(SUMPRODUCT(D8:H8, N$31:R$31)*0.35)/3.6 -> 0 | K8: =($R$31*H8*0.35)/3.6 -> 0 | L8: =VLOOKUP(A8,F30:G51,2,FALSE) -> 27 | M8: =L8*J8 -> 0 | N8: =45*($R$31*H8*0.35)/3.6 -> 0 | O8: =SUMPRODUCT(D8:H8, N$31:R$31)*0.35*0.65/3.6 -> 0 | P8: =SUMPRODUCT(D8:H8, N$30:R$30) -> 0 | Q8: =J8*0.8*0.87*15 -> 0 | R8: =IFERROR(M8+N8-O8-P8-Q8,0) -> 0 | S8: =H8*$R$31 -> 0 | T8: =SUMPRODUCT(D8:H8, N$32:R$32)*0.01 -> 0 | U8: =IFERROR(S8/I8,0) -> 0 | V8: =0.1*I8 -> 0 | W8: =SUMPRODUCT($N$31:$Q$31,D8:G8) -> 0 | Y8: =K8-0.1*J8 -> 0
A9: June - Weekend Peak | B9: 96 | C9: =B9*1000 -> 96000 | D9: 34431.837 | E9: 0 | F9: 0 | G9: 0 | H9: 5485.7143 | I9: =SUMPRODUCT(D9:H9, N$31:R$31) -> 987428.57 | J9: =(SUMPRODUCT(D9:H9, N$31:R$31)*0.35)/3.6 -> 96000 | K9: =($R$31*H9*0.35)/3.6 -> 9600 | L9: =VLOOKUP(A9,F31:G52,2,FALSE) -> 33.5 | M9: =L9*J9 -> 3216000 | N9: =45*($R$31*H9*0.35)/3.6 -> 432000 | O9: =SUMPRODUCT(D9:H9, N$31:R$31)*0.35*0.65/3.6 -> 62400 | P9: =SUMPRODUCT(D9:H9, N$30:R$30) -> 1870100.1 | Q9: =J9*0.8*0.87*15 -> 1002240 | R9: =IFERROR(M9+N9-O9-P9-Q9,0) -> 713259.87 | S9: =H9*$R$31 -> 98742.857 | T9: =SUMPRODUCT(D9:H9, N$32:R$32)*0.01 -> 475.70792 | U9: =IFERROR(S9/I9,0) -> 0.1 | V9: =0.1*I9 -> 98742.857 | W9: =SUMPRODUCT($N$31:$Q$31,D9:G9) -> 888685.71 | Y9: =K9-0.1*J9 -> 0
A10: June - Weekend Off-peak | B10: 96 | C10: =B10*1000 -> 96000 | D10: 0 | E10: 0 | F10: 0 | G10: 0 | H10: 0 | I10: =SUMPRODUCT(D10:H10, N$31:R$31) -> 0 | J10: =(SUMPRODUCT(D10:H10, N$31:R$31)*0.35)/3.6 -> 0 | K10: =($R$31*H10*0.35)/3.6 -> 0 | L10: =VLOOKUP(A10,F32:G53,2,FALSE) -> 26.2 | M10: =L10*J10 -> 0 | N10: =45*($R$31*H10*0.35)/3.6 -> 0 | O10: =SUMPRODUCT(D10:H10, N$31:R$31)*0.35*0.65/3.6 -> 0 | P10: =SUMPRODUCT(D10:H10, N$30:R$30) -> 0 | Q10: =J10*0.8*0.87*15 -> 0 | R10: =IFERROR(M10+N10-O10-P10-Q10,0) -> 0 | S10: =H10*$R$31 -> 0 | T10: =SUMPRODUCT(D10:H10, N$32:R$32)*0.01 -> 0 | U10: =IFERROR(S10/I10,0) -> 0 | V10: =0.1*I10 -> 0 | W10: =SUMPRODUCT($N$31:$Q$31,D10:G10) -> 0 | Y10: =K10-0.1*J10 -> 0
A11: July - Weekday Peak | B11: 264 | C11: =B11*1000 -> 264000 | D11: 94687.552 | E11: 0 | F11: 0 | G11: 0 | H11: 15085.714 | I11: =SUMPRODUCT(D11:H11, N$31:R$31) -> 2715428.6 | J11: =(SUMPRODUCT(D11:H11, N$31:R$31)*0.35)/3.6 -> 264000 | K11: =($R$31*H11*0.35)/3.6 -> 26400 | L11: =VLOOKUP(A11,F33:G54,2,FALSE) -> 36.35 | M11: =L11*J11 -> 9596400 | N11: =45*($R$31*H11*0.35)/3.6 -> 1188000 | O11: =SUMPRODUCT(D11:H11, N$31:R$31)*0.35*0.65/3.6 -> 171600 | P11: =SUMPRODUCT(D11:H11, N$30:R$30) -> 5142775.4 | Q11: =J11*0.8*0.87*15 -> 2756160 | R11: =IFERROR(M11+N11-O11-P11-Q11,0) -> 2713864.6 | S11: =H11*$R$31 -> 271542.86 | T11: =SUMPRODUCT(D11:H11, N$32:R$32)*0.01 -> 1308.1968 | U11: =IFERROR(S11/I11,0) -> 0.1 | V11: =0.1*I11 -> 271542.86 | W11: =SUMPRODUCT($N$31:$Q$31,D11:G11) -> 2443885.7 | Y11: =K11-0.1*J11 -> 0
A12: July - Weekday Off-peak | B12: 264 | C12: =B12*1000 -> 264000 | D12: 70610.505 | E12: 0 | F12: 0 | G12: 0 | H12: 11249.735 | I12: =SUMPRODUCT(D12:H12, N$31:R$31) -> 2024952.4 | J12: =(SUMPRODUCT(D12:H12, N$31:R$31)*0.35)/3.6 -> 196870.37 | K12: =($R$31*H12*0.35)/3.6 -> 19687.037 | L12: =VLOOKUP(A12,F34:G55,2,FALSE) -> 27 | M12: =L12*J12 -> 5315500 | N12: =45*($R$31*H12*0.35)/3.6 -> 885916.67 | O12: =SUMPRODUCT(D12:H12, N$31:R$31)*0.35*0.65/3.6 -> 127965.74 | P12: =SUMPRODUCT(D12:H12, N$30:R$30) -> 3835076.1 | Q12: =J12*0.8*0.87*15 -> 2055326.7 | R12: =IFERROR(M12+N12-O12-P12-Q12,0) -> 183048.17 | S12: =H12*$R$31 -> 202495.24 | T12: =SUMPRODUCT(D12:H12, N$32:R$32)*0.01 -> 975.54995 | U12: =IFERROR(S12/I12,0) -> 0.1 | V12: =0.1*I12 -> 202495.24 | W12: =SUMPRODUCT($N$31:$Q$31,D12:G12) -> 1822457.1 | Y12: =K12-0.1*J12 -> 0
A13: July - Weekend Peak | B13: 108 | C13: =B13*1000 -> 108000 | D13: 38735.817 | E13: 0 | F13: 0 | G13: 0 | H13: 6171.4286 | I13: =SUMPRODUCT(D13:H13, N$31:R$31) -> 1110857.1 | J13: =(SUMPRODUCT(D13:H13, N$31:R$31)*0.35)/3.6 -> 108000 | K13: =($R$31*H13*0.35)/3.6 -> 10800 | L13: =VLOOKUP(A13,F35:G56,2,FALSE) -> 34.3 | M13: =L13*J13 -> 3704400 | N13: =45*($R$31*H13*0.35)/3.6 -> 486000 | O13: =SUMPRODUCT(D13:H13, N$31:R$31)*0.35*0.65/3.6 -> 70200 | P13: =SUMPRODUCT(D13:H13, N$30:R$30) -> 2103862.6 | Q13: =J13*0.8*0.87*15 -> 1127520 | R13: =IFERROR(M13+N13-O13-P13-Q13,0) -> 888817.36 | S13: =H13*$R$31 -> 111085.71 | T13: =SUMPRODUCT(D13:H13, N$32:R$32)*0.01 -> 535.17141 | U13: =IFERROR(S13/I13,0) -> 0.1 | V13: =0.1*I13 -> 111085.71 | W13: =SUMPRODUCT($N$31:$Q$31,D13:G13) -> 999771.43 | Y13: =K13-0.1*J13 -> 0
A14: July - Weekend Off-peak | B14: 108 | C14: =B14*1000 -> 108000 | D14: 0 | E14: 0 | F14: 0 | G14: 0 | H14: 0 | I14: =SUMPRODUCT(D14:H14, N$31:R$31) -> 0 | J14: =(SUMPRODUCT(D14:H14, N$31:R$31)*0.35)/3.6 -> 0 | K14: =($R$31*H14*0.35)/3.6 -> 0 | L14: =VLOOKUP(A14,F36:G57,2,FALSE) -> 26.3 | M14: =L14*J14 -> 0 | N14: =45*($R$31*H14*0.35)/3.6 -> 0 | O14: =SUMPRODUCT(D14:H14, N$31:R$31)*0.35*0.65/3.6 -> 0 | P14: =SUMPRODUCT(D14:H14, N$30:R$30) -> 0 | Q14: =J14*0.8*0.87*15 -> 0 | R14: =IFERROR(M14+N14-O14-P14-Q14,0) -> 0 | S14: =H14*$R$31 -> 0 | T14: =SUMPRODUCT(D14:H14, N$32:R$32)*0.01 -> 0 | U14: =IFERROR(S14/I14,0) -> 0 | V14: =0.1*I14 -> 0 | W14: =SUMPRODUCT($N$31:$Q$31,D14:G14) -> 0 | Y14: =K14-0.1*J14 -> 0
A15: August - Weekday Peak | B15: 264 | C15: =B15*1000 -> 264000 | D15: 94687.552 | E15: 0 | F15: 0 | G15: 0 | H15: 15085.714 | I15: =SUMPRODUCT(D15:H15, N$31:R$31) -> 2715428.6 | J15: =(SUMPRODUCT(D15:H15, N$31:R$31)*0.35)/3.6 -> 264000 | K15: =($R$31*H15*0.35)/3.6 -> 26400 | L15: =VLOOKUP(A15,F37:G58,2,FALSE) -> 37.65 | M15: =L15*J15 -> 9939600 | N15: =45*($R$31*H15*0.35)/3.6 -> 1188000 | O15: =SUMPRODUCT(D15:H15, N$31:R$31)*0.35*0.65/3.6 -> 171600 | P15: =SUMPRODUCT(D15:H15, N$30:R$30) -> 5142775.4 | Q15: =J15*0.8*0.87*15 -> 2756160 | R15: =IFERROR(M15+N15-O15-P15-Q15,0) -> 3057064.6 | S15: =H15*$R$31 -> 271542.86 | T15: =SUMPRODUCT(D15:H15, N$32:R$32)*0.01 -> 1308.1968 | U15: =IFERROR(S15/I15,0) -> 0.1 | V15: =0.1*I15 -> 271542.86 | W15: =SUMPRODUCT($N$31:$Q$31,D15:G15) -> 2443885.7 | Y15: =K15-0.1*J15 -> 0
A16: August - Weekday Off-peak | B16: 264 | C16: =B16*1000 -> 264000 | D16: 94687.552 | E16: 0 | F16: 0 | G16: 0 | H16: 15085.714 | I16: =SUMPRODUCT(D16:H16, N$31:R$31) -> 2715428.6 | J16: =(SUMPRODUCT(D16:H16, N$31:R$31)*0.35)/3.6 -> 264000 | K16: =($R$31*H16*0.35)/3.6 -> 26400 | L16: =VLOOKUP(A16,F38:G59,2,FALSE) -> 28.2 | M16: =L16*J16 -> 7444800 | N16: =45*($R$31*H16*0.35)/3.6 -> 1188000 | O16: =SUMPRODUCT(D16:H16, N$31:R$31)*0.35*0.65/3.6 -> 171600 | P16: =SUMPRODUCT(D16:H16, N$30:R$30) -> 5142775.4 | Q16: =J16*0.8*0.87*15 -> 2756160 | R16: =IFERROR(M16+N16-O16-P16-Q16,0) -> 562264.65 | S16: =H16*$R$31 -> 271542.86 | T16: =SUMPRODUCT(D16:H16, N$32:R$32)*0.01 -> 1308.1968 | U16: =IFERROR(S16/I16,0) -> 0.1 | V16: =0.1*I16 -> 271542.86 | W16: =SUMPRODUCT($N$31:$Q$31,D16:G16) -> 2443885.7 | Y16: =K16-0.1*J16 -> 0
A17: August - Weekend Peak | B17: 108 | C17: =B17*1000 -> 108000 | D17: 38735.817 | E17: 0 | F17: 0 | G17: 0 | H17: 6171.4286 | I17: =SUMPRODUCT(D17:H17, N$31:R$31) -> 1110857.1 | J17: =(SUMPRODUCT(D17:H17, N$31:R$31)*0.35)/3.6 -> 108000 | K17: =($R$31*H17*0.35)/3.6 -> 10800 | L17: =VLOOKUP(A17,F39:G60,2,FALSE) -> 35.65 | M17: =L17*J17 -> 3850200 | N17: =45*($R$31*H17*0.35)/3.6 -> 486000 | O17: =SUMPRODUCT(D17:H17, N$31:R$31)*0.35*0.65/3.6 -> 70200 | P17: =SUMPRODUCT(D17:H17, N$30:R$30) -> 2103862.6 | Q17: =J17*0.8*0.87*15 -> 1127520 | R17: =IFERROR(M17+N17-O17-P17-Q17,0) -> 1034617.4 | S17: =H17*$R$31 -> 111085.71 | T17: =SUMPRODUCT(D17:H17, N$32:R$32)*0.01 -> 535.17141 | U17: =IFERROR(S17/I17,0) -> 0.1 | V17: =0.1*I17 -> 111085.71 | W17: =SUMPRODUCT($N$31:$Q$31,D17:G17) -> 999771.43 | Y17: =K17-0.1*J17 -> 0
A18: August - Weekend Off-peak | B18: 108 | C18: =B18*1000 -> 108000 | D18: 38735.817 | E18: 0 | F18: 0 | G18: 0 | H18: 6171.4286 | I18: =SUMPRODUCT(D18:H18, N$31:R$31) -> 1110857.1 | J18: =(SUMPRODUCT(D18:H18, N$31:R$31)*0.35)/3.6 -> 108000 | K18: =($R$31*H18*0.35)/3.6 -> 10800 | L18: =VLOOKUP(A18,F40:G61,2,FALSE) -> 27.5 | M18: =L18*J18 -> 2970000 | N18: =45*($R$31*H18*0.35)/3.6 -> 486000 | O18: =SUMPRODUCT(D18:H18, N$31:R$31)*0.35*0.65/3.6 -> 70200 | P18: =SUMPRODUCT(D18:H18, N$30:R$30) -> 2103862.6 | Q18: =J18*0.8*0.87*15 -> 1127520 | R18: =IFERROR(M18+N18-O18-P18-Q18,0) -> 154417.36 | S18: =H18*$R$31 -> 111085.71 | T18: =SUMPRODUCT(D18:H18, N$32:R$32)*0.01 -> 535.17141 | U18: =IFERROR(S18/I18,0) -> 0.1 | V18: =0.1*I18 -> 111085.71 | W18: =SUMPRODUCT($N$31:$Q$31,D18:G18) -> 999771.43 | Y18: =K18-0.1*J18 -> 0
A19: September - Weekday Peak | B19: 264 | C19: =B19*1000 -> 264000 | D19: 0 | E19: 0 | F19: 0 | G19: 93278.081 | H19: 15085.714 | I19: =SUMPRODUCT(D19:H19, N$31:R$31) -> 2715428.6 | J19: =(SUMPRODUCT(D19:H19, N$31:R$31)*0.35)/3.6 -> 264000 | K19: =($R$31*H19*0.35)/3.6 -> 26400 | L19: =VLOOKUP(A19,F41:G62,2,FALSE) -> 38.35 | M19: =L19*J19 -> 10124400 | N19: =45*($R$31*H19*0.35)/3.6 -> 1188000 | O19: =SUMPRODUCT(D19:H19, N$31:R$31)*0.35*0.65/3.6 -> 171600 | P19: =SUMPRODUCT(D19:H19, N$30:R$30) -> 5030552.5 | Q19: =J19*0.8*0.87*15 -> 2756160 | R19: =IFERROR(M19+N19-O19-P19-Q19,0) -> 3354087.5 | S19: =H19*$R$31 -> 271542.86 | T19: =SUMPRODUCT(D19:H19, N$32:R$32)*0.01 -> 1605.8916 | U19: =IFERROR(S19/I19,0) -> 0.1 | V19: =0.1*I19 -> 271542.86 | W19: =SUMPRODUCT($N$31:$Q$31,D19:G19) -> 2443885.7 | Y19: =K19-0.1*J19 -> 0
... A26: October - Weekend Off-peak | B26: 120 | C26: =B26*1000 -> 120000 | D26: 0 | E26: 0 | F26: 0 | G26: 42399.128 | H26: 6857.1429 | I26: =SUMPRODUCT(D26:H26, N$31:R$31) -> 1234285.7 | J26: =(SUMPRODUCT(D26:H26, N$31:R$31)*0.35)/3.6 -> 120000 | K26: =($R$31*H26*0.35)/3.6 -> 12000 | L26: =VLOOKUP(A26,F48:G69,2,FALSE) -> 30.1 | M26: =L26*J26 -> 3612000 | N26: =45*($R$31*H26*0.35)/3.6 -> 540000 | O26: =SUMPRODUCT(D26:H26, N$31:R$31)*0.35*0.65/3.6 -> 78000 | P26: =SUMPRODUCT(D26:H26, N$30:R$30) -> 2286614.8 | Q26: =J26*0.8*0.87*15 -> 1252800 | R26: =IFERROR(M26+N26-O26-P26-Q26,0) -> 534585.21 | S26: =H26*$R$31 -> 123428.57 | T26: =SUMPRODUCT(D26:H26, N$32:R$32)*0.01 -> 729.95071 | U26: =IFERROR(S26/I26,0) -> 0.1 | V26: =0.1*I26 -> 123428.57 | W26: =SUMPRODUCT($N$31:$Q$31,D26:G26) -> 1110857.1 | Y26: =K26-0.1*J26 -> 0
A27: Total | C27: =SUM(C7:C26) -> 3672000 | D27: =SUM(D7:D26) -> 600000 | E27: =SUM(E7:E26) -> 0 | F27: =SUM(F7:F26) -> 0 | G27: =SUM(G7:G26) -> 517269.36 | H27: =SUM(H7:H26) -> 179249.74 | J27: =SUM(J7:J26) -> 3136870.4 | K27: =SUM(K7:K26) -> 313687.04 | L27: =SUM(L7:L26) -> 650.15 | M27: =SUM(M7:M26) -> 1.065373e+08 | N27: =SUM(N7:N26) -> 14115917 | O27: =SUM(O7:O26) -> 2038965.7 | P27: =SUM(P7:P26) -> 60484566 | Q27: =SUM(Q7:Q26) -> 32748927 | R27: =SUM(R7:R26)-T27*40 -> 24692960 | S27: =SUM(S7:S26) -> 3226495.2 | T27: =SUM(T7:T26) -> 17194.958 | V27: =SUM(V7:V26) -> 3226495.2 | W27: =SUMPRODUCT($N$31:$Q$31,D27:G27) -> 29038457
F29: Period | G29: Electricity_Forward_Price | J29: Scalars | K29: Value | M29: Fuel | N29: Stockpile coal | O29: Colombian coal | P29: Russian coal | Q29: Scottish coal | R29: Wood chips
F30: June - Weekday Peak | G30: 36 | J30: Efficiency | K30: 0.35 | M30: Price_per_t | N30: 42.56 | O30: 43.93 | P30: 43.8 | Q30: 42 | R30: 73.77
F31: June - Weekday Off-peak | G31: 27 | J31: Plant_Capacity_MW | K31: 1000 | M31: CV_GJ_per_t | N31: 25.81 | O31: 25.12 | P31: 24.5 | Q31: 26.2 | R31: 18
F32: June - Weekend Peak | G32: 33.5 | J32: Grid_Charge_per_MWh | K32: 0.65 | M32: SO2_percent | N32: 1.38 | O32: 0.7 | P32: 0.35 | Q32: 1.72 | R32: 0.01
F33: June - Weekend Off-peak | G33: 26.2 | J33: CO2_Intensity_t_per_MWh | K33: 0.8
F34: July - Weekday Peak | G34: 36.35 | J34: CO2_Cost_EUR_per_t | K34: 15
F35: July - Weekday Off-peak | G35: 27 | J35: FX_EUR_per_GBP | K35: 0.87
F36: July - Weekend Peak | G36: 34.3 | J36: ROC_per_MWh | K36: 45
F37: July - Weekend Off-peak | G37: 26.3 | J37: Sulphur_Allowance_t | K37: 9000
F38: August - Weekday Peak | G38: 37.65 | J38: Stockpile_Tonnes | K38: 600000
F39: August - Weekday Off-peak | G39: 28.2 | J39: Biomass_Share_Max | K39: 0.1
F40: August - Weekend Peak | G40: 35.65 | J40: Hours_Peak_per_Day | K40: 12
F41: August - Weekend Off-peak | G41: 27.5 | J41: Hours_Offpeak_per_Day | K41: 12
F42: September - Weekday Peak | G42: 38.35 | J42: P_Colombian_t | K42: 0
F43: September - Weekday Off-peak | G43: 28.5 | J43: P_Russian_t | K43: 0
F44: September - Weekend Peak | G44: 35.8 | J44: P_Scottish_t | K44: 0
F45: September - Weekend Off-peak | G45: 27.65
F46: October - Weekday Peak | G46: 43.7
F47: October - Weekday Off-peak | G47: 31.7
F48: October - Weekend Peak | G48: 38.7
F49: October - Weekend Off-peak | G49: 30.1

Sheet SO2 50£
A6: Month | B6: Hours | C6: Max_Capacity | D6: X_Stockpile_t | E6: X_Colombian_t | F6: X_Russian_t | G6: X_Scottish_t | H6: X_Wood_t | I6: Thermal_Input_GJ | J6: Total_MWh | K6: Wood_Chips_MWh | L6: Price_per MWh | M6: Revenue | N6: ROC_Revenue | O6: Grid_Charge | P6: Fuel_Cost | Q6: CO2_Cost | R6: Profit | S6: Wood_Thermal_GJ | T6: SO2_tonnes | U6: Biomass_share | V6: Thermal_Input_GJ*0.1 | W6: Coal fule | Y6: Wood_Chips_Constraint
A7: June - Weekday Peak | B7: 264 | C7: =B7*1000 -> 264000 | D7: 94687.552 | E7: 0 | F7: 0 | G7: 0 | H7: 15085.714 | I7: =SUMPRODUCT(D7:H7, N$31:R$31) -> 2715428.6 | J7: =(SUMPRODUCT(D7:H7, N$31:R$31)*0.35)/3.6 -> 264000 | K7: =($R$31*H7*0.35)/3.6 -> 26400 | L7: =VLOOKUP(A7,F29:G49,2,FALSE) -> 36 | M7: =L7*J7 -> 9504000 | N7: =45*($R$31*H7*0.35)/3.6 -> 1188000 | O7: =SUMPRODUCT(D7:H7, N$31:R$31)*0.35*0.65/3.6 -> 171600 | P7: =SUMPRODUCT(D7:H7, N$30:R$30) -> 5142775.4 | Q7: =J7*0.8*0.87*15 -> 2756160 | R7: =IFERROR(M7+N7-O7-P7-Q7,0) -> 2621464.6 | S7: =H7*$R$31 -> 271542.86 | T7: =SUMPRODUCT(D7:H7, N$32:R$32)*0.01 -> 1308.1968 | U7: =IFERROR(S7/I7,0) -> 0.1 | V7: =0.1*I7 -> 271542.86 | W7: =SUMPRODUCT($N$31:$Q$31,D7:G7) -> 2443885.7 | Y7: =K7-0.1*J7 -> 0
A8: June - Weekday Off-peak | B8: 264 | C8: =B8*1000 -> 264000 | D8: 0 | E8: 0 | F8: 0 | G8: 0 | H8: 0 | I8: =SUMPRODUCT(D8:H8, N$31:R$31) -> 0 | J8: =(SUMPRODUCT(D8:H8, N$31:R$31)*0.35)/3.6 -> 0 | K8: =($R$31*H8*0.35)/3.6 -> 0 | L8: =VLOOKUP(A8,F30:G51,2,FALSE) -> 27 | M8: =L8*J8 -> 0 | N8: =45*($R$31*H8*0.35)/3.6 -> 0 | O8: =SUMPRODUCT(D8:H8, N$31:R$31)*0.35*0.65/3.6 -> 0 | P8: =SUMPRODUCT(D8:H8, N$30:R$30) -> 0 | Q8: =J8*0.8*0.87*15 -> 0 | R8: =IFERROR(M8+N8-O8-P8-Q8,0) -> 0 | S8: =H8*$R$31 -> 0 | T8: =SUMPRODUCT(D8:H8, N$32:R$32)*0.01 -> 0 | U8: =IFERROR(S8/I8,0) -> 0 | V8: =0.1*I8 -> 0 | W8: =SUMPRODUCT($N$31:$Q$31,D8:G8) -> 0 | Y8: =K8-0.1*J8 -> 0
A9: June - Weekend Peak | B9: 96 | C9: =B9*1000 -> 96000 | D9: 34431.837 | E9: 0 | F9: 0 | G9: 0 | H9: 5485.7143 | I9: =SUMPRODUCT(D9:H9, N$31:R$31) -> 987428.57 | J9: =(SUMPRODUCT(D9:H9, N$31:R$31)*0.35)/3.6 -> 96000 | K9: =($R$31*H9*0.35)/3.6 -> 9600 | L9: =VLOOKUP(A9,F31:G52,2,FALSE) -> 33.5 | M9: =L9*J9 -> 3216000 | N9: =45*($R$31*H9*0.35)/3.6 -> 432000 | O9: =SUMPRODUCT(D9:H9, N$31:R$31)*0.35*0.65/3.6 -> 62400 | P9: =SUMPRODUCT(D9:H9, N$30:R$30) -> 1870100.1 | Q9: =J9*0.8*0.87*15 -> 1002240 | R9: =IFERROR(M9+N9-O9-P9-Q9,0) -> 713259.87 | S9: =H9*$R$31 -> 98742.857 | T9: =SUMPRODUCT(D9:H9, N$32:R$32)*0.01 -> 475.70792 | U9: =IFERROR(S9/I9,0) -> 0.1 | V9: =0.1*I9 -> 98742.857 | W9: =SUMPRODUCT($N$31:$Q$31,D9:G9) -> 888685.71 | Y9: =K9-0.1*J9 -> 0
A10: June - Weekend Off-peak | B10: 96 | C10: =B10*1000 -> 96000 | D10: 0 | E10: 0 | F10: 0 | G10: 0 | H10: 0 | I10: =SUMPRODUCT(D10:H10, N$31:R$31) -> 0 | J10: =(SUMPRODUCT(D10:H10, N$31:R$31)*0.35)/3.6 -> 0 | K10: =($R$31*H10*0.35)/3.6 -> 0 | L10: =VLOOKUP(A10,F32:G53,2,FALSE) -> 26.2 | M10: =L10*J10 -> 0 | N10: =45*($R$31*H10*0.35)/3.6 -> 0 | O10: =SUMPRODUCT(D10:H10, N$31:R$31)*0.35*0.65/3.6 -> 0 | P10: =SUMPRODUCT(D10:H10, N$30:R$30) -> 0 | Q10: =J10*0.8*0.87*15 -> 0 | R10: =IFERROR(M10+N10-O10-P10-Q10,0) -> 0 | S10: =H10*$R$31 -> 0 | T10: =SUMPRODUCT(D10:H10, N$32:R$32)*0.01 -> 0 | U10: =IFERROR(S10/I10,0) -> 0 | V10: =0.1*I10 -> 0 | W10: =SUMPRODUCT($N$31:$Q$31,D10:G10) -> 0 | Y10: =K10-0.1*J10 -> 0
A11: July - Weekday Peak | B11: 264 | C11: =B11*1000 -> 264000 | D11: 94687.552 | E11: 0 | F11: 0 | G11: 0 | H11: 15085.714 | I11: =SUMPRODUCT(D11:H11, N$31:R$31) -> 2715428.6 | J11: =(SUMPRODUCT(D11:H11, N$31:R$31)*0.35)/3.6 -> 264000 | K11: =($R$31*H11*0.35)/3.6 -> 26400 | L11: =VLOOKUP(A11,F33:G54,2,FALSE) -> 36.35 | M11: =L11*J11 -> 9596400 | N11: =45*($R$31*H11*0.35)/3.6 -> 1188000 | O11: =SUMPRODUCT(D11:H11, N$31:R$31)*0.35*0.65/3.6 -> 171600 | P11: =SUMPRODUCT(D11:H11, N$30:R$30) -> 5142775.4 | Q11: =J11*0.8*0.87*15 -> 2756160 | R11: =IFERROR(M11+N11-O11-P11-Q11,0) -> 2713864.6 | S11: =H11*$R$31 -> 271542.86 | T11: =SUMPRODUCT(D11:H11, N$32:R$32)*0.01 -> 1308.1968 | U11: =IFERROR(S11/I11,0) -> 0.1 | V11: =0.1*I11 -> 271542.86 | W11: =SUMPRODUCT($N$31:$Q$31,D11:G11) -> 2443885.7 | Y11: =K11-0.1*J11 -> 0
A12: July - Weekday Off-peak | B12: 264 | C12: =B12*1000 -> 264000 | D12: 70610.505 | E12: 0 | F12: 0 | G12: 0 | H12: 11249.735 | I12: =SUMPRODUCT(D12:H12, N$31:R$31) -> 2024952.4 | J12: =(SUMPRODUCT(D12:H12, N$31:R$31)*0.35)/3.6 -> 196870.37 | K12: =($R$31*H12*0.35)/3.6 -> 19687.037 | L12: =VLOOKUP(A12,F34:G55,2,FALSE) -> 27 | M12: =L12*J12 -> 5315500 | N12: =45*($R$31*H12*0.35)/3.6 -> 885916.67 | O12: =SUMPRODUCT(D12:H12, N$31:R$31)*0.35*0.65/3.6 -> 127965.74 | P12: =SUMPRODUCT(D12:H12, N$30:R$30) -> 3835076.1 | Q12: =J12*0.8*0.87*15 -> 2055326.7 | R12: =IFERROR(M12+N12-O12-P12-Q12,0) -> 183048.17 | S12: =H12*$R$31 -> 202495.24 | T12: =SUMPRODUCT(D12:H12, N$32:R$32)*0.01 -> 975.54995 | U12: =IFERROR(S12/I12,0) -> 0.1 | V12: =0.1*I12 -> 202495.24 | W12: =SUMPRODUCT($N$31:$Q$31,D12:G12) -> 1822457.1 | Y12: =K12-0.1*J12 -> 0
A13: July - Weekend Peak | B13: 108 | C13: =B13*1000 -> 108000 | D13: 38735.817 | E13: 0 | F13: 0 | G13: 0 | H13: 6171.4286 | I13: =SUMPRODUCT(D13:H13, N$31:R$31) -> 1110857.1 | J13: =(SUMPRODUCT(D13:H13, N$31:R$31)*0.35)/3.6 -> 108000 | K13: =($R$31*H13*0.35)/3.6 -> 10800 | L13: =VLOOKUP(A13,F35:G56,2,FALSE) -> 34.3 | M13: =L13*J13 -> 3704400 | N13: =45*($R$31*H13*0.35)/3.6 -> 486000 | O13: =SUMPRODUCT(D13:H13, N$31:R$31)*0.35*0.65/3.6 -> 70200 | P13: =SUMPRODUCT(D13:H13, N$30:R$30) -> 2103862.6 | Q13: =J13*0.8*0.87*15 -> 1127520 | R13: =IFERROR(M13+N13-O13-P13-Q13,0) -> 888817.36 | S13: =H13*$R$31 -> 111085.71 | T13: =SUMPRODUCT(D13:H13, N$32:R$32)*0.01 -> 535.17141 | U13: =IFERROR(S13/I13,0) -> 0.1 | V13: =0.1*I13 -> 111085.71 | W13: =SUMPRODUCT($N$31:$Q$31,D13:G13) -> 999771.43 | Y13: =K13-0.1*J13 -> 0
A14: July - Weekend Off-peak | B14: 108 | C14: =B14*1000 -> 108000 | D14: 0 | E14: 0 | F14: 0 | G14: 0 | H14: 0 | I14: =SUMPRODUCT(D14:H14, N$31:R$31) -> 0 | J14: =(SUMPRODUCT(D14:H14, N$31:R$31)*0.35)/3.6 -> 0 | K14: =($R$31*H14*0.35)/3.6 -> 0 | L14: =VLOOKUP(A14,F36:G57,2,FALSE) -> 26.3 | M14: =L14*J14 -> 0 | N14: =45*($R$31*H14*0.35)/3.6 -> 0 | O14: =SUMPRODUCT(D14:H14, N$31:R$31)*0.35*0.65/3.6 -> 0 | P14: =SUMPRODUCT(D14:H14, N$30:R$30) -> 0 | Q14: =J14*0.8*0.87*15 -> 0 | R14: =IFERROR(M14+N14-O14-P14-Q14,0) -> 0 | S14: =H14*$R$31 -> 0 | T14: =SUMPRODUCT(D14:H14, N$32:R$32)*0.01 -> 0 | U14: =IFERROR(S14/I14,0) -> 0 | V14: =0.1*I14 -> 0 | W14: =SUMPRODUCT($N$31:$Q$31,D14:G14) -> 0 | Y14: =K14-0.1*J14 -> 0
A15: August - Weekday Peak | B15: 264 | C15: =B15*1000 -> 264000 | D15: 94687.552 | E15: 0 | F15: 0 | G15: 0 | H15: 15085.714 | I15: =SUMPRODUCT(D15:H15, N$31:R$31) -> 2715428.6 | J15: =(SUMPRODUCT(D15:H15, N$31:R$31)*0.35)/3.6 -> 264000 | K15: =($R$31*H15*0.35)/3.6 -> 26400 | L15: =VLOOKUP(A15,F37:G58,2,FALSE) -> 37.65 | M15: =L15*J15 -> 9939600 | N15: =45*($R$31*H15*0.35)/3.6 -> 1188000 | O15: =SUMPRODUCT(D15:H15, N$31:R$31)*0.35*0.65/3.6 -> 171600 | P15: =SUMPRODUCT(D15:H15, N$30:R$30) -> 5142775.4 | Q15: =J15*0.8*0.87*15 -> 2756160 | R15: =IFERROR(M15+N15-O15-P15-Q15,0) -> 3057064.6 | S15: =H15*$R$31 -> 271542.86 | T15: =SUMPRODUCT(D15:H15, N$32:R$32)*0.01 -> 1308.1968 | U15: =IFERROR(S15/I15,0) -> 0.1 | V15: =0.1*I15 -> 271542.86 | W15: =SUMPRODUCT($N$31:$Q$31,D15:G15) -> 2443885.7 | Y15: =K15-0.1*J15 -> 0
A16: August - Weekday Off-peak | B16: 264 | C16: =B16*1000 -> 264000 | D16: 94687.552 | E16: 0 | F16: 0 | G16: 0 | H16: 15085.714 | I16: =SUMPRODUCT(D16:H16, N$31:R$31) -> 2715428.6 | J16: =(SUMPRODUCT(D16:H16, N$31:R$31)*0.35)/3.6 -> 264000 | K16: =($R$31*H16*0.35)/3.6 -> 26400 | L16: =VLOOKUP(A16,F38:G59,2,FALSE) -> 28.2 | M16: =L16*J16 -> 7444800 | N16: =45*($R$31*H16*0.35)/3.6 -> 1188000 | O16: =SUMPRODUCT(D16:H16, N$31:R$31)*0.35*0.65/3.6 -> 171600 | P16: =SUMPRODUCT(D16:H16, N$30:R$30) -> 5142775.4 | Q16: =J16*0.8*0.87*15 -> 2756160 | R16: =IFERROR(M16+N16-O16-P16-Q16,0) -> 562264.65 | S16: =H16*$R$31 -> 271542.86 | T16: =SUMPRODUCT(D16:H16, N$32:R$32)*0.01 -> 1308.1968 | U16: =IFERROR(S16/I16,0) -> 0.1 | V16: =0.1*I16 -> 271542.86 | W16: =SUMPRODUCT($N$31:$Q$31,D16:G16) -> 2443885.7 | Y16: =K16-0.1*J16 -> 0
A17: August - Weekend Peak | B17: 108 | C17: =B17*1000 -> 108000 | D17: 38735.817 | E17: 0 | F17: 0 | G17: 0 | H17: 6171.4286 | I17: =SUMPRODUCT(D17:H17, N$31:R$31) -> 1110857.1 | J17: =(SUMPRODUCT(D17:H17, N$31:R$31)*0.35)/3.6 -> 108000 | K17: =($R$31*H17*0.35)/3.6 -> 10800 | L17: =VLOOKUP(A17,F39:G60,2,FALSE) -> 35.65 | M17: =L17*J17 -> 3850200 | N17: =45*($R$31*H17*0.35)/3.6 -> 486000 | O17: =SUMPRODUCT(D17:H17, N$31:R$31)*0.35*0.65/3.6 -> 70200 | P17: =SUMPRODUCT(D17:H17, N$30:R$30) -> 2103862.6 | Q17: =J17*0.8*0.87*15 -> 1127520 | R17: =IFERROR(M17+N17-O17-P17-Q17,0) -> 1034617.4 | S17: =H17*$R$31 -> 111085.71 | T17: =SUMPRODUCT(D17:H17, N$32:R$32)*0.01 -> 535.17141 | U17: =IFERROR(S17/I17,0) -> 0.1 | V17: =0.1*I17 -> 111085.71 | W17: =SUMPRODUCT($N$31:$Q$31,D17:G17) -> 999771.43 | Y17: =K17-0.1*J17 -> 0
A18: August - Weekend Off-peak | B18: 108 | C18: =B18*1000 -> 108000 | D18: 38735.817 | E18: 0 | F18: 0 | G18: 0 | H18: 6171.4286 | I18: =SUMPRODUCT(D18:H18, N$31:R$31) -> 1110857.1 | J18: =(SUMPRODUCT(D18:H18, N$31:R$31)*0.35)/3.6 -> 108000 | K18: =($R$31*H18*0.35)/3.6 -> 10800 | L18: =VLOOKUP(A18,F40:G61,2,FALSE) -> 27.5 | M18: =L18*J18 -> 2970000 | N18: =45*($R$31*H18*0.35)/3.6 -> 486000 | O18: =SUMPRODUCT(D18:H18, N$31:R$31)*0.35*0.65/3.6 -> 70200 | P18: =SUMPRODUCT(D18:H18, N$30:R$30) -> 2103862.6 | Q18: =J18*0.8*0.87*15 -> 1127520 | R18: =IFERROR(M18+N18-O18-P18-Q18,0) -> 154417.36 | S18: =H18*$R$31 -> 111085.71 | T18: =SUMPRODUCT(D18:H18, N$32:R$32)*0.01 -> 535.17141 | U18: =IFERROR(S18/I18,0) -> 0.1 | V18: =0.1*I18 -> 111085.71 | W18: =SUMPRODUCT($N$31:$Q$31,D18:G18) -> 999771.43 | Y18: =K18-0.1*J18 -> 0
A19: September - Weekday Peak | B19: 264 | C19: =B19*1000 -> 264000 | D19: 0 | E19: 0 | F19: 0 | G19: 93278.081 | H19: 15085.714 | I19: =SUMPRODUCT(D19:H19, N$31:R$31) -> 2715428.6 | J19: =(SUMPRODUCT(D19:H19, N$31:R$31)*0.35)/3.6 -> 264000 | K19: =($R$31*H19*0.35)/3.6 -> 26400 | L19: =VLOOKUP(A19,F41:G62,2,FALSE) -> 38.35 | M19: =L19*J19 -> 10124400 | N19: =45*($R$31*H19*0.35)/3.6 -> 1188000 | O19: =SUMPRODUCT(D19:H19, N$31:R$31)*0.35*0.65/3.6 -> 171600 | P19: =SUMPRODUCT(D19:H19, N$30:R$30) -> 5030552.5 | Q19: =J19*0.8*0.87*15 -> 2756160 | R19: =IFERROR(M19+N19-O19-P19-Q19,0) -> 3354087.5 | S19: =H19*$R$31 -> 271542.86 | T19: =SUMPRODUCT(D19:H19, N$32:R$32)*0.01 -> 1605.8916 | U19: =IFERROR(S19/I19,0) -> 0.1 | V19: =0.1*I19 -> 271542.86 | W19: =SUMPRODUCT($N$31:$Q$31,D19:G19) -> 2443885.7 | Y19: =K19-0.1*J19 -> 0
... A26: October - Weekend Off-peak | B26: 120 | C26: =B26*1000 -> 120000 | D26: 0 | E26: 0 | F26: 0 | G26: 42399.128 | H26: 6857.1429 | I26: =SUMPRODUCT(D26:H26, N$31:R$31) -> 1234285.7 | J26: =(SUMPRODUCT(D26:H26, N$31:R$31)*0.35)/3.6 -> 120000 | K26: =($R$31*H26*0.35)/3.6 -> 12000 | L26: =VLOOKUP(A26,F48:G69,2,FALSE) -> 30.1 | M26: =L26*J26 -> 3612000 | N26: =45*($R$31*H26*0.35)/3.6 -> 540000 | O26: =SUMPRODUCT(D26:H26, N$31:R$31)*0.35*0.65/3.6 -> 78000 | P26: =SUMPRODUCT(D26:H26, N$30:R$30) -> 2286614.8 | Q26: =J26*0.8*0.87*15 -> 1252800 | R26: =IFERROR(M26+N26-O26-P26-Q26,0) -> 534585.21 | S26: =H26*$R$31 -> 123428.57 | T26: =SUMPRODUCT(D26:H26, N$32:R$32)*0.01 -> 729.95071 | U26: =IFERROR(S26/I26,0) -> 0.1 | V26: =0.1*I26 -> 123428.57 | W26: =SUMPRODUCT($N$31:$Q$31,D26:G26) -> 1110857.1 | Y26: =K26-0.1*J26 -> 0
A27: Total | C27: =SUM(C7:C26) -> 3672000 | D27: =SUM(D7:D26) -> 600000 | E27: =SUM(E7:E26) -> 0 | F27: =SUM(F7:F26) -> 0 | G27: =SUM(G7:G26) -> 517269.36 | H27: =SUM(H7:H26) -> 179249.74 | J27: =SUM(J7:J26) -> 3136870.4 | K27: =SUM(K7:K26) -> 313687.04 | L27: =SUM(L7:L26) -> 650.15 | M27: =SUM(M7:M26) -> 1.065373e+08 | N27: =SUM(N7:N26) -> 14115917 | O27: =SUM(O7:O26) -> 2038965.7 | P27: =SUM(P7:P26) -> 60484566 | Q27: =SUM(Q7:Q26) -> 32748927 | R27: =SUM(R7:R26)-T27*50 -> 24521010 | S27: =SUM(S7:S26) -> 3226495.2 | T27: =SUM(T7:T26) -> 17194.958 | V27: =SUM(V7:V26) -> 3226495.2 | W27: =SUMPRODUCT($N$31:$Q$31,D27:G27) -> 29038457
F29: Period | G29: Electricity_Forward_Price | J29: Scalars | K29: Value | M29: Fuel | N29: Stockpile coal | O29: Colombian coal | P29: Russian coal | Q29: Scottish coal | R29: Wood chips
F30: June - Weekday Peak | G30: 36 | J30: Efficiency | K30: 0.35 | M30: Price_per_t | N30: 42.56 | O30: 43.93 | P30: 43.8 | Q30: 42 | R30: 73.77
F31: June - Weekday Off-peak | G31: 27 | J31: Plant_Capacity_MW | K31: 1000 | M31: CV_GJ_per_t | N31: 25.81 | O31: 25.12 | P31: 24.5 | Q31: 26.2 | R31: 18
F32: June - Weekend Peak | G32: 33.5 | J32: Grid_Charge_per_MWh | K32: 0.65 | M32: SO2_percent | N32: 1.38 | O32: 0.7 | P32: 0.35 | Q32: 1.72 | R32: 0.01
F33: June - Weekend Off-peak | G33: 26.2 | J33: CO2_Intensity_t_per_MWh | K33: 0.8
F34: July - Weekday Peak | G34: 36.35 | J34: CO2_Cost_EUR_per_t | K34: 15
F35: July - Weekday Off-peak | G35: 27 | J35: FX_EUR_per_GBP | K35: 0.87
F36: July - Weekend Peak | G36: 34.3 | J36: ROC_per_MWh | K36: 45
F37: July - Weekend Off-peak | G37: 26.3 | J37: Sulphur_Allowance_t | K37: 9000
F38: August - Weekday Peak | G38: 37.65 | J38: Stockpile_Tonnes | K38: 600000
F39: August - Weekday Off-peak | G39: 28.2 | J39: Biomass_Share_Max | K39: 0.1
F40: August - Weekend Peak | G40: 35.65 | J40: Hours_Peak_per_Day | K40: 12
F41: August - Weekend Off-peak | G41: 27.5 | J41: Hours_Offpeak_per_Day | K41: 12
F42: September - Weekday Peak | G42: 38.35 | J42: P_Colombian_t | K42: 0
F43: September - Weekday Off-peak | G43: 28.5 | J43: P_Russian_t | K43: 0
F44: September - Weekend Peak | G44: 35.8 | J44: P_Scottish_t | K44: 0
F45: September - Weekend Off-peak | G45: 27.65
F46: October - Weekday Peak | G46: 43.7
F47: October - Weekday Off-peak | G47: 31.7
F48: October - Weekend Peak | G48: 38.7
F49: October - Weekend Off-peak | G49: 30.1

Sheet FGD wet limstone
A1: The Fuel Buying Decision
A4: Variables | G4: Period
A5: Amount of fuel burned | B5: Stockpile | C5: Columbian | D5: Russian | E5: Scottish | F5: Wood chips | G5: Hours in each period
A6: June- WD-Peak | B6: 93306.543 | C6: 0 | D6: 0 | E6: 0 | F6: 14865.691 | G6: =12*22 -> 264 | H6: June
A7: June-WD-Off-peak | B7: 0 | C7: 0 | D7: 0 | E7: 0 | F7: 0 | G7: =12*22 -> 264
A8: June-WK-Peak | B8: 37699.607 | C8: 0 | D8: 0 | E8: 0 | F8: 0 | G8: =12*8 -> 96
A9: June-WK-Off-peak | B9: 0 | C9: 0 | D9: 0 | E9: 0 | F9: 0 | G9: =12*8 -> 96
A10: July-WD-Peak | B10: 103723.41 | C10: 0 | D10: 0 | E10: 0 | F10: 0 | G10: =22*12 -> 264 | H10: July
A11: July-WD-Off-peak | B11: 0 | C11: 0 | D11: 0 | E11: 0 | F11: 0 | G11: =12*22 -> 264
A12: July-WK-Peak | B12: 42432.305 | C12: 0 | D12: 0 | E12: 0 | F12: 0 | G12: =12*9 -> 108
A13: July-WK-Off-peak | B13: 0 | C13: 0 | D13: 0 | E13: 0 | F13: 0 | G13: =12*9 -> 108
A14: Aug-WD-Peak | B14: 103723.41 | C14: 0 | D14: 0 | E14: 0 | F14: 0 | G14: =12*22 -> 264 | H14: August
A15: Aug-WD-Off-peak | B15: 103723.41 | C15: 0 | D15: 0 | E15: 0 | F15: 0 | G15: =12*22 -> 264
A16: Aug-WK-Peak | B16: 42432.305 | C16: 0 | D16: 0 | E16: 0 | F16: 0 | G16: =12*9 -> 108
A17: Aug-WK-Off-peak | B17: 0 | C17: 0 | D17: 0 | E17: 0 | F17: 0 | G17: =12*9 -> 108
A18: Sept-WD-Peak | B18: 0 | C18: 0 | D18: 0 | E18: 102130.95 | F18: 0 | G18: =12*22 -> 264 | H18: September
A19: Sept-WD-Off-peak | B19: 0 | C19: 0 | D19: 0 | E19: 102130.95 | F19: 0 | G19: =12*22 -> 264
A20: Sept-WK-Peak | B20: 0 | C20: 0 | D20: 0 | E20: 37138.527 | F20: 0 | G20: =12*8 -> 96
A21: Sept-WK-Off-peak | B21: 0 | C21: 0 | D21: 0 | E21: 37138.527 | F21: 0 | G21: =12*8 -> 96
A22: Oct-WD-Peak | B22: 0 | C22: 0 | D22: 0 | E22: 97535.175 | F22: 0 | G22: =21*12 -> 252 | H22: October
A23: Oct-WD-Off-peak | B23: 0 | C23: 0 | D23: 0 | E23: 97535.175 | F23: 0 | G23: =21*12 -> 252
A24: Oct-WK-Peak | B24: 0 | C24: 0 | D24: 0 | E24: 46445.321 | F24: 0 | G24: =12*10 -> 120
A25: Oct-WK-Off-peak | B25: 0 | C25: 0 | D25: 0 | E25: 46445.321 | F25: 0 | G25: =12*10 -> 120
A26: Total | B26: =SUM(B6:B25) -> 527040.99 | C26: =SUM(C6:C25) -> 0 | D26: =SUM(D6:D25) -> 0 | E26: =SUM(E6:E25) -> 566499.95 | F26: =SUM(F6:F25) -> 14865.691
R34: Period | S34: Unit | T34: June | U34: July | V34: August | W34: September | X34: October
R35: Weekday Peak | S35: £ per MWh | T35: 36 | U35: 36.35 | V35: 37.65 | W35: 38.35 | X35: 43.7
R36: Weekday Off-peak | S36: £ per MWh | T36: 27 | U36: 27 | V36: 28.2 | W36: 28.5 | X36: 31.7
I37: Yearly cost for installation | J37: SO2 Profit | K37: Final Profit | R37: Weekend Peak | S37: £ per MWh | T37: 33.5 | U37: 34.3 | V37: 35.65 | W37: 35.8 | X37: 38.7
A38: Profit | G38: Total | H38: =SUMPRODUCT($B$6:$F$25,$B$40:$F$59) -> 19740170 | I38: 877240.42 | J38: =G92*30 -> 25527.677 | K38: =H38+J38-I38 -> 18888458 | L38: Scenario 1: SO2 : 30 euro/ton | R38: Weekend Off-peak | S38: £ per MWh | T38: 26.2 | U38: 26.3 | V38: 27.5 | W38: 27.65 | X38: 30.1
B39: Stock | C39: Col | D39: Rus | E39: Sco | F39: Wood Chips (Bio) | J39: =G92*40 -> 34036.903 | K39: =H38+J39-I38 -> 18896967 | L39: Scenario 2: SO2 : 40 euro/ton
A40: June weekday peak | B40: 19.946801 | C40: 16.905756 | D40: 15.534236 | E40: 21.451306 | F40: 48.5725 | H40: June | J40: =G92*50 -> 42546.128 | K40: =H38+J40-I38 -> 18905476 | L40: Scenario 3: SO2 : 50 euro/ton
A41: June weekday off-peak | B41: -2.6369486 | C41: -5.0742444 | D41: -5.9032639 | E41: -1.4736944 | F41: 32.8225
A42: June weekend peak | B42: 13.673538 | C42: 10.8002 | D42: 9.579375 | E42: 15.08325 | F42: 44.1975
A43: June weekend off-peak | B43: -4.6443931 | C43: -7.0280222 | D43: -7.8088194 | E43: -3.5114722 | F43: 31.4225
A44: July weekday peak | B44: 20.825058 | C44: 17.760533 | D44: 16.367917 | E44: 22.342833 | F44: 49.185 | H44: July
A45: July weekday off-peak | B45: -2.6369486 | C45: -5.0742444 | D45: -5.9032639 | E45: -1.4736944 | F45: 32.8225
A46: July weekend peak | B46: 15.680982 | C46: 12.753978 | D46: 11.484931 | E46: 17.121028 | F46: 45.5975
A47: July weekend off-peak | B47: -4.3934625 | C47: -6.7838 | D47: -7.570625 | E47: -3.25675 | F47: 31.5975
A48: August weekday peak | B48: 24.087156 | C48: 20.935422 | D48: 19.464444 | E48: 25.654222 | F48: 51.46 | H48: August
A49: August weekday off-peak | B49: 0.37421806 | C49: -2.1435778 | D49: -3.0449306 | E49: 1.5829722 | F49: 34.9225
A50: August weekend peak | B50: 19.068544 | C50: 16.050978 | D50: 14.700556 | E50: 20.559778 | F50: 47.96
A51: August weekend off-peak | B51: -1.3822958 | C51: -3.8531333 | D51: -4.7122917 | E51: -0.20008333 | F51: 33.6975
A52: September weekday peak | B52: 25.843669 | C52: 22.644978 | D52: 21.131806 | E52: 27.437278 | F52: 52.685 | H52: September
A53: September weekday off-peak | B53: 1.1270097 | C53: -1.4109111 | D53: -2.3303472 | E53: 2.3471389 | F53: 35.4475
A54: September weekend peak | B54: 19.44494 | C54: 16.417311 | D54: 15.057847 | E54: 20.941861 | F54: 48.2225
A55: September weekend off-peak | B55: -1.0059 | C55: -3.4868 | D55: -4.355 | E55: 0.182 | F55: 33.96
A56: October weekday peak | B56: 39.268454 | C56: 35.710867 | D56: 33.875208 | E56: 41.064917 | F56: 62.0475 | H56: October
A57: October weekday off-peak | B57: 9.1567875 | C57: 6.4042 | D57: 5.291875 | E57: 10.49825 | F57: 41.0475
A58: October weekend peak | B58: 26.721926 | C58: 23.499756 | D58: 21.965486 | E58: 28.328806 | F58: 53.2975
A59: October weekend off-peak | B59: 5.1418986 | C59: 2.4966444 | D59: 1.4807639 | E59: 6.4226944 | F59: 38.2475
A70: Constraints | G70: Total(LHS) | I70: Available(RHS) | K70: meaning
A72: Biomass(Calorific value) | B72: 25.81 | C72: 25.12 | D72: 24.5 | E72: 26.2 | F72: 18 | G72: =$F$72*$F$26 -> 267582.43 | H72: <= | I72: =0.1*SUMPRODUCT($B$72:$F$72,B6:F6) -> 267582.43
B73: 25.81 | C73: 25.12 | D73: 24.5 | E73: 26.2 | F73: 18 | G73: =$F$72*F7 -> 0 | I73: =0.1*SUMPRODUCT($B$72:$F$72,B7:F7) -> 0
B74: 25.81 | C74: 25.12 | D74: 24.5 | E74: 26.2 | F74: 18 | G74: =$F$72*F8 -> 0 | I74: =0.1*SUMPRODUCT($B$72:$F$72,B8:F8) -> 97302.685
B75: 25.81 | C75: 25.12 | D75: 24.5 | E75: 26.2 | F75: 18 | G75: =$F$72*F9 -> 0 | I75: =0.1*SUMPRODUCT($B$72:$F$72,B9:F9) -> 0
B76: 25.81 | C76: 25.12 | D76: 24.5 | E76: 26.2 | F76: 18 | G76: =$F$72*F10 -> 0 | I76: =0.1*SUMPRODUCT($B$72:$F$72,B10:F10) -> 267710.12
B77: 25.81 | C77: 25.12 | D77: 24.5 | E77: 26.2 | F77: 18 | G77: =$F$72*F11 -> 0 | I77: =0.1*SUMPRODUCT($B$72:$F$72,B11:F11) -> 0
B78: 25.81 | C78: 25.12 | D78: 24.5 | E78: 26.2 | F78: 18 | G78: =$F$72*F12 -> 0 | I78: =0.1*SUMPRODUCT($B$72:$F$72,B12:F12) -> 109517.78
B79: 25.81 | C79: 25.12 | D79: 24.5 | E79: 26.2 | F79: 18 | G79: =$F$72*F13 -> 0 | I79: =0.1*SUMPRODUCT($B$72:$F$72,B13:F13) -> 0
B80: 25.81 | C80: 25.12 | D80: 24.5 | E80: 26.2 | F80: 18 | G80: =$F$72*F14 -> 0 | I80: =0.1*SUMPRODUCT($B$72:$F$72,B14:F14) -> 267710.12
B81: 25.81 | C81: 25.12 | D81: 24.5 | E81: 26.2 | F81: 18 | G81: =$F$72*F15 -> 0 | I81: =0.1*SUMPRODUCT($B$72:$F$72,B15:F15) -> 267710.12
B82: 25.81 | C82: 25.12 | D82: 24.5 | E82: 26.2 | F82: 18 | G82: =$F$72*F16 -> 0 | I82: =0.1*SUMPRODUCT($B$72:$F$72,B16:F16) -> 109517.78
B83: 25.81 | C83: 25.12 | D83: 24.5 | E83: 26.2 | F83: 18 | G83: =$F$72*F17 -> 0 | I83: =0.1*SUMPRODUCT($B$72:$F$72,B17:F17) -> 0
B84: 25.81 | C84: 25.12 | D84: 24.5 | E84: 26.2 | F84: 18 | G84: =$F$72*F18 -> 0 | I84: =0.1*SUMPRODUCT($B$72:$F$72,B18:F18) -> 267583.09
... B91: 25.81 | C91: 25.12 | D91: 24.5 | E91: 26.2 | F91: 18 | G91: =$F$72*F25 -> 0 | I91: =0.1*SUMPRODUCT($B$72:$F$72,B25:F25) -> 121686.74
A92: SO2 | B92: 0.00069 | C92: 0.00035 | D92: 0.000175 | E92: 0.00086 | F92: 5e-06 | G92: =SUMPRODUCT($B$92:$F$92,$B$26:$F$26) -> 850.92257 | H92: <= | I92: 9000
A93: Stock | G93: =$B$26 -> 527040.99 | H93: <= | I93: 600000
A94: Non-negativity
A95: zero for certain period | H95: = | I95: 0 | K95: 1000*Hp(number of hours) | L95: minus electricity for FGD result | N95: percentage
A96: Period capacity | B96: 2.50931 | C96: 2.44222 | D96: 2.38194 | E96: 2.54722 | F96: 1.75 | G96: =SUMPRODUCT($B$96:$F$96,B6:F6) -> 260150 | H96: <= | I96: =12*22 -> 264 | J96: 1000 | K96: =I96*$J$96 -> 264000 | L96: =K96-10.5*1000*N96 -> 260150 | N96: =I96/SUM($I$96:$I$99) -> 0.36666667
B97: 2.50931 | C97: 2.44222 | D97: 2.38194 | E97: 2.54722 | F97: 1.75 | G97: =SUMPRODUCT($B$96:$F$96,B7:F7) -> 0 | H97: <= | I97: =12*22 -> 264 | K97: =I97*$J$96 -> 264000 | L97: =K97-10.5*1000*N97 -> 260150 | N97: =I97/SUM($I$96:$I$99) -> 0.36666667
B98: 2.50931 | C98: 2.44222 | D98: 2.38194 | E98: 2.54722 | F98: 1.75 | G98: =SUMPRODUCT($B$96:$F$96,B8:F8) -> 94600 | H98: <= | I98: =12*8 -> 96 | K98: =I98*$J$96 -> 96000 | L98: =K98-10.5*1000*N98 -> 94600 | N98: =I98/SUM($I$96:$I$99) -> 0.13333333
B99: 2.50931 | C99: 2.44222 | D99: 2.38194 | E99: 2.54722 | F99: 1.75 | G99: =SUMPRODUCT($B$96:$F$96,B9:F9) -> 0 | H99: <= | I99: =12*8 -> 96 | K99: =I99*$J$96 -> 96000 | L99: =K99-10.5*1000*N99 -> 94600 | N99: =I99/SUM($I$96:$I$99) -> 0.13333333
B100: 2.50931 | C100: 2.44222 | D100: 2.38194 | E100: 2.54722 | F100: 1.75 | G100: =SUMPRODUCT($B$96:$F$96,B10:F10) -> 260274.19 | H100: <= | I100: =22*12 -> 264 | K100: =I100*$J$96 -> 264000 | L100: =K100-10.5*1000*N100 -> 260274.19 | N100: =I100/SUM($I$100:$I$103) -> 0.35483871
B101: 2.50931 | C101: 2.44222 | D101: 2.38194 | E101: 2.54722 | F101: 1.75 | G101: =SUMPRODUCT($B$96:$F$96,B11:F11) -> 0 | H101: <= | I101: =12*22 -> 264 | K101: =I101*$J$96 -> 264000 | L101: =K101-10.5*1000*N101 -> 260274.19 | N101: =I101/SUM($I$100:$I$103) -> 0.35483871
B102: 2.50931 | C102: 2.44222 | D102: 2.38194 | E102: 2.54722 | F102: 1.75 | G102: =SUMPRODUCT($B$96:$F$96,B12:F12) -> 106475.81 | H102: <= | I102: =12*9 -> 108 | K102: =I102*$J$96 -> 108000 | L102: =K102-10.5*1000*N102 -> 106475.81 | N102: =I102/SUM($I$100:$I$103) -> 0.14516129
B103: 2.50931 | C103: 2.44222 | D103: 2.38194 | E103: 2.54722 | F103: 1.75 | G103: =SUMPRODUCT($B$96:$F$96,B13:F13) -> 0 | H103: <= | I103: =12*9 -> 108 | K103: =I103*$J$96 -> 108000 | L103: =K103-10.5*1000*N103 -> 106475.81 | N103: =I103/SUM($I$100:$I$103) -> 0.14516129
B104: 2.50931 | C104: 2.44222 | D104: 2.38194 | E104: 2.54722 | F104: 1.75 | G104: =SUMPRODUCT($B$96:$F$96,B14:F14) -> 260274.19 | H104: <= | I104: =12*22 -> 264 | K104: =I104*$J$96 -> 264000 | L104: =K104-10.5*1000*N104 -> 260274.19 | N104: =I104/SUM($I$104:$I$107) -> 0.35483871
B105: 2.50931 | C105: 2.44222 | D105: 2.38194 | E105: 2.54722 | F105: 1.75 | G105: =SUMPRODUCT($B$96:$F$96,B15:F15) -> 260274.19 | H105: <= | I105: =12*22 -> 264 | K105: =I105*$J$96 -> 264000 | L105: =K105-10.5*1000*N105 -> 260274.19 | N105: =I105/SUM($I$104:$I$107) -> 0.35483871
B106: 2.50931 | C106: 2.44222 | D106: 2.38194 | E106: 2.54722 | F106: 1.75 | G106: =SUMPRODUCT($B$96:$F$96,B16:F16) -> 106475.81 | H106: <= | I106: =12*9 -> 108 | K106: =I106*$J$96 -> 108000 | L106: =K106-10.5*1000*N106 -> 106475.81 | N106: =I106/SUM($I$104:$I$107) -> 0.14516129
B107: 2.50931 | C107: 2.44222 | D107: 2.38194 | E107: 2.54722 | F107: 1.75 | G107: =SUMPRODUCT($B$96:$F$96,B17:F17) -> 0 | H107: <= | I107: =12*9 -> 108 | K107: =I107*$J$96 -> 108000 | L107: =K107-10.5*1000*N107 -> 106475.81 | N107: =I107/SUM($I$104:$I$107) -> 0.14516129
B108: 2.50931 | C108: 2.44222 | D108: 2.38194 | E108: 2.54722 | F108: 1.75 | G108: =SUMPRODUCT($B$96:$F$96,B18:F18) -> 260150 | H108: <= | I108: =12*22 -> 264 | K108: =I108*$J$96 -> 264000 | L108: =K108-10.5*1000*N108 -> 260150 | N108: =I108/SUM($I$108:$I$111) -> 0.36666667
B109: 2.50931 | C109: 2.44222 | D109: 2.38194 | E109: 2.54722 | F109: 1.75 | G109: =SUMPRODUCT($B$96:$F$96,B19:F19) -> 260150 | H109: <= | I109: =12*22 -> 264 | K109: =I109*$J$96 -> 264000 | L109: =K109-10.5*1000*N109 -> 260150 | N109: =I109/SUM($I$108:$I$111) -> 0.36666667
B110: 2.50931 | C110: 2.44222 | D110: 2.38194 | E110: 2.54722 | F110: 1.75 | G110: =SUMPRODUCT($B$96:$F$96,B20:F20) -> 94600 | H110: <= | I110: =12*8 -> 96 | K110: =I110*$J$96 -> 96000 | L110: =K110-10.5*1000*N110 -> 94600 | N110: =I110/SUM($I$108:$I$111) -> 0.13333333
B111: 2.50931 | C111: 2.44222 | D111: 2.38194 | E111: 2.54722 | F111: 1.75 | G111: =SUMPRODUCT($B$96:$F$96,B21:F21) -> 94600 | H111: <= | I111: =12*8 -> 96 | K111: =I111*$J$96 -> 96000 | L111: =K111-10.5*1000*N111 -> 94600 | N111: =I111/SUM($I$108:$I$111) -> 0.13333333
B112: 2.50931 | C112: 2.44222 | D112: 2.38194 | E112: 2.54722 | F112: 1.75 | G112: =SUMPRODUCT($B$96:$F$96,B22:F22) -> 248443.55 | H112: <= | I112: =21*12 -> 252 | K112: =I112*$J$96 -> 252000 | L112: =K112-10.5*1000*N112 -> 248443.55 | N112: =I112/SUM($I$112:$I$115) -> 0.33870968
B113: 2.50931 | C113: 2.44222 | D113: 2.38194 | E113: 2.54722 | F113: 1.75 | G113: =SUMPRODUCT($B$96:$F$96,B23:F23) -> 248443.55 | H113: <= | I113: =21*12 -> 252 | K113: =I113*$J$96 -> 252000 | L113: =K113-10.5*1000*N113 -> 248443.55 | N113: =I113/SUM($I$112:$I$115) -> 0.33870968
B114: 2.50931 | C114: 2.44222 | D114: 2.38194 | E114: 2.54722 | F114: 1.75 | G114: =SUMPRODUCT($B$96:$F$96,B24:F24) -> 118306.45 | H114: <= | I114: =12*10 -> 120 | K114: =I114*$J$96 -> 120000 | L114: =K114-10.5*1000*N114 -> 118306.45 | N114: =I114/SUM($I$112:$I$115) -> 0.16129032
B115: 2.50931 | C115: 2.44222 | D115: 2.38194 | E115: 2.54722 | F115: 1.75 | G115: =SUMPRODUCT($B$96:$F$96,B25:F25) -> 118306.45 | H115: <= | I115: =12*10 -> 120 | K115: =I115*$J$96 -> 120000 | L115: =K115-10.5*1000*N115 -> 118306.45 | N115: =I115/SUM($I$112:$I$115) -> 0.16129032

Sheet period for FGD wet limstone
A1: Electricity in each month | B1: Stock | C1: Col | D1: Rus | E1: Sco | F1: Wood Chips (Bio)
A2: Period | B2: Profit per ton | C2: Profit per ton | D2: Profit per ton | E2: Profit per ton | F2: Profit per ton | G2: Hours in each period
A3: June weekday peak | B3: =(L19-$K$6-$K$7*$K$8*$K$9)*$L$28-$H$46 -> 19.946801 | C3: =(L19-$K$6-$K$7*$K$8*$K$9)*$L$29-$H$47 -> 16.905756 | D3: =(L19-$K$6-$K$7*$K$8*$K$9)*$L$30-$H$48 -> 15.534236 | E3: =(L19-$K$6-$K$7*$K$8*$K$9)*$L$31-$H$49 -> 21.451306 | F3: =(L19-$K$6-$K$7*$K$8*$K$9+$K$10)*$L$32-$H$50 -> 48.5725 | G3: =12*22 -> 264 | J3: Scalars | K3: Value
A4: June weekday off-peak | B4: =(L20-$K$6-$K$7*$K$8*$K$9)*$L$28-$H$46 -> -2.6369486 | C4: =(L20-$K$6-$K$7*$K$8*$K$9)*$L$29-$H$47 -> -5.0742444 | D4: =(L20-$K$6-$K$7*$K$8*$K$9)*$L$30-$H$48 -> -5.9032639 | E4: =(L20-$K$6-$K$7*$K$8*$K$9)*$L$31-$H$49 -> -1.4736944 | F4: =(L20-$K$6-$K$7*$K$8*$K$9+$K$10)*$L$32-$H$50 -> 32.8225 | G4: =12*22 -> 264 | J4: Efficiency | K4: 0.35
A5: June weekend peak | B5: =(L21-$K$6-$K$7*$K$8*$K$9)*$L$28-$H$46 -> 13.673538 | C5: =(L21-$K$6-$K$7*$K$8*$K$9)*$L$29-$H$47 -> 10.8002 | D5: =(L21-$K$6-$K$7*$K$8*$K$9)*$L$30-$H$48 -> 9.579375 | E5: =(L21-$K$6-$K$7*$K$8*$K$9)*$L$31-$H$49 -> 15.08325 | F5: =(L21-$K$6-$K$7*$K$8*$K$9+$K$10)*$L$32-$H$50 -> 44.1975 | G5: =12*8 -> 96 | J5: Plant_Capacity_MW | K5: 1000
A6: June weekend off-peak | B6: =(L22-$K$6-$K$7*$K$8*$K$9)*$L$28-$H$46 -> -4.6443931 | C6: =(L22-$K$6-$K$7*$K$8*$K$9)*$L$29-$H$47 -> -7.0280222 | D6: =(L22-$K$6-$K$7*$K$8*$K$9)*$L$30-$H$48 -> -7.8088194 | E6: =(L22-$K$6-$K$7*$K$8*$K$9)*$L$31-$H$49 -> -3.5114722 | F6: =(L22-$K$6-$K$7*$K$8*$K$9+$K$10)*$L$32-$H$50 -> 31.4225 | G6: =12*8 -> 96 | J6: Grid_Charge_per_MWh | K6: 0.65
A7: July weekday peak | B7: =(M19-$K$6-$K$7*$K$8*$K$9)*$L$28-$H$46 -> 20.825058 | C7: =(M19-$K$6-$K$7*$K$8*$K$9)*$L$29-$H$47 -> 17.760533 | D7: =(M19-$K$6-$K$7*$K$8*$K$9)*$L$30-$H$48 -> 16.367917 | E7: =(M19-$K$6-$K$7*$K$8*$K$9)*$L$31-$H$49 -> 22.342833 | F7: =(M19-$K$6-$K$7*$K$8*$K$9+$K$10)*$L$32-$H$50 -> 49.185 | G7: =22*12 -> 264 | J7: CO2_Intensity_t_per_MWh | K7: 0.8
A8: July weekday off-peak | B8: =(M20-$K$6-$K$7*$K$8*$K$9)*$L$28-$H$46 -> -2.6369486 | C8: =(M20-$K$6-$K$7*$K$8*$K$9)*$L$29-$H$47 -> -5.0742444 | D8: =(M20-$K$6-$K$7*$K$8*$K$9)*$L$30-$H$48 -> -5.9032639 | E8: =(M20-$K$6-$K$7*$K$8*$K$9)*$L$31-$H$49 -> -1.4736944 | F8: =(M20-$K$6-$K$7*$K$8*$K$9+$K$10)*$L$32-$H$50 -> 32.8225 | G8: =12*22 -> 264 | J8: CO2_Cost_EUR_per_t | K8: 15
A9: July weekend peak | B9: =(M21-$K$6-$K$7*$K$8*$K$9)*$L$28-$H$46 -> 15.680982 | C9: =(M21-$K$6-$K$7*$K$8*$K$9)*$L$29-$H$47 -> 12.753978 | D9: =(M21-$K$6-$K$7*$K$8*$K$9)*$L$30-$H$48 -> 11.484931 | E9: =(M21-$K$6-$K$7*$K$8*$K$9)*$L$31-$H$49 -> 17.121028 | F9: =(M21-$K$6-$K$7*$K$8*$K$9+$K$10)*$L$32-$H$50 -> 45.5975 | G9: =12*9 -> 108 | J9: FX_EUR_per_GBP | K9: 0.87
A10: July weekend off-peak | B10: =(M22-$K$6-$K$7*$K$8*$K$9)*$L$28-$H$46 -> -4.3934625 | C10: =(M22-$K$6-$K$7*$K$8*$K$9)*$L$29-$H$47 -> -6.7838 | D10: =(M22-$K$6-$K$7*$K$8*$K$9)*$L$30-$H$48 -> -7.570625 | E10: =(M22-$K$6-$K$7*$K$8*$K$9)*$L$31-$H$49 -> -3.25675 | F10: =(M22-$K$6-$K$7*$K$8*$K$9+$K$10)*$L$32-$H$50 -> 31.5975 | G10: =12*9 -> 108 | J10: ROC_per_MWh | K10: 45
A11: August weekday peak | B11: =(N19-$K$6-$K$7*$K$8*$K$9)*$L$28-$H$46 -> 24.087156 | C11: =(N19-$K$6-$K$7*$K$8*$K$9)*$L$29-$H$47 -> 20.935422 | D11: =(N19-$K$6-$K$7*$K$8*$K$9)*$L$30-$H$48 -> 19.464444 | E11: =(N19-$K$6-$K$7*$K$8*$K$9)*$L$31-$H$49 -> 25.654222 | F11: =(N19-$K$6-$K$7*$K$8*$K$9+$K$10)*$L$32-$H$50 -> 51.46 | G11: =12*22 -> 264 | J11: Sulphur_Allowance_t | K11: 9000
A12: August weekday off-peak | B12: =(N20-$K$6-$K$7*$K$8*$K$9)*$L$28-$H$46 -> 0.37421806 | C12: =(N20-$K$6-$K$7*$K$8*$K$9)*$L$29-$H$47 -> -2.1435778 | D12: =(N20-$K$6-$K$7*$K$8*$K$9)*$L$30-$H$48 -> -3.0449306 | E12: =(N20-$K$6-$K$7*$K$8*$K$9)*$L$31-$H$49 -> 1.5829722 | F12: =(N20-$K$6-$K$7*$K$8*$K$9+$K$10)*$L$32-$H$50 -> 34.9225 | G12: =12*22 -> 264 | J12: Stockpile_Tonnes | K12: 600000
A13: August weekend peak | B13: =(N21-$K$6-$K$7*$K$8*$K$9)*$L$28-$H$46 -> 19.068544 | C13: =(N21-$K$6-$K$7*$K$8*$K$9)*$L$29-$H$47 -> 16.050978 | D13: =(N21-$K$6-$K$7*$K$8*$K$9)*$L$30-$H$48 -> 14.700556 | E13: =(N21-$K$6-$K$7*$K$8*$K$9)*$L$31-$H$49 -> 20.559778 | F13: =(N21-$K$6-$K$7*$K$8*$K$9+$K$10)*$L$32-$H$50 -> 47.96 | G13: =12*9 -> 108 | J13: Biomass_Share_Max | K13: 0.1
A14: August weekend off-peak | B14: =(N22-$K$6-$K$7*$K$8*$K$9)*$L$28-$H$46 -> -1.3822958 | C14: =(N22-$K$6-$K$7*$K$8*$K$9)*$L$29-$H$47 -> -3.8531333 | D14: =(N22-$K$6-$K$7*$K$8*$K$9)*$L$30-$H$48 -> -4.7122917 | E14: =(N22-$K$6-$K$7*$K$8*$K$9)*$L$31-$H$49 -> -0.20008333 | F14: =(N22-$K$6-$K$7*$K$8*$K$9+$K$10)*$L$32-$H$50 -> 33.6975 | G14: =12*9 -> 108 | J14: Hours_Peak_per_Day | K14: 12
A15: September weekday peak | B15: =(O19-$K$6-$K$7*$K$8*$K$9)*$L$28-$H$46 -> 25.843669 | C15: =(O19-$K$6-$K$7*$K$8*$K$9)*$L$29-$H$47 -> 22.644978 | D15: =(O19-$K$6-$K$7*$K$8*$K$9)*$L$30-$H$48 -> 21.131806 | E15: =(O19-$K$6-$K$7*$K$8*$K$9)*$L$31-$H$49 -> 27.437278 | F15: =(O19-$K$6-$K$7*$K$8*$K$9+$K$10)*$L$32-$H$50 -> 52.685 | G15: =12*22 -> 264 | J15: Hours_Offpeak_per_Day | K15: 12
A16: September weekday off-peak | B16: =(O20-$K$6-$K$7*$K$8*$K$9)*$L$28-$H$46 -> 1.1270097 | C16: =(O20-$K$6-$K$7*$K$8*$K$9)*$L$29-$H$47 -> -1.4109111 | D16: =(O20-$K$6-$K$7*$K$8*$K$9)*$L$30-$H$48 -> -2.3303472 | E16: =(O20-$K$6-$K$7*$K$8*$K$9)*$L$31-$H$49 -> 2.3471389 | F16: =(O20-$K$6-$K$7*$K$8*$K$9+$K$10)*$L$32-$H$50 -> 35.4475 | G16: =12*22 -> 264
A17: September weekend peak | B17: =(O21-$K$6-$K$7*$K$8*$K$9)*$L$28-$H$46 -> 19.44494 | C17: =(O21-$K$6-$K$7*$K$8*$K$9)*$L$29-$H$47 -> 16.417311 | D17: =(O21-$K$6-$K$7*$K$8*$K$9)*$L$30-$H$48 -> 15.057847 | E17: =(O21-$K$6-$K$7*$K$8*$K$9)*$L$31-$H$49 -> 20.941861 | F17: =(O21-$K$6-$K$7*$K$8*$K$9+$K$10)*$L$32-$H$50 -> 48.2225 | G17: =12*8 -> 96
A18: September weekend off-peak | B18: =(O22-$K$6-$K$7*$K$8*$K$9)*$L$28-$H$46 -> -1.0059 | C18: =(O22-$K$6-$K$7*$K$8*$K$9)*$L$29-$H$47 -> -3.4868 | D18: =(O22-$K$6-$K$7*$K$8*$K$9)*$L$30-$H$48 -> -4.355 | E18: =(O22-$K$6-$K$7*$K$8*$K$9)*$L$31-$H$49 -> 0.182 | F18: =(O22-$K$6-$K$7*$K$8*$K$9+$K$10)*$L$32-$H$50 -> 33.96 | G18: =12*8 -> 96 | J18: Period | K18: Unit | L18: June | M18: July | N18: August | O18: September | P18: October
A19: October weekday peak | B19: =(P19-$K$6-$K$7*$K$8*$K$9)*$L$28-$H$46 -> 39.268454 | C19: =(P19-$K$6-$K$7*$K$8*$K$9)*$L$29-$H$47 -> 35.710867 | D19: =(P19-$K$6-$K$7*$K$8*$K$9)*$L$30-$H$48 -> 33.875208 | E19: =(P19-$K$6-$K$7*$K$8*$K$9)*$L$31-$H$49 -> 41.064917 | F19: =(P19-$K$6-$K$7*$K$8*$K$9+$K$10)*$L$32-$H$50 -> 62.0475 | G19: =21*12 -> 252 | J19: Weekday Peak | K19: £ per MWh | L19: 36 | M19: 36.35 | N19: 37.65 | O19: 38.35 | P19: 43.7
A20: October weekday off-peak | B20: =(P20-$K$6-$K$7*$K$8*$K$9)*$L$28-$H$46 -> 9.1567875 | C20: =(P20-$K$6-$K$7*$K$8*$K$9)*$L$29-$H$47 -> 6.4042 | D20: =(P20-$K$6-$K$7*$K$8*$K$9)*$L$30-$H$48 -> 5.291875 | E20: =(P20-$K$6-$K$7*$K$8*$K$9)*$L$31-$H$49 -> 10.49825 | F20: =(P20-$K$6-$K$7*$K$8*$K$9+$K$10)*$L$32-$H$50 -> 41.0475 | G20: =21*12 -> 252 | J20: Weekday Off-peak | K20: £ per MWh | L20: 27 | M20: 27 | N20: 28.2 | O20: 28.5 | P20: 31.7
A21: October weekend peak | B21: =(P21-$K$6-$K$7*$K$8*$K$9)*$L$28-$H$46 -> 26.721926 | C21: =(P21-$K$6-$K$7*$K$8*$K$9)*$L$29-$H$47 -> 23.499756 | D21: =(P21-$K$6-$K$7*$K$8*$K$9)*$L$30-$H$48 -> 21.965486 | E21: =(P21-$K$6-$K$7*$K$8*$K$9)*$L$31-$H$49 -> 28.328806 | F21: =(P21-$K$6-$K$7*$K$8*$K$9+$K$10)*$L$32-$H$50 -> 53.2975 | G21: =12*10 -> 120 | J21: Weekend Peak | K21: £ per MWh | L21: 33.5 | M21: 34.3 | N21: 35.65 | O21: 35.8 | P21: 38.7
A22: October weekend off-peak | B22: =(P22-$K$6-$K$7*$K$8*$K$9)*$L$28-$H$46 -> 5.1418986 | C22: =(P22-$K$6-$K$7*$K$8*$K$9)*$L$29-$H$47 -> 2.4966444 | D22: =(P22-$K$6-$K$7*$K$8*$K$9)*$L$30-$H$48 -> 1.4807639 | E22: =(P22-$K$6-$K$7*$K$8*$K$9)*$L$31-$H$49 -> 6.4226944 | F22: =(P22-$K$6-$K$7*$K$8*$K$9+$K$10)*$L$32-$H$50 -> 38.2475 | G22: =12*10 -> 120 | J22: Weekend Off-peak | K22: £ per MWh | L22: 26.2 | M22: 26.3 | N22: 27.5 | O22: 27.65 | P22: 30.1
I26: Fuel | J26: Qf (GJ/t) | K26: #VALUE!
I28: Stock | J28: 25.81 | K28: 2.50931 | L28: =J28*0.35/3.6 -> 2.5093056
I29: Col | J29: 25.12 | K29: 2.44222 | L29: =J29*0.35/3.6 -> 2.4422222
I30: Rus | J30: 24.5 | K30: 2.38194 | L30: =J30*0.35/3.6 -> 2.3819444
I31: Sco | J31: 26.2 | K31: 2.54722 | L31: =J31*0.35/3.6 -> 2.5472222
I32: Bio | J32: 18 | K32: 1.75 | L32: =J32*0.35/3.6 -> 1.75
I36: SO2 Rating
I37: Fuel | J37: Sf (%) | K37: t SO₂ / t fuel | L37: FGD1
I38: Stock | J38: 1.38 | K38: 0.0138 | L38: =K38*(1-95%) -> 0.00069
I39: Col | J39: 0.7 | K39: 0.007 | L39: =K39*(1-95%) -> 0.00035
I40: Rus | J40: 0.35 | K40: 0.0035 | L40: =K40*(1-95%) -> 0.000175
I41: Sco | J41: 1.72 | K41: 0.0172 | L41: =K41*(1-95%) -> 0.00086
I42: Bio | J42: 0.01 | K42: 0.0001 | L42: =K42*(1-95%) -> 5e-06
G45: Fuel | H45: Price (£/tonne) | I45: Calorific value (GJ/tonne) | J45: SO2 (%)
G46: Coal: Stockpile | H46: 42.56 | I46: 25.81 | J46: 1.38
G47: Coal: Columbian | H47: 43.93 | I47: 25.12 | J47: 0.7
G48: Coal: Russian | H48: 43.8 | I48: 24.5 | J48: 0.35
G49: Coal: Scottish | H49: 42 | I49: 26.2 | J49: 1.72
G50: Wood chips | H50: 73.77 | I50: 18 | J50: 0.01
G56: Variables | M56: Period | Q56: Variables | W56: Period
G57: Amount of fuel burned | H57: Stockpile | I57: Columbian | J57: Russian | K57: Scottish | L57: Wood chips | M57: Hours in each period | Q57: Amount of fuel burned | R57: Stockpile | S57: Columbian | T57: Russian | U57: Scottish | V57: Wood chips | W57: Hours in each period
G58: June- WD-Peak | H58: 93306.543 | I58: 0 | J58: 0 | K58: 0 | L58: 14865.691 | M58: 264 | N58: June | Q58: June- WD-Peak | R58: =H58*$L$28 -> 234134.63 | S58: =I58*$L$29 -> 0 | T58: =J58*$L$30 -> 0 | U58: =K58*$L$31 -> 0 | V58: =L58*$L$32 -> 26014.959 | W58: 264 | X58: June
G59: June-WD-Off-peak | H59: 0 | I59: 0 | J59: 0 | K59: 0 | L59: 0 | M59: 264 | Q59: June-WD-Off-peak | R59: =H59*$L$28 -> 0 | S59: =I59*$L$29 -> 0 | T59: =J59*$L$30 -> 0 | U59: =K59*$L$31 -> 0 | V59: =L59*$L$32 -> 0 | W59: 264
G60: June-WK-Peak | H60: 37699.607 | I60: 0 | J60: 0 | K60: 0 | L60: 0 | M60: 96 | Q60: June-WK-Peak | R60: =H60*$L$28 -> 94599.832 | S60: =I60*$L$29 -> 0 | T60: =J60*$L$30 -> 0 | U60: =K60*$L$31 -> 0 | V60: =L60*$L$32 -> 0 | W60: 96
G61: June-WK-Off-peak | H61: 0 | I61: 0 | J61: 0 | K61: 0 | L61: 0 | M61: 96 | Q61: June-WK-Off-peak | R61: =H61*$L$28 -> 0 | S61: =I61*$L$29 -> 0 | T61: =J61*$L$30 -> 0 | U61: =K61*$L$31 -> 0 | V61: =L61*$L$32 -> 0 | W61: 96
G62: July-WD-Peak | H62: 103723.41 | I62: 0 | J62: 0 | K62: 0 | L62: 0 | M62: 264 | N62: July | Q62: July-WD-Peak | R62: =H62*$L$28 -> 260273.73 | S62: =I62*$L$29 -> 0 | T62: =J62*$L$30 -> 0 | U62: =K62*$L$31 -> 0 | V62: =L62*$L$32 -> 0 | W62: 264 | X62: July
G63: July-WD-Off-peak | H63: 0 | I63: 0 | J63: 0 | K63: 0 | L63: 0 | M63: 264 | Q63: July-WD-Off-peak | R63: =H63*$L$28 -> 0 | S63: =I63*$L$29 -> 0 | T63: =J63*$L$30 -> 0 | U63: =K63*$L$31 -> 0 | V63: =L63*$L$32 -> 0 | W63: 264
G64: July-WK-Peak | H64: 42432.305 | I64: 0 | J64: 0 | K64: 0 | L64: 0 | M64: 108 | Q64: July-WK-Peak | R64: =H64*$L$28 -> 106475.62 | S64: =I64*$L$29 -> 0 | T64: =J64*$L$30 -> 0 | U64: =K64*$L$31 -> 0 | V64: =L64*$L$32 -> 0 | W64: 108
G65: July-WK-Off-peak | H65: 0 | I65: 0 | J65: 0 | K65: 0 | L65: 0 | M65: 108 | Q65: July-WK-Off-peak | R65: =H65*$L$28 -> 0 | S65: =I65*$L$29 -> 0 | T65: =J65*$L$30 -> 0 | U65: =K65*$L$31 -> 0 | V65: =L65*$L$32 -> 0 | W65: 108
G66: Aug-WD-Peak | H66: 103723.41 | I66: 0 | J66: 0 | K66: 0 | L66: 0 | M66: 264 | N66: August | Q66: Aug-WD-Peak | R66: =H66*$L$28 -> 260273.73 | S66: =I66*$L$29 -> 0 | T66: =J66*$L$30 -> 0 | U66: =K66*$L$31 -> 0 | V66: =L66*$L$32 -> 0 | W66: 264 | X66: August
G67: Aug-WD-Off-peak | H67: 103723.41 | I67: 0 | J67: 0 | K67: 0 | L67: 0 | M67: 264 | Q67: Aug-WD-Off-peak | R67: =H67*$L$28 -> 260273.73 | S67: =I67*$L$29 -> 0 | T67: =J67*$L$30 -> 0 | U67: =K67*$L$31 -> 0 | V67: =L67*$L$32 -> 0 | W67: 264
G68: Aug-WK-Peak | H68: 42432.305 | I68: 0 | J68: 0 | K68: 0 | L68: 0 | M68: 108 | Q68: Aug-WK-Peak | R68: =H68*$L$28 -> 106475.62 | S68: =I68*$L$29 -> 0 | T68: =J68*$L$30 -> 0 | U68: =K68*$L$31 -> 0 | V68: =L68*$L$32 -> 0 | W68: 108
G69: Aug-WK-Off-peak | H69: 0 | I69: 0 | J69: 0 | K69: 0 | L69: 0 | M69: 108 | Q69: Aug-WK-Off-peak | R69: =H69*$L$28 -> 0 | S69: =I69*$L$29 -> 0 | T69: =J69*$L$30 -> 0 | U69: =K69*$L$31 -> 0 | V69: =L69*$L$32 -> 0 | W69: 108
G70: Sept-WD-Peak | H70: 0 | I70: 0 | J70: 0 | K70: 102130.95 | L70: 0 | M70: 264 | N70: September | Q70: Sept-WD-Peak | R70: =H70*$L$28 -> 0 | S70: =I70*$L$29 -> 0 | T70: =J70*$L$30 -> 0 | U70: =K70*$L$31 -> 260150.23 | V70: =L70*$L$32 -> 0 | W70: 264 | X70: September
G71: Sept-WD-Off-peak | H71: 0 | I71: 0 | J71: 0 | K71: 102130.95 | L71: 0 | M71: 264 | Q71: Sept-WD-Off-peak | R71: =H71*$L$28 -> 0 | S71: =I71*$L$29 -> 0 | T71: =J71*$L$30 -> 0 | U71: =K71*$L$31 -> 260150.23 | V71: =L71*$L$32 -> 0 | W71: 264
G72: Sept-WK-Peak | H72: 0 | I72: 0 | J72: 0 | K72: 37138.527 | L72: 0 | M72: 96 | Q72: Sept-WK-Peak | R72: =H72*$L$28 -> 0 | S72: =I72*$L$29 -> 0 | T72: =J72*$L$30 -> 0 | U72: =K72*$L$31 -> 94600.083 | V72: =L72*$L$32 -> 0 | W72: 96
G73: Sept-WK-Off-peak | H73: 0 | I73: 0 | J73: 0 | K73: 37138.527 | L73: 0 | M73: 96 | Q73: Sept-WK-Off-peak | R73: =H73*$L$28 -> 0 | S73: =I73*$L$29 -> 0 | T73: =J73*$L$30 -> 0 | U73: =K73*$L$31 -> 94600.083 | V73: =L73*$L$32 -> 0 | W73: 96
G74: Oct-WD-Peak | H74: 0 | I74: 0 | J74: 0 | K74: 97535.175 | L74: 0 | M74: 252 | N74: October | Q74: Oct-WD-Peak | R74: =H74*$L$28 -> 0 | S74: =I74*$L$29 -> 0 | T74: =J74*$L$30 -> 0 | U74: =K74*$L$31 -> 248443.77 | V74: =L74*$L$32 -> 0 | W74: 252 | X74: October
G75: Oct-WD-Off-peak | H75: 0 | I75: 0 | J75: 0 | K75: 97535.175 | L75: 0 | M75: 252 | Q75: Oct-WD-Off-peak | R75: =H75*$L$28 -> 0 | S75: =I75*$L$29 -> 0 | T75: =J75*$L$30 -> 0 | U75: =K75*$L$31 -> 248443.77 | V75: =L75*$L$32 -> 0 | W75: 252
G76: Oct-WK-Peak | H76: 0 | I76: 0 | J76: 0 | K76: 46445.321 | L76: 0 | M76: 120 | Q76: Oct-WK-Peak | R76: =H76*$L$28 -> 0 | S76: =I76*$L$29 -> 0 | T76: =J76*$L$30 -> 0 | U76: =K76*$L$31 -> 118306.55 | V76: =L76*$L$32 -> 0 | W76: 120
G77: Oct-WK-Off-peak | H77: 0 | I77: 0 | J77: 0 | K77: 46445.321 | L77: 0 | M77: 120 | Q77: Oct-WK-Off-peak | R77: =H77*$L$28 -> 0 | S77: =I77*$L$29 -> 0 | T77: =J77*$L$30 -> 0 | U77: =K77*$L$31 -> 118306.55 | V77: =L77*$L$32 -> 0 | W77: 120
G78: Total | H78: 527040.99 | I78: 0 | J78: 0 | K78: 566499.95 | L78: 14865.691 | Q78: Total | R78: =SUM(R58:R77) -> 1322506.9 | S78: =SUM(S58:S77) -> 0 | T78: =SUM(T58:T77) -> 0 | U78: =SUM(U58:U77) -> 1443001.3 | V78: =SUM(V58:V77) -> 26014.959 | X78: =SUM(R78:V78) -> 2791523.1

Sheet scenario FGD DSI 
A1: The Fuel Buying Decision
A4: Variables | G4: Period
A5: Amount of fuel burned | B5: Stockpile | C5: Columbian | D5: Russian | E5: Scottish | F5: Wood chips | G5: Hours in each period
A6: June- WD-Peak | B6: 94424.38 | C6: 0 | D6: 0 | E6: 0 | F6: 15043.786 | G6: =12*22 -> 264 | H6: June
A7: June-WD-Off-peak | B7: 0 | C7: 0 | D7: 0 | E7: 0 | F7: 0 | G7: =12*22 -> 264
A8: June-WK-Peak | B8: 38151.258 | C8: 0 | D8: 0 | E8: 0 | F8: 0 | G8: =12*8 -> 96
A9: June-WK-Off-peak | B9: 0 | C9: 0 | D9: 0 | E9: 0 | F9: 0 | G9: =12*8 -> 96
A10: July-WD-Peak | B10: 104925.39 | C10: 0 | D10: 0 | E10: 0 | F10: 0 | G10: =22*12 -> 264 | H10: July
A11: July-WD-Off-peak | B11: 0 | C11: 0 | D11: 0 | E11: 0 | F11: 0 | G11: =12*22 -> 264
A12: July-WK-Peak | B12: 42924.022 | C12: 0 | D12: 0 | E12: 0 | F12: 0 | G12: =12*9 -> 108
A13: July-WK-Off-peak | B13: 0 | C13: 0 | D13: 0 | E13: 0 | F13: 0 | G13: =12*9 -> 108
A14: Aug-WD-Peak | B14: 104925.39 | C14: 0 | D14: 0 | E14: 0 | F14: 0 | G14: =12*22 -> 264 | H14: August
A15: Aug-WD-Off-peak | B15: 104925.39 | C15: 0 | D15: 0 | E15: 0 | F15: 0 | G15: =12*22 -> 264
A16: Aug-WK-Peak | B16: 42924.022 | C16: 0 | D16: 0 | E16: 0 | F16: 0 | G16: =12*9 -> 108
A17: Aug-WK-Off-peak | B17: 0 | C17: 0 | D17: 0 | E17: 0 | F17: 0 | G17: =12*9 -> 108
A18: Sept-WD-Peak | B18: 0 | C18: 0 | D18: 0 | E18: 103354.51 | F18: 0 | G18: =12*22 -> 264 | H18: September
A19: Sept-WD-Off-peak | B19: 0 | C19: 0 | D19: 0 | E19: 103354.51 | F19: 0 | G19: =12*22 -> 264
A20: Sept-WK-Peak | B20: 0 | C20: 0 | D20: 0 | E20: 37583.457 | F20: 0 | G20: =12*8 -> 96
A21: Sept-WK-Off-peak | B21: 0 | C21: 0 | D21: 0 | E21: 37583.457 | F21: 0 | G21: =12*8 -> 96
A22: Oct-WD-Peak | B22: 0 | C22: 0 | D22: 0 | E22: 98665.439 | F22: 0 | G22: =21*12 -> 252 | H22: October
A23: Oct-WD-Off-peak | B23: 0 | C23: 0 | D23: 0 | E23: 98665.439 | F23: 0 | G23: =21*12 -> 252
A24: Oct-WK-Peak | B24: 0 | C24: 0 | D24: 0 | E24: 46983.543 | F24: 0 | G24: =12*10 -> 120
A25: Oct-WK-Off-peak | B25: 0 | C25: 0 | D25: 0 | E25: 46983.543 | F25: 0 | G25: =12*10 -> 120
A26: Total | B26: =SUM(B6:B25) -> 533199.84 | C26: =SUM(C6:C25) -> 0 | D26: =SUM(D6:D25) -> 0 | E26: =SUM(E6:E25) -> 573173.89 | F26: =SUM(F6:F25) -> 15043.786
R34: Period | S34: Unit | T34: June | U34: July | V34: August | W34: September | X34: October
R35: Weekday Peak | S35: £ per MWh | T35: 36 | U35: 36.35 | V35: 37.65 | W35: 38.35 | X35: 43.7
R36: Weekday Off-peak | S36: £ per MWh | T36: 27 | U36: 27 | V36: 28.2 | W36: 28.5 | X36: 31.7
I37: yearly cost for installation | J37: SO2 Profit | K37: final profit | R37: Weekend Peak | S37: £ per MWh | T37: 33.5 | U37: 34.3 | V37: 35.65 | W37: 35.8 | X37: 38.7
A38: Profit | G38: Total | H38: =SUMPRODUCT($B$6:$F$25,$B$40:$F$59) -> 19971640 | I38: 13277240 | J38: =G92*30 -> 258273.8 | K38: =H38+J38-I38 -> 6952673 | L38: Scenario 1: SO2 : 30 euro/ton | R38: Weekend Off-peak | S38: £ per MWh | T38: 26.2 | U38: 26.3 | V38: 27.5 | W38: 27.65 | X38: 30.1
B39: Stock | C39: Col | D39: Rus | E39: Sco | F39: Wood Chips (Bio) | J39: =G92*40 -> 344365.06 | K39: =H38+J39-I38 -> 7038764.3 | L39: Scenario 2: SO2 : 40 euro/ton
A40: June weekday peak | B40: 19.946801 | C40: 16.905756 | D40: 15.534236 | E40: 21.451306 | F40: 48.5725 | H40: June | J40: =G92*50 -> 430456.33 | K40: =H38+J40-I38 -> 7124855.5 | L40: Scenario 3: SO2 : 50 euro/ton
A41: June weekday off-peak | B41: -2.6369486 | C41: -5.0742444 | D41: -5.9032639 | E41: -1.4736944 | F41: 32.8225
A42: June weekend peak | B42: 13.673538 | C42: 10.8002 | D42: 9.579375 | E42: 15.08325 | F42: 44.1975
A43: June weekend off-peak | B43: -4.6443931 | C43: -7.0280222 | D43: -7.8088194 | E43: -3.5114722 | F43: 31.4225
A44: July weekday peak | B44: 20.825058 | C44: 17.760533 | D44: 16.367917 | E44: 22.342833 | F44: 49.185 | H44: July
A45: July weekday off-peak | B45: -2.6369486 | C45: -5.0742444 | D45: -5.9032639 | E45: -1.4736944 | F45: 32.8225
A46: July weekend peak | B46: 15.680982 | C46: 12.753978 | D46: 11.484931 | E46: 17.121028 | F46: 45.5975
A47: July weekend off-peak | B47: -4.3934625 | C47: -6.7838 | D47: -7.570625 | E47: -3.25675 | F47: 31.5975
A48: August weekday peak | B48: 24.087156 | C48: 20.935422 | D48: 19.464444 | E48: 25.654222 | F48: 51.46 | H48: August
A49: August weekday off-peak | B49: 0.37421806 | C49: -2.1435778 | D49: -3.0449306 | E49: 1.5829722 | F49: 34.9225
A50: August weekend peak | B50: 19.068544 | C50: 16.050978 | D50: 14.700556 | E50: 20.559778 | F50: 47.96
A51: August weekend off-peak | B51: -1.3822958 | C51: -3.8531333 | D51: -4.7122917 | E51: -0.20008333 | F51: 33.6975
A52: September weekday peak | B52: 25.843669 | C52: 22.644978 | D52: 21.131806 | E52: 27.437278 | F52: 52.685 | H52: September
A53: September weekday off-peak | B53: 1.1270097 | C53: -1.4109111 | D53: -2.3303472 | E53: 2.3471389 | F53: 35.4475
A54: September weekend peak | B54: 19.44494 | C54: 16.417311 | D54: 15.057847 | E54: 20.941861 | F54: 48.2225
A55: September weekend off-peak | B55: -1.0059 | C55: -3.4868 | D55: -4.355 | E55: 0.182 | F55: 33.96
A56: October weekday peak | B56: 39.268454 | C56: 35.710867 | D56: 33.875208 | E56: 41.064917 | F56: 62.0475 | H56: October
A57: October weekday off-peak | B57: 9.1567875 | C57: 6.4042 | D57: 5.291875 | E57: 10.49825 | F57: 41.0475
A58: October weekend peak | B58: 26.721926 | C58: 23.499756 | D58: 21.965486 | E58: 28.328806 | F58: 53.2975
A59: October weekend off-peak | B59: 5.1418986 | C59: 2.4966444 | D59: 1.4807639 | E59: 6.4226944 | F59: 38.2475
A70: Constraints | G70: Total(LHS) | I70: Available(RHS) | K70: meaning
A72: Biomass(Calorific value) | B72: 25.81 | C72: 25.12 | D72: 24.5 | E72: 26.2 | F72: 18 | G72: =$F$72*$F$26 -> 270788.14 | H72: <= | I72: =0.1*SUMPRODUCT($B$72:$F$72,B6:F6) -> 270788.14
B73: 25.81 | C73: 25.12 | D73: 24.5 | E73: 26.2 | F73: 18 | G73: =$F$72*F7 -> 0 | I73: =0.1*SUMPRODUCT($B$72:$F$72,B7:F7) -> 0
B74: 25.81 | C74: 25.12 | D74: 24.5 | E74: 26.2 | F74: 18 | G74: =$F$72*F8 -> 0 | I74: =0.1*SUMPRODUCT($B$72:$F$72,B8:F8) -> 98468.397
B75: 25.81 | C75: 25.12 | D75: 24.5 | E75: 26.2 | F75: 18 | G75: =$F$72*F9 -> 0 | I75: =0.1*SUMPRODUCT($B$72:$F$72,B9:F9) -> 0
B76: 25.81 | C76: 25.12 | D76: 24.5 | E76: 26.2 | F76: 18 | G76: =$F$72*F10 -> 0 | I76: =0.1*SUMPRODUCT($B$72:$F$72,B10:F10) -> 270812.42
B77: 25.81 | C77: 25.12 | D77: 24.5 | E77: 26.2 | F77: 18 | G77: =$F$72*F11 -> 0 | I77: =0.1*SUMPRODUCT($B$72:$F$72,B11:F11) -> 0
B78: 25.81 | C78: 25.12 | D78: 24.5 | E78: 26.2 | F78: 18 | G78: =$F$72*F12 -> 0 | I78: =0.1*SUMPRODUCT($B$72:$F$72,B12:F12) -> 110786.9
B79: 25.81 | C79: 25.12 | D79: 24.5 | E79: 26.2 | F79: 18 | G79: =$F$72*F13 -> 0 | I79: =0.1*SUMPRODUCT($B$72:$F$72,B13:F13) -> 0
B80: 25.81 | C80: 25.12 | D80: 24.5 | E80: 26.2 | F80: 18 | G80: =$F$72*F14 -> 0 | I80: =0.1*SUMPRODUCT($B$72:$F$72,B14:F14) -> 270812.42
B81: 25.81 | C81: 25.12 | D81: 24.5 | E81: 26.2 | F81: 18 | G81: =$F$72*F15 -> 0 | I81: =0.1*SUMPRODUCT($B$72:$F$72,B15:F15) -> 270812.42
B82: 25.81 | C82: 25.12 | D82: 24.5 | E82: 26.2 | F82: 18 | G82: =$F$72*F16 -> 0 | I82: =0.1*SUMPRODUCT($B$72:$F$72,B16:F16) -> 110786.9
B83: 25.81 | C83: 25.12 | D83: 24.5 | E83: 26.2 | F83: 18 | G83: =$F$72*F17 -> 0 | I83: =0.1*SUMPRODUCT($B$72:$F$72,B17:F17) -> 0
B84: 25.81 | C84: 25.12 | D84: 24.5 | E84: 26.2 | F84: 18 | G84: =$F$72*F18 -> 0 | I84: =0.1*SUMPRODUCT($B$72:$F$72,B18:F18) -> 270788.81
... B91: 25.81 | C91: 25.12 | D91: 24.5 | E91: 26.2 | F91: 18 | G91: =$F$72*F25 -> 0 | I91: =0.1*SUMPRODUCT($B$72:$F$72,B25:F25) -> 123096.88
A92: SO2 | B92: 0.0069 | C92: 0.0035 | D92: 0.00175 | E92: 0.0086 | F92: 5e-05 | G92: =SUMPRODUCT($B$92:$F$92,$B$26:$F$26) -> 8609.1266 | H92: <= | I92: 9000
A93: Stock | G93: =$B$26 -> 533199.84 | H93: <= | I93: 600000
A94: Non-negativity
A95: zero for certain period | H95: = | I95: 0 | K95: 1000*Hp(number of hours) | L95: minus electricity for FGD result | N95: percentage
A96: Period capacity | B96: 2.50931 | C96: 2.44222 | D96: 2.38194 | E96: 2.54722 | F96: 1.75 | G96: =SUMPRODUCT($B$96:$F$96,B6:F6) -> 263266.67 | H96: <= | I96: =12*22 -> 264 | J96: 1000 | K96: =I96*$J$96 -> 264000 | L96: =K96-2*1000*N96 -> 263266.67 | N96: =I96/SUM($I$96:$I$99) -> 0.36666667
B97: 2.50931 | C97: 2.44222 | D97: 2.38194 | E97: 2.54722 | F97: 1.75 | G97: =SUMPRODUCT($B$96:$F$96,B7:F7) -> 0 | H97: <= | I97: =12*22 -> 264 | K97: =I97*$J$96 -> 264000 | L97: =K97-2*1000*N97 -> 263266.67 | N97: =I97/SUM($I$96:$I$99) -> 0.36666667
B98: 2.50931 | C98: 2.44222 | D98: 2.38194 | E98: 2.54722 | F98: 1.75 | G98: =SUMPRODUCT($B$96:$F$96,B8:F8) -> 95733.333 | H98: <= | I98: =12*8 -> 96 | K98: =I98*$J$96 -> 96000 | L98: =K98-2*1000*N98 -> 95733.333 | N98: =I98/SUM($I$96:$I$99) -> 0.13333333
B99: 2.50931 | C99: 2.44222 | D99: 2.38194 | E99: 2.54722 | F99: 1.75 | G99: =SUMPRODUCT($B$96:$F$96,B9:F9) -> 0 | H99: <= | I99: =12*8 -> 96 | K99: =I99*$J$96 -> 96000 | L99: =K99-2*1000*N99 -> 95733.333 | N99: =I99/SUM($I$96:$I$99) -> 0.13333333
B100: 2.50931 | C100: 2.44222 | D100: 2.38194 | E100: 2.54722 | F100: 1.75 | G100: =SUMPRODUCT($B$96:$F$96,B10:F10) -> 263290.32 | H100: <= | I100: =22*12 -> 264 | K100: =I100*$J$96 -> 264000 | L100: =K100-2*1000*N100 -> 263290.32 | N100: =I100/SUM($I$100:$I$103) -> 0.35483871
B101: 2.50931 | C101: 2.44222 | D101: 2.38194 | E101: 2.54722 | F101: 1.75 | G101: =SUMPRODUCT($B$96:$F$96,B11:F11) -> 0 | H101: <= | I101: =12*22 -> 264 | K101: =I101*$J$96 -> 264000 | L101: =K101-2*1000*N101 -> 263290.32 | N101: =I101/SUM($I$100:$I$103) -> 0.35483871
B102: 2.50931 | C102: 2.44222 | D102: 2.38194 | E102: 2.54722 | F102: 1.75 | G102: =SUMPRODUCT($B$96:$F$96,B12:F12) -> 107709.68 | H102: <= | I102: =12*9 -> 108 | K102: =I102*$J$96 -> 108000 | L102: =K102-2*1000*N102 -> 107709.68 | N102: =I102/SUM($I$100:$I$103) -> 0.14516129
B103: 2.50931 | C103: 2.44222 | D103: 2.38194 | E103: 2.54722 | F103: 1.75 | G103: =SUMPRODUCT($B$96:$F$96,B13:F13) -> 0 | H103: <= | I103: =12*9 -> 108 | K103: =I103*$J$96 -> 108000 | L103: =K103-2*1000*N103 -> 107709.68 | N103: =I103/SUM($I$100:$I$103) -> 0.14516129
B104: 2.50931 | C104: 2.44222 | D104: 2.38194 | E104: 2.54722 | F104: 1.75 | G104: =SUMPRODUCT($B$96:$F$96,B14:F14) -> 263290.32 | H104: <= | I104: =12*22 -> 264 | K104: =I104*$J$96 -> 264000 | L104: =K104-2*1000*N104 -> 263290.32 | N104: =I104/SUM($I$104:$I$107) -> 0.35483871
B105: 2.50931 | C105: 2.44222 | D105: 2.38194 | E105: 2.54722 | F105: 1.75 | G105: =SUMPRODUCT($B$96:$F$96,B15:F15) -> 263290.32 | H105: <= | I105: =12*22 -> 264 | K105: =I105*$J$96 -> 264000 | L105: =K105-2*1000*N105 -> 263290.32 | N105: =I105/SUM($I$104:$I$107) -> 0.35483871
B106: 2.50931 | C106: 2.44222 | D106: 2.38194 | E106: 2.54722 | F106: 1.75 | G106: =SUMPRODUCT($B$96:$F$96,B16:F16) -> 107709.68 | H106: <= | I106: =12*9 -> 108 | K106: =I106*$J$96 -> 108000 | L106: =K106-2*1000*N106 -> 107709.68 | N106: =I106/SUM($I$104:$I$107) -> 0.14516129
B107: 2.50931 | C107: 2.44222 | D107: 2.38194 | E107: 2.54722 | F107: 1.75 | G107: =SUMPRODUCT($B$96:$F$96,B17:F17) -> 0 | H107: <= | I107: =12*9 -> 108 | K107: =I107*$J$96 -> 108000 | L107: =K107-2*1000*N107 -> 107709.68 | N107: =I107/SUM($I$104:$I$107) -> 0.14516129
B108: 2.50931 | C108: 2.44222 | D108: 2.38194 | E108: 2.54722 | F108: 1.75 | G108: =SUMPRODUCT($B$96:$F$96,B18:F18) -> 263266.67 | H108: <= | I108: =12*22 -> 264 | K108: =I108*$J$96 -> 264000 | L108: =K108-2*1000*N108 -> 263266.67 | N108: =I108/SUM($I$108:$I$111) -> 0.36666667
B109: 2.50931 | C109: 2.44222 | D109: 2.38194 | E109: 2.54722 | F109: 1.75 | G109: =SUMPRODUCT($B$96:$F$96,B19:F19) -> 263266.67 | H109: <= | I109: =12*22 -> 264 | K109: =I109*$J$96 -> 264000 | L109: =K109-2*1000*N109 -> 263266.67 | N109: =I109/SUM($I$108:$I$111) -> 0.36666667
B110: 2.50931 | C110: 2.44222 | D110: 2.38194 | E110: 2.54722 | F110: 1.75 | G110: =SUMPRODUCT($B$96:$F$96,B20:F20) -> 95733.333 | H110: <= | I110: =12*8 -> 96 | K110: =I110*$J$96 -> 96000 | L110: =K110-2*1000*N110 -> 95733.333 | N110: =I110/SUM($I$108:$I$111) -> 0.13333333
B111: 2.50931 | C111: 2.44222 | D111: 2.38194 | E111: 2.54722 | F111: 1.75 | G111: =SUMPRODUCT($B$96:$F$96,B21:F21) -> 95733.333 | H111: <= | I111: =12*8 -> 96 | K111: =I111*$J$96 -> 96000 | L111: =K111-2*1000*N111 -> 95733.333 | N111: =I111/SUM($I$108:$I$111) -> 0.13333333
B112: 2.50931 | C112: 2.44222 | D112: 2.38194 | E112: 2.54722 | F112: 1.75 | G112: =SUMPRODUCT($B$96:$F$96,B22:F22) -> 251322.58 | H112: <= | I112: =21*12 -> 252 | K112: =I112*$J$96 -> 252000 | L112: =K112-2*1000*N112 -> 251322.58 | N112: =I112/SUM($I$112:$I$115) -> 0.33870968
B113: 2.50931 | C113: 2.44222 | D113: 2.38194 | E113: 2.54722 | F113: 1.75 | G113: =SUMPRODUCT($B$96:$F$96,B23:F23) -> 251322.58 | H113: <= | I113: =21*12 -> 252 | K113: =I113*$J$96 -> 252000 | L113: =K113-2*1000*N113 -> 251322.58 | N113: =I113/SUM($I$112:$I$115) -> 0.33870968
B114: 2.50931 | C114: 2.44222 | D114: 2.38194 | E114: 2.54722 | F114: 1.75 | G114: =SUMPRODUCT($B$96:$F$96,B24:F24) -> 119677.42 | H114: <= | I114: =12*10 -> 120 | K114: =I114*$J$96 -> 120000 | L114: =K114-2*1000*N114 -> 119677.42 | N114: =I114/SUM($I$112:$I$115) -> 0.16129032
B115: 2.50931 | C115: 2.44222 | D115: 2.38194 | E115: 2.54722 | F115: 1.75 | G115: =SUMPRODUCT($B$96:$F$96,B25:F25) -> 119677.42 | H115: <= | I115: =12*10 -> 120 | K115: =I115*$J$96 -> 120000 | L115: =K115-2*1000*N115 -> 119677.42 | N115: =I115/SUM($I$112:$I$115) -> 0.16129032

Sheet period for DSI
A1: Electricity in each month | B1: Stock | C1: Col | D1: Rus | E1: Sco | F1: Wood Chips (Bio)
A2: Period | B2: Profit per ton | C2: Profit per ton | D2: Profit per ton | E2: Profit per ton | F2: Profit per ton | G2: Hours in each period
A3: June weekday peak | B3: =(L19-$K$6-$K$7*$K$8*$K$9)*$L$28-$H$46 -> 19.946801 | C3: =(L19-$K$6-$K$7*$K$8*$K$9)*$L$29-$H$47 -> 16.905756 | D3: =(L19-$K$6-$K$7*$K$8*$K$9)*$L$30-$H$48 -> 15.534236 | E3: =(L19-$K$6-$K$7*$K$8*$K$9)*$L$31-$H$49 -> 21.451306 | F3: =(L19-$K$6-$K$7*$K$8*$K$9+$K$10)*$L$32-$H$50 -> 48.5725 | G3: =12*22 -> 264 | J3: Scalars | K3: Value
A4: June weekday off-peak | B4: =(L20-$K$6-$K$7*$K$8*$K$9)*$L$28-$H$46 -> -2.6369486 | C4: =(L20-$K$6-$K$7*$K$8*$K$9)*$L$29-$H$47 -> -5.0742444 | D4: =(L20-$K$6-$K$7*$K$8*$K$9)*$L$30-$H$48 -> -5.9032639 | E4: =(L20-$K$6-$K$7*$K$8*$K$9)*$L$31-$H$49 -> -1.4736944 | F4: =(L20-$K$6-$K$7*$K$8*$K$9+$K$10)*$L$32-$H$50 -> 32.8225 | G4: =12*22 -> 264 | J4: Efficiency | K4: 0.35
A5: June weekend peak | B5: =(L21-$K$6-$K$7*$K$8*$K$9)*$L$28-$H$46 -> 13.673538 | C5: =(L21-$K$6-$K$7*$K$8*$K$9)*$L$29-$H$47 -> 10.8002 | D5: =(L21-$K$6-$K$7*$K$8*$K$9)*$L$30-$H$48 -> 9.579375 | E5: =(L21-$K$6-$K$7*$K$8*$K$9)*$L$31-$H$49 -> 15.08325 | F5: =(L21-$K$6-$K$7*$K$8*$K$9+$K$10)*$L$32-$H$50 -> 44.1975 | G5: =12*8 -> 96 | J5: Plant_Capacity_MW | K5: 1000
A6: June weekend off-peak | B6: =(L22-$K$6-$K$7*$K$8*$K$9)*$L$28-$H$46 -> -4.6443931 | C6: =(L22-$K$6-$K$7*$K$8*$K$9)*$L$29-$H$47 -> -7.0280222 | D6: =(L22-$K$6-$K$7*$K$8*$K$9)*$L$30-$H$48 -> -7.8088194 | E6: =(L22-$K$6-$K$7*$K$8*$K$9)*$L$31-$H$49 -> -3.5114722 | F6: =(L22-$K$6-$K$7*$K$8*$K$9+$K$10)*$L$32-$H$50 -> 31.4225 | G6: =12*8 -> 96 | J6: Grid_Charge_per_MWh | K6: 0.65
A7: July weekday peak | B7: =(M19-$K$6-$K$7*$K$8*$K$9)*$L$28-$H$46 -> 20.825058 | C7: =(M19-$K$6-$K$7*$K$8*$K$9)*$L$29-$H$47 -> 17.760533 | D7: =(M19-$K$6-$K$7*$K$8*$K$9)*$L$30-$H$48 -> 16.367917 | E7: =(M19-$K$6-$K$7*$K$8*$K$9)*$L$31-$H$49 -> 22.342833 | F7: =(M19-$K$6-$K$7*$K$8*$K$9+$K$10)*$L$32-$H$50 -> 49.185 | G7: =22*12 -> 264 | J7: CO2_Intensity_t_per_MWh | K7: 0.8
A8: July weekday off-peak | B8: =(M20-$K$6-$K$7*$K$8*$K$9)*$L$28-$H$46 -> -2.6369486 | C8: =(M20-$K$6-$K$7*$K$8*$K$9)*$L$29-$H$47 -> -5.0742444 | D8: =(M20-$K$6-$K$7*$K$8*$K$9)*$L$30-$H$48 -> -5.9032639 | E8: =(M20-$K$6-$K$7*$K$8*$K$9)*$L$31-$H$49 -> -1.4736944 | F8: =(M20-$K$6-$K$7*$K$8*$K$9+$K$10)*$L$32-$H$50 -> 32.8225 | G8: =12*22 -> 264 | J8: CO2_Cost_EUR_per_t | K8: 15
A9: July weekend peak | B9: =(M21-$K$6-$K$7*$K$8*$K$9)*$L$28-$H$46 -> 15.680982 | C9: =(M21-$K$6-$K$7*$K$8*$K$9)*$L$29-$H$47 -> 12.753978 | D9: =(M21-$K$6-$K$7*$K$8*$K$9)*$L$30-$H$48 -> 11.484931 | E9: =(M21-$K$6-$K$7*$K$8*$K$9)*$L$31-$H$49 -> 17.121028 | F9: =(M21-$K$6-$K$7*$K$8*$K$9+$K$10)*$L$32-$H$50 -> 45.5975 | G9: =12*9 -> 108 | J9: FX_EUR_per_GBP | K9: 0.87
A10: July weekend off-peak | B10: =(M22-$K$6-$K$7*$K$8*$K$9)*$L$28-$H$46 -> -4.3934625 | C10: =(M22-$K$6-$K$7*$K$8*$K$9)*$L$29-$H$47 -> -6.7838 | D10: =(M22-$K$6-$K$7*$K$8*$K$9)*$L$30-$H$48 -> -7.570625 | E10: =(M22-$K$6-$K$7*$K$8*$K$9)*$L$31-$H$49 -> -3.25675 | F10: =(M22-$K$6-$K$7*$K$8*$K$9+$K$10)*$L$32-$H$50 -> 31.5975 | G10: =12*9 -> 108 | J10: ROC_per_MWh | K10: 45
A11: August weekday peak | B11: =(N19-$K$6-$K$7*$K$8*$K$9)*$L$28-$H$46 -> 24.087156 | C11: =(N19-$K$6-$K$7*$K$8*$K$9)*$L$29-$H$47 -> 20.935422 | D11: =(N19-$K$6-$K$7*$K$8*$K$9)*$L$30-$H$48 -> 19.464444 | E11: =(N19-$K$6-$K$7*$K$8*$K$9)*$L$31-$H$49 -> 25.654222 | F11: =(N19-$K$6-$K$7*$K$8*$K$9+$K$10)*$L$32-$H$50 -> 51.46 | G11: =12*22 -> 264 | J11: Sulphur_Allowance_t | K11: 9000
A12: August weekday off-peak | B12: =(N20-$K$6-$K$7*$K$8*$K$9)*$L$28-$H$46 -> 0.37421806 | C12: =(N20-$K$6-$K$7*$K$8*$K$9)*$L$29-$H$47 -> -2.1435778 | D12: =(N20-$K$6-$K$7*$K$8*$K$9)*$L$30-$H$48 -> -3.0449306 | E12: =(N20-$K$6-$K$7*$K$8*$K$9)*$L$31-$H$49 -> 1.5829722 | F12: =(N20-$K$6-$K$7*$K$8*$K$9+$K$10)*$L$32-$H$50 -> 34.9225 | G12: =12*22 -> 264 | J12: Stockpile_Tonnes | K12: 600000
A13: August weekend peak | B13: =(N21-$K$6-$K$7*$K$8*$K$9)*$L$28-$H$46 -> 19.068544 | C13: =(N21-$K$6-$K$7*$K$8*$K$9)*$L$29-$H$47 -> 16.050978 | D13: =(N21-$K$6-$K$7*$K$8*$K$9)*$L$30-$H$48 -> 14.700556 | E13: =(N21-$K$6-$K$7*$K$8*$K$9)*$L$31-$H$49 -> 20.559778 | F13: =(N21-$K$6-$K$7*$K$8*$K$9+$K$10)*$L$32-$H$50 -> 47.96 | G13: =12*9 -> 108 | J13: Biomass_Share_Max | K13: 0.1
A14: August weekend off-peak | B14: =(N22-$K$6-$K$7*$K$8*$K$9)*$L$28-$H$46 -> -1.3822958 | C14: =(N22-$K$6-$K$7*$K$8*$K$9)*$L$29-$H$47 -> -3.8531333 | D14: =(N22-$K$6-$K$7*$K$8*$K$9)*$L$30-$H$48 -> -4.7122917 | E14: =(N22-$K$6-$K$7*$K$8*$K$9)*$L$31-$H$49 -> -0.20008333 | F14: =(N22-$K$6-$K$7*$K$8*$K$9+$K$10)*$L$32-$H$50 -> 33.6975 | G14: =12*9 -> 108 | J14: Hours_Peak_per_Day | K14: 12
A15: September weekday peak | B15: =(O19-$K$6-$K$7*$K$8*$K$9)*$L$28-$H$46 -> 25.843669 | C15: =(O19-$K$6-$K$7*$K$8*$K$9)*$L$29-$H$47 -> 22.644978 | D15: =(O19-$K$6-$K$7*$K$8*$K$9)*$L$30-$H$48 -> 21.131806 | E15: =(O19-$K$6-$K$7*$K$8*$K$9)*$L$31-$H$49 -> 27.437278 | F15: =(O19-$K$6-$K$7*$K$8*$K$9+$K$10)*$L$32-$H$50 -> 52.685 | G15: =12*22 -> 264 | J15: Hours_Offpeak_per_Day | K15: 12
A16: September weekday off-peak | B16: =(O20-$K$6-$K$7*$K$8*$K$9)*$L$28-$H$46 -> 1.1270097 | C16: =(O20-$K$6-$K$7*$K$8*$K$9)*$L$29-$H$47 -> -1.4109111 | D16: =(O20-$K$6-$K$7*$K$8*$K$9)*$L$30-$H$48 -> -2.3303472 | E16: =(O20-$K$6-$K$7*$K$8*$K$9)*$L$31-$H$49 -> 2.3471389 | F16: =(O20-$K$6-$K$7*$K$8*$K$9+$K$10)*$L$32-$H$50 -> 35.4475 | G16: =12*22 -> 264
A17: September weekend peak | B17: =(O21-$K$6-$K$7*$K$8*$K$9)*$L$28-$H$46 -> 19.44494 | C17: =(O21-$K$6-$K$7*$K$8*$K$9)*$L$29-$H$47 -> 16.417311 | D17: =(O21-$K$6-$K$7*$K$8*$K$9)*$L$30-$H$48 -> 15.057847 | E17: =(O21-$K$6-$K$7*$K$8*$K$9)*$L$31-$H$49 -> 20.941861 | F17: =(O21-$K$6-$K$7*$K$8*$K$9+$K$10)*$L$32-$H$50 -> 48.2225 | G17: =12*8 -> 96
A18: September weekend off-peak | B18: =(O22-$K$6-$K$7*$K$8*$K$9)*$L$28-$H$46 -> -1.0059 | C18: =(O22-$K$6-$K$7*$K$8*$K$9)*$L$29-$H$47 -> -3.4868 | D18: =(O22-$K$6-$K$7*$K$8*$K$9)*$L$30-$H$48 -> -4.355 | E18: =(O22-$K$6-$K$7*$K$8*$K$9)*$L$31-$H$49 -> 0.182 | F18: =(O22-$K$6-$K$7*$K$8*$K$9+$K$10)*$L$32-$H$50 -> 33.96 | G18: =12*8 -> 96 | J18: Period | K18: Unit | L18: June | M18: July | N18: August | O18: September | P18: October
A19: October weekday peak | B19: =(P19-$K$6-$K$7*$K$8*$K$9)*$L$28-$H$46 -> 39.268454 | C19: =(P19-$K$6-$K$7*$K$8*$K$9)*$L$29-$H$47 -> 35.710867 | D19: =(P19-$K$6-$K$7*$K$8*$K$9)*$L$30-$H$48 -> 33.875208 | E19: =(P19-$K$6-$K$7*$K$8*$K$9)*$L$31-$H$49 -> 41.064917 | F19: =(P19-$K$6-$K$7*$K$8*$K$9+$K$10)*$L$32-$H$50 -> 62.0475 | G19: =21*12 -> 252 | J19: Weekday Peak | K19: £ per MWh | L19: 36 | M19: 36.35 | N19: 37.65 | O19: 38.35 | P19: 43.7
A20: October weekday off-peak | B20: =(P20-$K$6-$K$7*$K$8*$K$9)*$L$28-$H$46 -> 9.1567875 | C20: =(P20-$K$6-$K$7*$K$8*$K$9)*$L$29-$H$47 -> 6.4042 | D20: =(P20-$K$6-$K$7*$K$8*$K$9)*$L$30-$H$48 -> 5.291875 | E20: =(P20-$K$6-$K$7*$K$8*$K$9)*$L$31-$H$49 -> 10.49825 | F20: =(P20-$K$6-$K$7*$K$8*$K$9+$K$10)*$L$32-$H$50 -> 41.0475 | G20: =21*12 -> 252 | J20: Weekday Off-peak | K20: £ per MWh | L20: 27 | M20: 27 | N20: 28.2 | O20: 28.5 | P20: 31.7
A21: October weekend peak | B21: =(P21-$K$6-$K$7*$K$8*$K$9)*$L$28-$H$46 -> 26.721926 | C21: =(P21-$K$6-$K$7*$K$8*$K$9)*$L$29-$H$47 -> 23.499756 | D21: =(P21-$K$6-$K$7*$K$8*$K$9)*$L$30-$H$48 -> 21.965486 | E21: =(P21-$K$6-$K$7*$K$8*$K$9)*$L$31-$H$49 -> 28.328806 | F21: =(P21-$K$6-$K$7*$K$8*$K$9+$K$10)*$L$32-$H$50 -> 53.2975 | G21: =12*10 -> 120 | J21: Weekend Peak | K21: £ per MWh | L21: 33.5 | M21: 34.3 | N21: 35.65 | O21: 35.8 | P21: 38.7
A22: October weekend off-peak | B22: =(P22-$K$6-$K$7*$K$8*$K$9)*$L$28-$H$46 -> 5.1418986 | C22: =(P22-$K$6-$K$7*$K$8*$K$9)*$L$29-$H$47 -> 2.4966444 | D22: =(P22-$K$6-$K$7*$K$8*$K$9)*$L$30-$H$48 -> 1.4807639 | E22: =(P22-$K$6-$K$7*$K$8*$K$9)*$L$31-$H$49 -> 6.4226944 | F22: =(P22-$K$6-$K$7*$K$8*$K$9+$K$10)*$L$32-$H$50 -> 38.2475 | G22: =12*10 -> 120 | J22: Weekend Off-peak | K22: £ per MWh | L22: 26.2 | M22: 26.3 | N22: 27.5 | O22: 27.65 | P22: 30.1
I26: Fuel | J26: Qf (GJ/t) | K26: #VALUE!
I28: Stock | J28: 25.81 | K28: 2.50931 | L28: =J28*0.35/3.6 -> 2.5093056
I29: Col | J29: 25.12 | K29: 2.44222 | L29: =J29*0.35/3.6 -> 2.4422222
I30: Rus | J30: 24.5 | K30: 2.38194 | L30: =J30*0.35/3.6 -> 2.3819444
I31: Sco | J31: 26.2 | K31: 2.54722 | L31: =J31*0.35/3.6 -> 2.5472222
I32: Bio | J32: 18 | K32: 1.75 | L32: =J32*0.35/3.6 -> 1.75
I36: SO2 Rating
I37: Fuel | J37: Sf (%) | K37: t SO₂ / t fuel | L37: FGD2
I38: Stock | J38: 1.38 | K38: 0.0138 | L38: =K38*(1-50%) -> 0.0069
I39: Col | J39: 0.7 | K39: 0.007 | L39: =K39*(1-50%) -> 0.0035
I40: Rus | J40: 0.35 | K40: 0.0035 | L40: =K40*(1-50%) -> 0.00175
I41: Sco | J41: 1.72 | K41: 0.0172 | L41: =K41*(1-50%) -> 0.0086
I42: Bio | J42: 0.01 | K42: 0.0001 | L42: =K42*(1-50%) -> 5e-05
G45: Fuel | H45: Price (£/tonne) | I45: Calorific value (GJ/tonne) | J45: SO2 (%)
G46: Coal: Stockpile | H46: 42.56 | I46: 25.81 | J46: 1.38
G47: Coal: Columbian | H47: 43.93 | I47: 25.12 | J47: 0.7
G48: Coal: Russian | H48: 43.8 | I48: 24.5 | J48: 0.35
G49: Coal: Scottish | H49: 42 | I49: 26.2 | J49: 1.72
G50: Wood chips | H50: 73.77 | I50: 18 | J50: 0.01
G55: Variables | M55: Period | P55: Variables | V55: Period
G56: Amount of fuel burned | H56: Stockpile | I56: Columbian | J56: Russian | K56: Scottish | L56: Wood chips | M56: Hours in each period | P56: Amount of fuel burned | Q56: Stockpile | R56: Columbian | S56: Russian | T56: Scottish | U56: Wood chips | V56: Hours in each period
G57: June- WD-Peak | H57: 94424.38 | I57: 0 | J57: 0 | K57: 0 | L57: 15043.786 | M57: 264 | N57: June | P57: June- WD-Peak | Q57: =H57*$L$28 -> 236939.62 | R57: =I57*$L$29 -> 0 | S57: =J57*$L$30 -> 0 | T57: =K57*$L$31 -> 0 | U57: =L57*$L$32 -> 26326.625 | V57: 264 | W57: June
G58: June-WD-Off-peak | H58: 0 | I58: 0 | J58: 0 | K58: 0 | L58: 0 | M58: 264 | P58: June-WD-Off-peak | Q58: =H58*$L$28 -> 0 | R58: =I58*$L$29 -> 0 | S58: =J58*$L$30 -> 0 | T58: =K58*$L$31 -> 0 | U58: =L58*$L$32 -> 0 | V58: 264
G59: June-WK-Peak | H59: 38151.258 | I59: 0 | J59: 0 | K59: 0 | L59: 0 | M59: 96 | P59: June-WK-Peak | Q59: =H59*$L$28 -> 95733.164 | R59: =I59*$L$29 -> 0 | S59: =J59*$L$30 -> 0 | T59: =K59*$L$31 -> 0 | U59: =L59*$L$32 -> 0 | V59: 96
G60: June-WK-Off-peak | H60: 0 | I60: 0 | J60: 0 | K60: 0 | L60: 0 | M60: 96 | P60: June-WK-Off-peak | Q60: =H60*$L$28 -> 0 | R60: =I60*$L$29 -> 0 | S60: =J60*$L$30 -> 0 | T60: =K60*$L$31 -> 0 | U60: =L60*$L$32 -> 0 | V60: 96
G61: July-WD-Peak | H61: 104925.39 | I61: 0 | J61: 0 | K61: 0 | L61: 0 | M61: 264 | N61: July | P61: July-WD-Peak | Q61: =H61*$L$28 -> 263289.86 | R61: =I61*$L$29 -> 0 | S61: =J61*$L$30 -> 0 | T61: =K61*$L$31 -> 0 | U61: =L61*$L$32 -> 0 | V61: 264 | W61: July
G62: July-WD-Off-peak | H62: 0 | I62: 0 | J62: 0 | K62: 0 | L62: 0 | M62: 264 | P62: July-WD-Off-peak | Q62: =H62*$L$28 -> 0 | R62: =I62*$L$29 -> 0 | S62: =J62*$L$30 -> 0 | T62: =K62*$L$31 -> 0 | U62: =L62*$L$32 -> 0 | V62: 264
G63: July-WK-Peak | H63: 42924.022 | I63: 0 | J63: 0 | K63: 0 | L63: 0 | M63: 108 | P63: July-WK-Peak | Q63: =H63*$L$28 -> 107709.49 | R63: =I63*$L$29 -> 0 | S63: =J63*$L$30 -> 0 | T63: =K63*$L$31 -> 0 | U63: =L63*$L$32 -> 0 | V63: 108
G64: July-WK-Off-peak | H64: 0 | I64: 0 | J64: 0 | K64: 0 | L64: 0 | M64: 108 | P64: July-WK-Off-peak | Q64: =H64*$L$28 -> 0 | R64: =I64*$L$29 -> 0 | S64: =J64*$L$30 -> 0 | T64: =K64*$L$31 -> 0 | U64: =L64*$L$32 -> 0 | V64: 108
G65: Aug-WD-Peak | H65: 104925.39 | I65: 0 | J65: 0 | K65: 0 | L65: 0 | M65: 264 | N65: August | P65: Aug-WD-Peak | Q65: =H65*$L$28 -> 263289.86 | R65: =I65*$L$29 -> 0 | S65: =J65*$L$30 -> 0 | T65: =K65*$L$31 -> 0 | U65: =L65*$L$32 -> 0 | V65: 264 | W65: August
G66: Aug-WD-Off-peak | H66: 104925.39 | I66: 0 | J66: 0 | K66: 0 | L66: 0 | M66: 264 | P66: Aug-WD-Off-peak | Q66: =H66*$L$28 -> 263289.86 | R66: =I66*$L$29 -> 0 | S66: =J66*$L$30 -> 0 | T66: =K66*$L$31 -> 0 | U66: =L66*$L$32 -> 0 | V66: 264
G67: Aug-WK-Peak | H67: 42924.022 | I67: 0 | J67: 0 | K67: 0 | L67: 0 | M67: 108 | P67: Aug-WK-Peak | Q67: =H67*$L$28 -> 107709.49 | R67: =I67*$L$29 -> 0 | S67: =J67*$L$30 -> 0 | T67: =K67*$L$31 -> 0 | U67: =L67*$L$32 -> 0 | V67: 108
G68: Aug-WK-Off-peak | H68: 0 | I68: 0 | J68: 0 | K68: 0 | L68: 0 | M68: 108 | P68: Aug-WK-Off-peak | Q68: =H68*$L$28 -> 0 | R68: =I68*$L$29 -> 0 | S68: =J68*$L$30 -> 0 | T68: =K68*$L$31 -> 0 | U68: =L68*$L$32 -> 0 | V68: 108
G69: Sept-WD-Peak | H69: 0 | I69: 0 | J69: 0 | K69: 103354.51 | L69: 0 | M69: 264 | N69: September | P69: Sept-WD-Peak | Q69: =H69*$L$28 -> 0 | R69: =I69*$L$29 -> 0 | S69: =J69*$L$30 -> 0 | T69: =K69*$L$31 -> 263266.9 | U69: =L69*$L$32 -> 0 | V69: 264 | W69: September
G70: Sept-WD-Off-peak | H70: 0 | I70: 0 | J70: 0 | K70: 103354.51 | L70: 0 | M70: 264 | P70: Sept-WD-Off-peak | Q70: =H70*$L$28 -> 0 | R70: =I70*$L$29 -> 0 | S70: =J70*$L$30 -> 0 | T70: =K70*$L$31 -> 263266.9 | U70: =L70*$L$32 -> 0 | V70: 264
G71: Sept-WK-Peak | H71: 0 | I71: 0 | J71: 0 | K71: 37583.457 | L71: 0 | M71: 96 | P71: Sept-WK-Peak | Q71: =H71*$L$28 -> 0 | R71: =I71*$L$29 -> 0 | S71: =J71*$L$30 -> 0 | T71: =K71*$L$31 -> 95733.417 | U71: =L71*$L$32 -> 0 | V71: 96
G72: Sept-WK-Off-peak | H72: 0 | I72: 0 | J72: 0 | K72: 37583.457 | L72: 0 | M72: 96 | P72: Sept-WK-Off-peak | Q72: =H72*$L$28 -> 0 | R72: =I72*$L$29 -> 0 | S72: =J72*$L$30 -> 0 | T72: =K72*$L$31 -> 95733.417 | U72: =L72*$L$32 -> 0 | V72: 96
G73: Oct-WD-Peak | H73: 0 | I73: 0 | J73: 0 | K73: 98665.439 | L73: 0 | M73: 252 | N73: October | P73: Oct-WD-Peak | Q73: =H73*$L$28 -> 0 | R73: =I73*$L$29 -> 0 | S73: =J73*$L$30 -> 0 | T73: =K73*$L$31 -> 251322.8 | U73: =L73*$L$32 -> 0 | V73: 252 | W73: October
G74: Oct-WD-Off-peak | H74: 0 | I74: 0 | J74: 0 | K74: 98665.439 | L74: 0 | M74: 252 | P74: Oct-WD-Off-peak | Q74: =H74*$L$28 -> 0 | R74: =I74*$L$29 -> 0 | S74: =J74*$L$30 -> 0 | T74: =K74*$L$31 -> 251322.8 | U74: =L74*$L$32 -> 0 | V74: 252
G75: Oct-WK-Peak | H75: 0 | I75: 0 | J75: 0 | K75: 46983.543 | L75: 0 | M75: 120 | P75: Oct-WK-Peak | Q75: =H75*$L$28 -> 0 | R75: =I75*$L$29 -> 0 | S75: =J75*$L$30 -> 0 | T75: =K75*$L$31 -> 119677.52 | U75: =L75*$L$32 -> 0 | V75: 120
G76: Oct-WK-Off-peak | H76: 0 | I76: 0 | J76: 0 | K76: 46983.543 | L76: 0 | M76: 120 | P76: Oct-WK-Off-peak | Q76: =H76*$L$28 -> 0 | R76: =I76*$L$29 -> 0 | S76: =J76*$L$30 -> 0 | T76: =K76*$L$31 -> 119677.52 | U76: =L76*$L$32 -> 0 | V76: 120
G77: Total | H77: 533199.84 | I77: 0 | J77: 0 | K77: 573173.89 | L77: 15043.786 | P77: Total | Q77: =SUM(Q57:Q76) -> 1337961.3 | R77: =SUM(R57:R76) -> 0 | S77: =SUM(S57:S76) -> 0 | T77: =SUM(T57:T76) -> 1460001.3 | U77: =SUM(U57:U76) -> 26326.625 | W77: =SUM(Q77:U77) -> 2824289.2

Sheet Params
A1: Fuel | B1: Price_per_tonne | C1: Calorific value | D1: SO2_percent | E1: Is_Renewable | J1: Scalars | K1: Value
A2: Stockpile coal | B2: 42.56 | C2: 25.81 | D2: 1.38 | E2: FALSE | J2: Efficiency | K2: 0.35
A3: Colombian coal | B3: 43.93 | C3: 25.12 | D3: 0.7 | E3: FALSE | J3: Plant_Capacity_MW | K3: 1000
A4: Russian coal | B4: 43.8 | C4: 24.5 | D4: 0.35 | E4: FALSE | J4: Grid_Charge_per_MWh | K4: 0.65
A5: Scottish coal | B5: 42 | C5: 26.2 | D5: 1.72 | E5: FALSE | J5: CO2_Intensity_t_per_MWh | K5: 0.8
A6: Wood chips | B6: 73.77 | C6: 18 | D6: 0.01 | E6: TRUE | J6: CO2_Cost_EUR_per_t | K6: 15
J7: FX_EUR_per_GBP | K7: 0.87
B8: GJ per tonne_ of_ SO2 | C8: MWh per tonne_of_SO2 | D8: MWH per tonne_fuel | E8: Price per MWh | F8: CO2:price per Mwh | J8: ROC_per_MWh | K8: 45
A9: Stockpile coal | B9: =C2/(D2*0.01) -> 1870.2899 | C9: =B9*0.35/3.6 -> 181.83374 | D9: =C2*0.35/3.6 -> 2.5093056 | E9: =B2/D9 -> 16.960868 | F9: =20*0.8*0.87 -> 13.92 | J9: Sulphur_Allowance_t | K9: 9000
A10: Colombian coal | B10: =C3/(D3*0.01) -> 3588.5714 | C10: =B10*0.35/3.6 -> 348.88889 | D10: =C3*0.35/3.6 -> 2.4422222 | E10: =B3/D10 -> 17.987716 | F10: =20*0.8*0.87 -> 13.92 | J10: Stockpile_Tonnes | K10: 600000
A11: Russian coal | B11: =C4/(D4*0.01) -> 7000 | C11: =B11*0.35/3.6 -> 680.55556 | D11: =C4*0.35/3.6 -> 2.3819444 | E11: =B4/D11 -> 18.388338 | F11: =20*0.8*0.87 -> 13.92 | J11: Biomass_Share_Max | K11: 0.1
A12: Scottish coal | B12: =C5/(D5*0.01) -> 1523.2558 | C12: =B12*0.35/3.6 -> 148.09432 | D12: =C5*0.35/3.6 -> 2.5472222 | E12: =B5/D12 -> 16.48855 | F12: =20*0.8*0.87 -> 13.92 | J12: Hours_Peak_per_Day | K12: 12
A13: Wood chips | B13: =C6/(D6*0.01) -> 180000 | C13: =B13*0.35/3.6 -> 17500 | D13: =C6*0.35/3.6 -> 1.75 | E13: =B6/D13 -> 42.154286 | F13: =20*0.8*0.87 -> 13.92 | J13: Hours_Offpeak_per_Day | K13: 12
J14: P_Colombian_t | K14: 0
J15: P_Russian_t | K15: 0
J16: P_Scottish_t | K16: 0
F18: Profit per MWh | L18: profit per SO2 | S18: profit per tonne
A19: Month | B19: Band | C19: Hours | D19: Price_per_MWh | E19: Key | F19: X_Stockpile_t | G19: X_Colombian_t | H19: X_Russian_t | I19: X_Scottish_t | J19: X_Wood_t | L19: X_Stockpile_t | M19: X_Colombian_t | N19: X_Russian_t | O19: X_Scottish_t | P19: X_Wood_t | S19: X_Stockpile_t | T19: X_Colombian_t | U19: X_Russian_t | V19: X_Scottish_t | W19: X_Wood_t
A20: June | B20: Weekday Peak | C20: 252 | D20: 36 | E20: June|Weekday Peak | F20: =D20-0.65-$E$9-10.44 -> 7.9491321 | G20: =D20-0.65-10.44-$E$10 -> 6.9222839 | H20: =D20-0.65-10.44-$E$11 -> 6.5216618 | I20: =D20-0.65-10.44-$E$12 -> 8.4214504 | J20: =D20+45-0.65-10.44-$E$13 -> 27.755714 | L20: =$C$9*F20 -> 1445.4204 | M20: =$C$10*G20 -> 2415.1079 | N20: =$C$11*H20 -> 4438.3532 | O20: =$C$12*I20 -> 1247.1689 | P20: =$C$13*J20 -> 485725 | S20: =($C$2*0.35/3.6*(D20-0.65-0.8*0.87*15)-$B$2) -> 19.946801 | T20: =($C$3*0.35/3.6*(D20-0.65-0.8*0.87*15)-$B$3) -> 16.905756 | U20: =($C$4*0.35/3.6*(D20-0.65-0.8*0.87*15)-$B$4) -> 15.534236 | V20: =($C$5*0.35/3.6*(D20-0.65-0.8*0.87*15)-$B$5) -> 21.451306 | W20: =($C$6*0.35/3.6*(D20+45-0.65-0.8*0.87*15)-$B$6) -> 48.5725
A21: June | B21: Weekday Off-peak | C21: 252 | D21: 27 | E21: June|Weekday Off-peak | F21: =D21-0.65-$E$9-10.44 -> -1.0508679 | G21: =D21-0.65-10.44-$E$10 -> -2.0777161 | H21: =D21-0.65-10.44-$E$11 -> -2.4783382 | I21: =D21-0.65-10.44-$E$12 -> -0.57854962 | J21: =D21+45-0.65-10.44-$E$13 -> 18.755714 | L21: =$C$9*F21 -> -191.08323 | M21: =$C$10*G21 -> -724.89206 | N21: =$C$11*H21 -> -1686.6468 | O21: =$C$12*I21 -> -85.67991 | P21: =$C$13*J21 -> 328225 | S21: =($C$2*0.35/3.6*(D21-0.65-0.8*0.87*15)-$B$2) -> -2.6369486 | T21: =($C$3*0.35/3.6*(D21-0.65-0.8*0.87*15)-$B$3) -> -5.0742444 | U21: =($C$4*0.35/3.6*(D21-0.65-0.8*0.87*15)-$B$4) -> -5.9032639 | V21: =($C$5*0.35/3.6*(D21-0.65-0.8*0.87*15)-$B$5) -> -1.4736944 | W21: =($C$6*0.35/3.6*(D21+45-0.65-0.8*0.87*15)-$B$6) -> 32.8225
A22: June | B22: Weekend Peak | C22: 108 | D22: 33.5 | E22: June|Weekend Peak | F22: =D22-0.65-$E$9-10.44 -> 5.4491321 | G22: =D22-0.65-10.44-$E$10 -> 4.4222839 | H22: =D22-0.65-10.44-$E$11 -> 4.0216618 | I22: =D22-0.65-10.44-$E$12 -> 5.9214504 | J22: =D22+45-0.65-10.44-$E$13 -> 25.255714 | L22: =$C$9*F22 -> 990.83605 | M22: =$C$10*G22 -> 1542.8857 | N22: =$C$11*H22 -> 2736.9643 | O22: =$C$12*I22 -> 876.93314 | P22: =$C$13*J22 -> 441975 | S22: =($C$2*0.35/3.6*(D22-0.65-0.8*0.87*15)-$B$2) -> 13.673537 | T22: =($C$3*0.35/3.6*(D22-0.65-0.8*0.87*15)-$B$3) -> 10.8002 | U22: =($C$4*0.35/3.6*(D22-0.65-0.8*0.87*15)-$B$4) -> 9.579375 | V22: =($C$5*0.35/3.6*(D22-0.65-0.8*0.87*15)-$B$5) -> 15.08325 | W22: =($C$6*0.35/3.6*(D22+45-0.65-0.8*0.87*15)-$B$6) -> 44.1975
A23: June | B23: Weekend Off-peak | C23: 108 | D23: 26.2 | E23: June|Weekend Off-peak | F23: =D23-0.65-$E$9-10.44 -> -1.8508679 | G23: =D23-0.65-10.44-$E$10 -> -2.8777161 | H23: =D23-0.65-10.44-$E$11 -> -3.2783382 | I23: =D23-0.65-10.44-$E$12 -> -1.3785496 | J23: =D23+45-0.65-10.44-$E$13 -> 17.955714 | L23: =$C$9*F23 -> -336.55022 | M23: =$C$10*G23 -> -1004.0032 | N23: =$C$11*H23 -> -2231.0913 | O23: =$C$12*I23 -> -204.15536 | P23: =$C$13*J23 -> 314225 | S23: =($C$2*0.35/3.6*(D23-0.65-0.8*0.87*15)-$B$2) -> -4.6443931 | T23: =($C$3*0.35/3.6*(D23-0.65-0.8*0.87*15)-$B$3) -> -7.0280222 | U23: =($C$4*0.35/3.6*(D23-0.65-0.8*0.87*15)-$B$4) -> -7.8088194 | V23: =($C$5*0.35/3.6*(D23-0.65-0.8*0.87*15)-$B$5) -> -3.5114722 | W23: =($C$6*0.35/3.6*(D23+45-0.65-0.8*0.87*15)-$B$6) -> 31.4225
A24: July | B24: Weekday Peak | C24: 276 | D24: 36.35 | E24: July|Weekday Peak | F24: =D24-0.65-$E$9-10.44 -> 8.2991321 | G24: =D24-0.65-10.44-$E$10 -> 7.2722839 | H24: =D24-0.65-10.44-$E$11 -> 6.8716618 | I24: =D24-0.65-10.44-$E$12 -> 8.7714504 | J24: =D24+45-0.65-10.44-$E$13 -> 28.105714 | L24: =$C$9*F24 -> 1509.0622 | M24: =$C$10*G24 -> 2537.219 | N24: =$C$11*H24 -> 4676.5476 | O24: =$C$12*I24 -> 1299.0019 | P24: =$C$13*J24 -> 491850 | S24: =($C$2*0.35/3.6*(D24-0.65-0.8*0.87*15)-$B$2) -> 20.825058 | T24: =($C$3*0.35/3.6*(D24-0.65-0.8*0.87*15)-$B$3) -> 17.760533 | U24: =($C$4*0.35/3.6*(D24-0.65-0.8*0.87*15)-$B$4) -> 16.367917 | V24: =($C$5*0.35/3.6*(D24-0.65-0.8*0.87*15)-$B$5) -> 22.342833 | W24: =($C$6*0.35/3.6*(D24+45-0.65-0.8*0.87*15)-$B$6) -> 49.185
A25: July | B25: Weekday Off-peak | C25: 276 | D25: 27 | E25: July|Weekday Off-peak | F25: =D25-0.65-$E$9-10.44 -> -1.0508679 | G25: =D25-0.65-10.44-$E$10 -> -2.0777161 | H25: =D25-0.65-10.44-$E$11 -> -2.4783382 | I25: =D25-0.65-10.44-$E$12 -> -0.57854962 | J25: =D25+45-0.65-10.44-$E$13 -> 18.755714 | L25: =$C$9*F25 -> -191.08323 | M25: =$C$10*G25 -> -724.89206 | N25: =$C$11*H25 -> -1686.6468 | O25: =$C$12*I25 -> -85.67991 | P25: =$C$13*J25 -> 328225 | S25: =($C$2*0.35/3.6*(D25-0.65-0.8*0.87*15)-$B$2) -> -2.6369486 | T25: =($C$3*0.35/3.6*(D25-0.65-0.8*0.87*15)-$B$3) -> -5.0742444 | U25: =($C$4*0.35/3.6*(D25-0.65-0.8*0.87*15)-$B$4) -> -5.9032639 | V25: =($C$5*0.35/3.6*(D25-0.65-0.8*0.87*15)-$B$5) -> -1.4736944 | W25: =($C$6*0.35/3.6*(D25+45-0.65-0.8*0.87*15)-$B$6) -> 32.8225
A26: July | B26: Weekend Peak | C26: 96 | D26: 34.3 | E26: July|Weekend Peak | F26: =D26-0.65-$E$9-10.44 -> 6.2491321 | G26: =D26-0.65-10.44-$E$10 -> 5.2222839 | H26: =D26-0.65-10.44-$E$11 -> 4.8216618 | I26: =D26-0.65-10.44-$E$12 -> 6.7214504 | J26: =D26+45-0.65-10.44-$E$13 -> 26.055714 | L26: =$C$9*F26 -> 1136.303 | M26: =$C$10*G26 -> 1821.9968 | N26: =$C$11*H26 -> 3281.4087 | O26: =$C$12*I26 -> 995.40859 | P26: =$C$13*J26 -> 455975 | S26: =($C$2*0.35/3.6*(D26-0.65-0.8*0.87*15)-$B$2) -> 15.680982 | T26: =($C$3*0.35/3.6*(D26-0.65-0.8*0.87*15)-$B$3) -> 12.753978 | U26: =($C$4*0.35/3.6*(D26-0.65-0.8*0.87*15)-$B$4) -> 11.484931 | V26: =($C$5*0.35/3.6*(D26-0.65-0.8*0.87*15)-$B$5) -> 17.121028 | W26: =($C$6*0.35/3.6*(D26+45-0.65-0.8*0.87*15)-$B$6) -> 45.5975
A27: July | B27: Weekend Off-peak | C27: 96 | D27: 26.3 | E27: July|Weekend Off-peak | F27: =D27-0.65-$E$9-10.44 -> -1.7508679 | G27: =D27-0.65-10.44-$E$10 -> -2.7777161 | H27: =D27-0.65-10.44-$E$11 -> -3.1783382 | I27: =D27-0.65-10.44-$E$12 -> -1.2785496 | J27: =D27+45-0.65-10.44-$E$13 -> 18.055714 | L27: =$C$9*F27 -> -318.36685 | M27: =$C$10*G27 -> -969.11429 | N27: =$C$11*H27 -> -2163.0357 | O27: =$C$12*I27 -> -189.34593 | P27: =$C$13*J27 -> 315975 | S27: =($C$2*0.35/3.6*(D27-0.65-0.8*0.87*15)-$B$2) -> -4.3934625 | T27: =($C$3*0.35/3.6*(D27-0.65-0.8*0.87*15)-$B$3) -> -6.7838 | U27: =($C$4*0.35/3.6*(D27-0.65-0.8*0.87*15)-$B$4) -> -7.570625 | V27: =($C$5*0.35/3.6*(D27-0.65-0.8*0.87*15)-$B$5) -> -3.25675 | W27: =($C$6*0.35/3.6*(D27+45-0.65-0.8*0.87*15)-$B$6) -> 31.5975
A28: August | B28: Weekday Peak | C28: 252 | D28: 37.65 | E28: August|Weekday Peak | F28: =D28-0.65-$E$9-10.44 -> 9.5991321 | G28: =D28-0.65-10.44-$E$10 -> 8.5722839 | H28: =D28-0.65-10.44-$E$11 -> 8.1716618 | I28: =D28-0.65-10.44-$E$12 -> 10.07145 | J28: =D28+45-0.65-10.44-$E$13 -> 29.405714 | L28: =$C$9*F28 -> 1745.4461 | M28: =$C$10*G28 -> 2990.7746 | N28: =$C$11*H28 -> 5561.2698 | O28: =$C$12*I28 -> 1491.5245 | P28: =$C$13*J28 -> 514600 | S28: =($C$2*0.35/3.6*(D28-0.65-0.8*0.87*15)-$B$2) -> 24.087156 | T28: =($C$3*0.35/3.6*(D28-0.65-0.8*0.87*15)-$B$3) -> 20.935422 | U28: =($C$4*0.35/3.6*(D28-0.65-0.8*0.87*15)-$B$4) -> 19.464444 | V28: =($C$5*0.35/3.6*(D28-0.65-0.8*0.87*15)-$B$5) -> 25.654222 | W28: =($C$6*0.35/3.6*(D28+45-0.65-0.8*0.87*15)-$B$6) -> 51.46
A29: August | B29: Weekday Off-peak | C29: 252 | D29: 28.2 | E29: August|Weekday Off-peak | F29: =D29-0.65-$E$9-10.44 -> 0.14913212 | G29: =D29-0.65-10.44-$E$10 -> -0.87771611 | H29: =D29-0.65-10.44-$E$11 -> -1.2783382 | I29: =D29-0.65-10.44-$E$12 -> 0.62145038 | J29: =D29+45-0.65-10.44-$E$13 -> 19.955714 | L29: =$C$9*F29 -> 27.11725 | M29: =$C$10*G29 -> -306.2254 | N29: =$C$11*H29 -> -869.98016 | O29: =$C$12*I29 -> 92.033269 | P29: =$C$13*J29 -> 349225 | S29: =($C$2*0.35/3.6*(D29-0.65-0.8*0.87*15)-$B$2) -> 0.37421806 | T29: =($C$3*0.35/3.6*(D29-0.65-0.8*0.87*15)-$B$3) -> -2.1435778 | U29: =($C$4*0.35/3.6*(D29-0.65-0.8*0.87*15)-$B$4) -> -3.0449306 | V29: =($C$5*0.35/3.6*(D29-0.65-0.8*0.87*15)-$B$5) -> 1.5829722 | W29: =($C$6*0.35/3.6*(D29+45-0.65-0.8*0.87*15)-$B$6) -> 34.9225
A30: August | B30: Weekend Peak | C30: 120 | D30: 35.65 | E30: August|Weekend Peak | F30: =D30-0.65-$E$9-10.44 -> 7.5991321 | G30: =D30-0.65-10.44-$E$10 -> 6.5722839 | H30: =D30-0.65-10.44-$E$11 -> 6.1716618 | I30: =D30-0.65-10.44-$E$12 -> 8.0714504 | J30: =D30+45-0.65-10.44-$E$13 -> 27.405714 | L30: =$C$9*F30 -> 1381.7786 | M30: =$C$10*G30 -> 2292.9968 | N30: =$C$11*H30 -> 4200.1587 | O30: =$C$12*I30 -> 1195.3359 | P30: =$C$13*J30 -> 479600 | S30: =($C$2*0.35/3.6*(D30-0.65-0.8*0.87*15)-$B$2) -> 19.068544 | T30: =($C$3*0.35/3.6*(D30-0.65-0.8*0.87*15)-$B$3) -> 16.050978 | U30: =($C$4*0.35/3.6*(D30-0.65-0.8*0.87*15)-$B$4) -> 14.700556 | V30: =($C$5*0.35/3.6*(D30-0.65-0.8*0.87*15)-$B$5) -> 20.559778 | W30: =($C$6*0.35/3.6*(D30+45-0.65-0.8*0.87*15)-$B$6) -> 47.96
A31: August | B31: Weekend Off-peak | C31: 120 | D31: 27.5 | E31: August|Weekend Off-peak | F31: =D31-0.65-$E$9-10.44 -> -0.55086788 | G31: =D31-0.65-10.44-$E$10 -> -1.5777161 | H31: =D31-0.65-10.44-$E$11 -> -1.9783382 | I31: =D31-0.65-10.44-$E$12 -> -0.078549618 | J31: =D31+45-0.65-10.44-$E$13 -> 19.255714 | L31: =$C$9*F31 -> -100.16636 | M31: =$C$10*G31 -> -550.44762 | N31: =$C$11*H31 -> -1346.369 | O31: =$C$12*I31 -> -11.632752 | P31: =$C$13*J31 -> 336975 | S31: =($C$2*0.35/3.6*(D31-0.65-0.8*0.87*15)-$B$2) -> -1.3822958 | T31: =($C$3*0.35/3.6*(D31-0.65-0.8*0.87*15)-$B$3) -> -3.8531333 | U31: =($C$4*0.35/3.6*(D31-0.65-0.8*0.87*15)-$B$4) -> -4.7122917 | V31: =($C$5*0.35/3.6*(D31-0.65-0.8*0.87*15)-$B$5) -> -0.20008333 | W31: =($C$6*0.35/3.6*(D31+45-0.65-0.8*0.87*15)-$B$6) -> 33.6975
... A39: October | B39: Weekend Off-peak | C39: 96 | D39: 30.1 | E39: October|Weekend Off-peak | F39: =D39-0.65-$E$9-10.44 -> 2.0491321 | G39: =D39-0.65-10.44-$E$10 -> 1.0222839 | H39: =D39-0.65-10.44-$E$11 -> 0.62166181 | I39: =D39-0.65-10.44-$E$12 -> 2.5214504 | J39: =D39+45-0.65-10.44-$E$13 -> 21.855714 | L39: =$C$9*F39 -> 372.60135 | M39: =$C$10*G39 -> 356.66349 | N39: =$C$11*H39 -> 423.0754 | O39: =$C$12*I39 -> 373.41247 | P39: =$C$13*J39 -> 382475 | S39: =($C$2*0.35/3.6*(D39-0.65-0.8*0.87*15)-$B$2) -> 5.1418986 | T39: =($C$3*0.35/3.6*(D39-0.65-0.8*0.87*15)-$B$3) -> 2.4966444 | U39: =($C$4*0.35/3.6*(D39-0.65-0.8*0.87*15)-$B$4) -> 1.4807639 | V39: =($C$5*0.35/3.6*(D39-0.65-0.8*0.87*15)-$B$5) -> 6.4226944 | W39: =($C$6*0.35/3.6*(D39+45-0.65-0.8*0.87*15)-$B$6) -> 38.2475

Sheet Prices
A1: Month | B1: Band | C1: Hours | D1: Price_per_MWh | E1: Key
A2: June | B2: Weekday Peak | C2: 252 | D2: 36 | E2: June|Weekday Peak
A3: June | B3: Weekday Off-peak | C3: 252 | D3: 27 | E3: June|Weekday Off-peak
A4: June | B4: Weekend Peak | C4: 108 | D4: 33.5 | E4: June|Weekend Peak
A5: June | B5: Weekend Off-peak | C5: 108 | D5: 26.2 | E5: June|Weekend Off-peak
A6: July | B6: Weekday Peak | C6: 276 | D6: 36.35 | E6: July|Weekday Peak
A7: July | B7: Weekday Off-peak | C7: 276 | D7: 27 | E7: July|Weekday Off-peak
A8: July | B8: Weekend Peak | C8: 96 | D8: 34.3 | E8: July|Weekend Peak
A9: July | B9: Weekend Off-peak | C9: 96 | D9: 26.3 | E9: July|Weekend Off-peak
A10: August | B10: Weekday Peak | C10: 252 | D10: 37.65 | E10: August|Weekday Peak
A11: August | B11: Weekday Off-peak | C11: 252 | D11: 28.2 | E11: August|Weekday Off-peak
A12: August | B12: Weekend Peak | C12: 120 | D12: 35.65 | E12: August|Weekend Peak
A13: August | B13: Weekend Off-peak | C13: 120 | D13: 27.5 | E13: August|Weekend Off-peak
... A21: October | B21: Weekend Off-peak | C21: 96 | D21: 30.1 | E21: October|Weekend Off-peak

Sheet Calendar
A1: Month | B1: Weekday Peak | C1: Weekday Off-peak | D1: Weekend Peak | E1: Weekend Off-peak | F1: WE_Peak_Hours | G1: WE_Offpeak_Hours | H1: Total Hour
A2: June | B2: 252 | C2: 252 | D2: 108 | E2: 108 | F2: =IF(C2="","",C2*Params!$K$11) -> 25.2 | G2: =IF(C2="","",C2*Params!$K$12) -> 3024 | H2: =SUM(B2:E2) -> 720
A3: July | B3: 276 | C3: 276 | D3: 96 | E3: 96 | F3: =IF(C3="","",C3*Params!$K$11) -> 27.6 | G3: =IF(C3="","",C3*Params!$K$12) -> 3312 | H3: =SUM(B3:E3) -> 744
A4: August | B4: 252 | C4: 252 | D4: 120 | E4: 120 | F4: =IF(C4="","",C4*Params!$K$11) -> 25.2 | G4: =IF(C4="","",C4*Params!$K$12) -> 3024 | H4: =SUM(B4:E4) -> 744
A5: September | B5: 264 | C5: 264 | D5: 96 | E5: 96 | F5: =IF(C5="","",C5*Params!$K$11) -> 26.4 | G5: =IF(C5="","",C5*Params!$K$12) -> 3168 | H5: =SUM(B5:E5) -> 720
A6: October | B6: 276 | C6: 276 | D6: 96 | E6: 96 | F6: =IF(C6="","",C6*Params!$K$11) -> 27.6 | G6: =IF(C6="","",C6*Params!$K$12) -> 3312 | H6: =SUM(B6:E6) -> 744
A9: Month | B9: Weekdays | C9: WeekendDays | D9: WD_Peak_Hours | E9: WD_Offpeak_Hours | F9: WE_Peak_Hours | G9: WE_Offpeak_Hours
A10: June | B10: 21 | C10: 9 | D10: 252 | E10: 252 | F10: 108 | G10: 108
A11: July | B11: 23 | C11: 8 | D11: 276 | E11: 276 | F11: 96 | G11: 96
A12: August | B12: 21 | C12: 10 | D12: 252 | E12: 252 | F12: 120 | G12: 120
A13: September | B13: 22 | C13: 8 | D13: 264 | E13: 264 | F13: 96 | G13: 96
A14: October | B14: 23 | C14: 8 | D14: 276 | E14: 276 | F14: 96 | G14: 96

Sheet Decisions
A1: Decisions (enter Y_MWh and X_*_t) | D1: Fuel | E1: Stockpile coal | F1: Colombian coal | G1: Russian coal | H1: Scottish coal | I1: Wood chips
D2: Price_per_t | E2: 42.56 | F2: 43.93 | G2: 43.8 | H2: 42 | I2: 73.77 | K2: =H19*H3/G3 -> 32122.992
D3: CV_GJ_per_t | E3: 25.81 | F3: 25.12 | G3: 24.5 | H3: 26.2 | I3: 18
D4: SO2_percent | E4: 1.38 | F4: 0.7 | G4: 0.35 | H4: 1.72 | I4: 0.01
A6: Month | B6: Hours | C6: Y_MWh | D6: FGD | E6: X_Stockpile_t | F6: X_Colombian_t | G6: X_Russian_t | H6: X_Scottish_t | I6: X_Wood_t | J6: Thermal_Input_GJ | K6: Total_MWh | L6: Renewable_MWh | M6: Price_per_MWh | N6: Revenue | O6: ROC_Revenue | P6: Grid_Charge | Q6: Fuel_Cost | R6: CO2_Cost | S6: Profit | T6: Wood_Thermal_GJ | U6: SO2_tonnes | V6: Biomass_share | W6: Thermal_Input_GJ*0.1 | X6: Coal fule
A7: June - Weekday Peak | B7: 264 | C7: =(SUMPRODUCT(E7:I7, E$3:I$3)*0.35)/3.6 -> 264000 | D7: 10000000 | E7: 94687.552 | F7: 0 | G7: 0 | H7: 0 | I7: 15085.714 | J7: =SUMPRODUCT(E7:I7, E$3:I$3) -> 2715428.6 | K7: =(SUMPRODUCT(E7:I7, E$3:I$3)*0.35)/3.6 -> 264000 | L7: =($I$3*I7*0.35)/3.6 -> 26400 | M7: 36 | N7: =M7*C7 -> 9504000 | O7: =45*($I$3*I7*0.35)/3.6 -> 1188000 | P7: =SUMPRODUCT(E7:I7, E$3:I$3)*0.35*0.65/3.6 -> 171600 | Q7: =SUMPRODUCT(E7:I7, E$2:I$2) -> 5142775.4 | R7: =C7*0.8*0.87*15 -> 2756160 | S7: =IFERROR(N7+O7-P7-Q7-R7,0) -> 2621464.6 | T7: =I7*$I$3 -> 271542.86 | U7: =SUMPRODUCT(E7:I7, E$4:I$4)*0.01 -> 1308.1968 | V7: =IFERROR(T7/J7,0) -> 0.1 | W7: =0.1*J7 -> 271542.86 | X7: =SUMPRODUCT($E$3:$H$3,E7:H7) -> 2443885.7
A8: June - Weekday Off-peak | B8: 264 | C8: =(SUMPRODUCT(E8:I8, E$3:I$3)*0.35)/3.6 -> 0 | D8: 0 | E8: 0 | F8: 0 | G8: 0 | H8: 0 | I8: 0 | J8: =SUMPRODUCT(E8:I8, E$3:I$3) -> 0 | K8: =(SUMPRODUCT(E8:I8, E$3:I$3)*0.35)/3.6 -> 0 | L8: =($I$3*I8*0.35)/3.6 -> 0 | M8: 27 | N8: =M8*C8 -> 0 | O8: =45*($I$3*I8*0.35)/3.6 -> 0 | P8: =SUMPRODUCT(E8:I8, E$3:I$3)*0.35*0.65/3.6 -> 0 | Q8: =SUMPRODUCT(E8:I8, E$2:I$2) -> 0 | R8: =C8*0.8*0.87*15 -> 0 | S8: =IFERROR(N8+O8-P8-Q8-R8,0) -> 0 | T8: =I8*$I$3 -> 0 | U8: =SUMPRODUCT(E8:I8, E$4:I$4)*0.01 -> 0 | V8: =IFERROR(T8/J8,0) -> 0 | W8: =0.1*J8 -> 0 | X8: =SUMPRODUCT($E$3:$H$3,E8:H8) -> 0
A9: June - Weekend Peak | B9: 96 | C9: =(SUMPRODUCT(E9:I9, E$3:I$3)*0.35)/3.6 -> 96000 | D9: 0 | E9: 34431.837 | F9: 0 | G9: 0 | H9: 0 | I9: 5485.7143 | J9: =SUMPRODUCT(E9:I9, E$3:I$3) -> 987428.57 | K9: =(SUMPRODUCT(E9:I9, E$3:I$3)*0.35)/3.6 -> 96000 | L9: =($I$3*I9*0.35)/3.6 -> 9600 | M9: 33.5 | N9: =M9*C9 -> 3216000 | O9: =45*($I$3*I9*0.35)/3.6 -> 432000 | P9: =SUMPRODUCT(E9:I9, E$3:I$3)*0.35*0.65/3.6 -> 62400 | Q9: =SUMPRODUCT(E9:I9, E$2:I$2) -> 1870100.1 | R9: =C9*0.8*0.87*15 -> 1002240 | S9: =IFERROR(N9+O9-P9-Q9-R9,0) -> 713259.87 | T9: =I9*$I$3 -> 98742.857 | U9: =SUMPRODUCT(E9:I9, E$4:I$4)*0.01 -> 475.70792 | V9: =IFERROR(T9/J9,0) -> 0.1 | W9: =0.1*J9 -> 98742.857 | X9: =SUMPRODUCT($E$3:$H$3,E9:H9) -> 888685.71
A10: June - Weekend Off-peak | B10: 96 | C10: =(SUMPRODUCT(E10:I10, E$3:I$3)*0.35)/3.6 -> 0 | D10: 0 | E10: 0 | F10: 0 | G10: 0 | H10: 0 | I10: 0 | J10: =SUMPRODUCT(E10:I10, E$3:I$3) -> 0 | K10: =(SUMPRODUCT(E10:I10, E$3:I$3)*0.35)/3.6 -> 0 | L10: =($I$3*I10*0.35)/3.6 -> 0 | M10: 26.2 | N10: =M10*C10 -> 0 | O10: =45*($I$3*I10*0.35)/3.6 -> 0 | P10: =SUMPRODUCT(E10:I10, E$3:I$3)*0.35*0.65/3.6 -> 0 | Q10: =SUMPRODUCT(E10:I10, E$2:I$2) -> 0 | R10: =C10*0.8*0.87*15 -> 0 | S10: =IFERROR(N10+O10-P10-Q10-R10,0) -> 0 | T10: =I10*$I$3 -> 0 | U10: =SUMPRODUCT(E10:I10, E$4:I$4)*0.01 -> 0 | V10: =IFERROR(T10/J10,0) -> 0 | W10: =0.1*J10 -> 0 | X10: =SUMPRODUCT($E$3:$H$3,E10:H10) -> 0
A11: July - Weekday Peak | B11: 264 | C11: =(SUMPRODUCT(E11:I11, E$3:I$3)*0.35)/3.6 -> 264000 | D11: 0 | E11: 94687.552 | F11: 0 | G11: 0 | H11: 0 | I11: 15085.714 | J11: =SUMPRODUCT(E11:I11, E$3:I$3) -> 2715428.6 | K11: =(SUMPRODUCT(E11:I11, E$3:I$3)*0.35)/3.6 -> 264000 | L11: =($I$3*I11*0.35)/3.6 -> 26400 | M11: 36.35 | N11: =M11*C11 -> 9596400 | O11: =45*($I$3*I11*0.35)/3.6 -> 1188000 | P11: =SUMPRODUCT(E11:I11, E$3:I$3)*0.35*0.65/3.6 -> 171600 | Q11: =SUMPRODUCT(E11:I11, E$2:I$2) -> 5142775.4 | R11: =C11*0.8*0.87*15 -> 2756160 | S11: =IFERROR(N11+O11-P11-Q11-R11,0) -> 2713864.6 | T11: =I11*$I$3 -> 271542.86 | U11: =SUMPRODUCT(E11:I11, E$4:I$4)*0.01 -> 1308.1968 | V11: =IFERROR(T11/J11,0) -> 0.1 | W11: =0.1*J11 -> 271542.86 | X11: =SUMPRODUCT($E$3:$H$3,E11:H11) -> 2443885.7
A12: July - Weekday Off-peak | B12: 264 | C12: =(SUMPRODUCT(E12:I12, E$3:I$3)*0.35)/3.6 -> 0 | D12: 0 | E12: 0 | F12: 0 | G12: 0 | H12: 0 | I12: 0 | J12: =SUMPRODUCT(E12:I12, E$3:I$3) -> 0 | K12: =(SUMPRODUCT(E12:I12, E$3:I$3)*0.35)/3.6 -> 0 | L12: =($I$3*I12*0.35)/3.6 -> 0 | M12: 27 | N12: =M12*C12 -> 0 | O12: =45*($I$3*I12*0.35)/3.6 -> 0 | P12: =SUMPRODUCT(E12:I12, E$3:I$3)*0.35*0.65/3.6 -> 0 | Q12: =SUMPRODUCT(E12:I12, E$2:I$2) -> 0 | R12: =C12*0.8*0.87*15 -> 0 | S12: =IFERROR(N12+O12-P12-Q12-R12,0) -> 0 | T12: =I12*$I$3 -> 0 | U12: =SUMPRODUCT(E12:I12, E$4:I$4)*0.01 -> 0 | V12: =IFERROR(T12/J12,0) -> 0 | W12: =0.1*J12 -> 0 | X12: =SUMPRODUCT($E$3:$H$3,E12:H12) -> 0
A13: July - Weekend Peak | B13: 108 | C13: =(SUMPRODUCT(E13:I13, E$3:I$3)*0.35)/3.6 -> 108000 | D13: 0 | E13: 38735.817 | F13: 0 | G13: 0 | H13: 0 | I13: 6171.4286 | J13: =SUMPRODUCT(E13:I13, E$3:I$3) -> 1110857.1 | K13: =(SUMPRODUCT(E13:I13, E$3:I$3)*0.35)/3.6 -> 108000 | L13: =($I$3*I13*0.35)/3.6 -> 10800 | M13: 34.3 | N13: =M13*C13 -> 3704400 | O13: =45*($I$3*I13*0.35)/3.6 -> 486000 | P13: =SUMPRODUCT(E13:I13, E$3:I$3)*0.35*0.65/3.6 -> 70200 | Q13: =SUMPRODUCT(E13:I13, E$2:I$2) -> 2103862.6 | R13: =C13*0.8*0.87*15 -> 1127520 | S13: =IFERROR(N13+O13-P13-Q13-R13,0) -> 888817.36 | T13: =I13*$I$3 -> 111085.71 | U13: =SUMPRODUCT(E13:I13, E$4:I$4)*0.01 -> 535.17141 | V13: =IFERROR(T13/J13,0) -> 0.1 | W13: =0.1*J13 -> 111085.71 | X13: =SUMPRODUCT($E$3:$H$3,E13:H13) -> 999771.43
A14: July - Weekend Off-peak | B14: 108 | C14: =(SUMPRODUCT(E14:I14, E$3:I$3)*0.35)/3.6 -> 0 | D14: 0 | E14: 0 | F14: 0 | G14: 0 | H14: 0 | I14: 0 | J14: =SUMPRODUCT(E14:I14, E$3:I$3) -> 0 | K14: =(SUMPRODUCT(E14:I14, E$3:I$3)*0.35)/3.6 -> 0 | L14: =($I$3*I14*0.35)/3.6 -> 0 | M14: 26.3 | N14: =M14*C14 -> 0 | O14: =45*($I$3*I14*0.35)/3.6 -> 0 | P14: =SUMPRODUCT(E14:I14, E$3:I$3)*0.35*0.65/3.6 -> 0 | Q14: =SUMPRODUCT(E14:I14, E$2:I$2) -> 0 | R14: =C14*0.8*0.87*15 -> 0 | S14: =IFERROR(N14+O14-P14-Q14-R14,0) -> 0 | T14: =I14*$I$3 -> 0 | U14: =SUMPRODUCT(E14:I14, E$4:I$4)*0.01 -> 0 | V14: =IFERROR(T14/J14,0) -> 0 | W14: =0.1*J14 -> 0 | X14: =SUMPRODUCT($E$3:$H$3,E14:H14) -> 0
A15: August - Weekday Peak | B15: 264 | C15: =(SUMPRODUCT(E15:I15, E$3:I$3)*0.35)/3.6 -> 264000 | D15: 0 | E15: 94687.552 | F15: 0 | G15: 0 | H15: 0 | I15: 15085.714 | J15: =SUMPRODUCT(E15:I15, E$3:I$3) -> 2715428.6 | K15: =(SUMPRODUCT(E15:I15, E$3:I$3)*0.35)/3.6 -> 264000 | L15: =($I$3*I15*0.35)/3.6 -> 26400 | M15: 37.65 | N15: =M15*C15 -> 9939600 | O15: =45*($I$3*I15*0.35)/3.6 -> 1188000 | P15: =SUMPRODUCT(E15:I15, E$3:I$3)*0.35*0.65/3.6 -> 171600 | Q15: =SUMPRODUCT(E15:I15, E$2:I$2) -> 5142775.4 | R15: =C15*0.8*0.87*15 -> 2756160 | S15: =IFERROR(N15+O15-P15-Q15-R15,0) -> 3057064.6 | T15: =I15*$I$3 -> 271542.86 | U15: =SUMPRODUCT(E15:I15, E$4:I$4)*0.01 -> 1308.1968 | V15: =IFERROR(T15/J15,0) -> 0.1 | W15: =0.1*J15 -> 271542.86 | X15: =SUMPRODUCT($E$3:$H$3,E15:H15) -> 2443885.7
A16: August - Weekday Off-peak | B16: 264 | C16: =(SUMPRODUCT(E16:I16, E$3:I$3)*0.35)/3.6 -> 264000 | D16: 0 | E16: 94687.552 | F16: 0 | G16: 0 | H16: 0 | I16: 15085.714 | J16: =SUMPRODUCT(E16:I16, E$3:I$3) -> 2715428.6 | K16: =(SUMPRODUCT(E16:I16, E$3:I$3)*0.35)/3.6 -> 264000 | L16: =($I$3*I16*0.35)/3.6 -> 26400 | M16: 28.2 | N16: =M16*C16 -> 7444800 | O16: =45*($I$3*I16*0.35)/3.6 -> 1188000 | P16: =SUMPRODUCT(E16:I16, E$3:I$3)*0.35*0.65/3.6 -> 171600 | Q16: =SUMPRODUCT(E16:I16, E$2:I$2) -> 5142775.4 | R16: =C16*0.8*0.87*15 -> 2756160 | S16: =IFERROR(N16+O16-P16-Q16-R16,0) -> 562264.65 | T16: =I16*$I$3 -> 271542.86 | U16: =SUMPRODUCT(E16:I16, E$4:I$4)*0.01 -> 1308.1968 | V16: =IFERROR(T16/J16,0) -> 0.1 | W16: =0.1*J16 -> 271542.86 | X16: =SUMPRODUCT($E$3:$H$3,E16:H16) -> 2443885.7
A17: August - Weekend Peak | B17: 108 | C17: =(SUMPRODUCT(E17:I17, E$3:I$3)*0.35)/3.6 -> 108000 | D17: 0 | E17: 38735.817 | F17: 0 | G17: 0 | H17: 0 | I17: 6171.4286 | J17: =SUMPRODUCT(E17:I17, E$3:I$3) -> 1110857.1 | K17: =(SUMPRODUCT(E17:I17, E$3:I$3)*0.35)/3.6 -> 108000 | L17: =($I$3*I17*0.35)/3.6 -> 10800 | M17: 35.65 | N17: =M17*C17 -> 3850200 | O17: =45*($I$3*I17*0.35)/3.6 -> 486000 | P17: =SUMPRODUCT(E17:I17, E$3:I$3)*0.35*0.65/3.6 -> 70200 | Q17: =SUMPRODUCT(E17:I17, E$2:I$2) -> 2103862.6 | R17: =C17*0.8*0.87*15 -> 1127520 | S17: =IFERROR(N17+O17-P17-Q17-R17,0) -> 1034617.4 | T17: =I17*$I$3 -> 111085.71 | U17: =SUMPRODUCT(E17:I17, E$4:I$4)*0.01 -> 535.17141 | V17: =IFERROR(T17/J17,0) -> 0.1 | W17: =0.1*J17 -> 111085.71 | X17: =SUMPRODUCT($E$3:$H$3,E17:H17) -> 999771.43
A18: August - Weekend Off-peak | B18: 108 | C18: =(SUMPRODUCT(E18:I18, E$3:I$3)*0.35)/3.6 -> 0 | D18: 0 | E18: 0 | F18: 0 | G18: 0 | H18: 0 | I18: 0 | J18: =SUMPRODUCT(E18:I18, E$3:I$3) -> 0 | K18: =(SUMPRODUCT(E18:I18, E$3:I$3)*0.35)/3.6 -> 0 | L18: =($I$3*I18*0.35)/3.6 -> 0 | M18: 27.5 | N18: =M18*C18 -> 0 | O18: =45*($I$3*I18*0.35)/3.6 -> 0 | P18: =SUMPRODUCT(E18:I18, E$3:I$3)*0.35*0.65/3.6 -> 0 | Q18: =SUMPRODUCT(E18:I18, E$2:I$2) -> 0 | R18: =C18*0.8*0.87*15 -> 0 | S18: =IFERROR(N18+O18-P18-Q18-R18,0) -> 0 | T18: =I18*$I$3 -> 0 | U18: =SUMPRODUCT(E18:I18, E$4:I$4)*0.01 -> 0 | V18: =IFERROR(T18/J18,0) -> 0 | W18: =0.1*J18 -> 0 | X18: =SUMPRODUCT($E$3:$H$3,E18:H18) -> 0
... A26: October - Weekend Off-peak | B26: 120 | C26: =(SUMPRODUCT(E26:I26, E$3:I$3)*0.35)/3.6 -> 120000 | D26: 0 | E26: 0 | F26: 0 | G26: 45341.108 | H26: 0 | I26: 6857.1429 | J26: =SUMPRODUCT(E26:I26, E$3:I$3) -> 1234285.7 | K26: =(SUMPRODUCT(E26:I26, E$3:I$3)*0.35)/3.6 -> 120000 | L26: =($I$3*I26*0.35)/3.6 -> 12000 | M26: 30.1 | N26: =M26*C26 -> 3612000 | O26: =45*($I$3*I26*0.35)/3.6 -> 540000 | P26: =SUMPRODUCT(E26:I26, E$3:I$3)*0.35*0.65/3.6 -> 78000 | Q26: =SUMPRODUCT(E26:I26, E$2:I$2) -> 2491792 | R26: =C26*0.8*0.87*15 -> 1252800 | S26: =IFERROR(N26+O26-P26-Q26-R26,0) -> 329408.05 | T26: =I26*$I$3 -> 123428.57 | U26: =SUMPRODUCT(E26:I26, E$4:I$4)*0.01 -> 159.37959 | V26: =IFERROR(T26/J26,0) -> 0.1 | W26: =0.1*J26 -> 123428.57 | X26: =SUMPRODUCT($E$3:$H$3,E26:H26) -> 1110857.1
A27: Total | C27: =SUM(C7:C26) -> 2736000 | E27: =SUM(E7:E26) -> 490653.68 | F27: =SUM(F7:F26) -> 0 | G27: =SUM(G7:G26) -> 484765.64 | H27: =SUM(H7:H26) -> 30038.676 | I27: =SUM(I7:I26) -> 156342.86 | K27: =SUM(K7:K26) -> 2736000 | N27: =SUM(N7:O26) -> 107909400 | P27: =SUM(P7:P26) -> 1778400 | Q27: =SUM(Q7:Q26) -> 54909992 | R27: =SUM(R7:R26) -> 28563840 | T27: =SUM(T7:T26) -> 2814171.4 | W27: =SUM(W7:W26) -> 2814171.4 | X27: =SUMPRODUCT($E$3:$H$3,E27:H27) -> 25327543
A28: Total_Profit | B28: =SUM(S7:S26) -> 22657168 | C28: Max | L28: profit per So2 tonne
A29: Total_SO2_tonnes | B29: =SUM(U7:U26) -> 9000 | C29: <= | D29: =9000 -> 9000 | F29: X_Stockpile_t | G29: X_Colombian_t | H29: X_Russian_t | I29: X_Scottish_t | J29: X_Wood_t | L29: X_Stockpile_t | M29: X_Colombian_t | N29: X_Russian_t | O29: X_Scottish_t | P29: X_Wood_t | Q29: price
A30: Total_burn3 | B30: =SUM(F7:H18) -> 0 | C30: = | D30: 0 | E30: June - Weekday Peak | F30: =E7*($E$3*0.35/3.6*(M7-0.65-0.8*0.87*15)-$E$2) -> 1888713.8 | G30: =F7*($E$3*0.35/3.6*(N7-0.65-0.8*0.87*30)-$E$2) -> 0 | H30: =G7*($G$3*0.35/3.6*(M7-0.65-0.8*0.87*15)-$G$2) -> 0 | I30: =H7*($H$3*0.35/3.6*(M7-0.65-0.8*0.87*15)-$H$2) -> 0 | J30: =I7*($I$3*(0.35/3.6)*(M7+45-0.65-0.8*0.87*15)-$I$2) -> 732750.86 | K30: =SUM(F30:J30) -> 2621464.6 | L30: 1445.4204 | M30: 2415.1079 | N30: 4438.3532 | O30: 1247.1689 | P30: 485725 | Q30: 36
A31: Total_stockpile | B31: =SUM(E7:E26) -> 490653.68 | C31: <= | D31: 600000 | E31: June - Weekday Off-peak | F31: =E8*($E$3*0.35/3.6*(M8-0.65-0.8*0.87*15)-$E$2) -> 0 | G31: =F8*($E$3*0.35/3.6*(N8-0.65-0.8*0.87*30)-$E$2) -> 0 | H31: =G8*($G$3*0.35/3.6*(M8-0.65-0.8*0.87*15)-$G$2) -> 0 | I31: =H8*($H$3*0.35/3.6*(M8-0.65-0.8*0.87*15)-$H$2) -> 0 | J31: =I8*($I$3*(0.35/3.6)*(M8+45-0.65-0.8*0.87*15)-$I$2) -> 0 | K31: =SUM(F31:J31) -> 0 | L31: -191.08323 | M31: -724.89206 | N31: -1686.6468 | O31: -85.67991 | P31: 328225 | Q31: 27
A32: Capacity_constraint | B32: =C7 -> 264000 | C32: <= | D32: =B7*1000 -> 264000 | E32: June - Weekend Peak | F32: =E9*($E$3*0.35/3.6*(M9-0.65-0.8*0.87*15)-$E$2) -> 470805.02 | G32: =F9*($E$3*0.35/3.6*(N9-0.65-0.8*0.87*30)-$E$2) -> 0 | H32: =G9*($G$3*0.35/3.6*(M9-0.65-0.8*0.87*15)-$G$2) -> 0 | I32: =H9*($H$3*0.35/3.6*(M9-0.65-0.8*0.87*15)-$H$2) -> 0 | J32: =I9*($I$3*(0.35/3.6)*(M9+45-0.65-0.8*0.87*15)-$I$2) -> 242454.86 | K32: =SUM(F32:J32) -> 713259.87 | L32: 990.83605 | M32: 1542.8857 | N32: 2736.9643 | O32: 876.93314 | P32: 441975 | Q32: 33.5 | S32: GJ/tonne_ of_ SO2 | T32: MWh/tonne_of_SO2 | U32: MWH/tonne | V32: Price/MWh | W32: CO2:price/Mwh | X32: SO2/MWh
B33: =C8 -> 0 | C33: <= | D33: =B8*1000 -> 264000 | E33: June - Weekend Off-peak | F33: =E10*($E$3*0.35/3.6*(M10-0.65-0.8*0.87*15)-$E$2) -> 0 | G33: =F10*($E$3*0.35/3.6*(N10-0.65-0.8*0.87*30)-$E$2) -> 0 | H33: =G10*($G$3*0.35/3.6*(M10-0.65-0.8*0.87*15)-$G$2) -> 0 | I33: =H10*($H$3*0.35/3.6*(M10-0.65-0.8*0.87*15)-$H$2) -> 0 | J33: =I10*($I$3*(0.35/3.6)*(M10+45-0.65-0.8*0.87*15)-$I$2) -> 0 | K33: =SUM(F33:J33) -> 0 | L33: -336.55022 | M33: -1004.0032 | N33: -2231.0913 | O33: -204.15536 | P33: 314225 | Q33: 26.2 | R33: Stockpile coal | S33: 1870.2899 | T33: 181.83374 | U33: 2.5093056 | V33: 16.960868 | W33: 10.44 | X33: =1/T33 -> 0.0054995295
B34: =C9 -> 96000 | C34: <= | D34: =B9*1000 -> 96000 | E34: July - Weekday Peak | F34: =E11*($E$3*0.35/3.6*(M11-0.65-0.8*0.87*15)-$E$2) -> 1971873.8 | G34: =F11*($E$3*0.35/3.6*(N11-0.65-0.8*0.87*30)-$E$2) -> 0 | H34: =G11*($G$3*0.35/3.6*(M11-0.65-0.8*0.87*15)-$G$2) -> 0 | I34: =H11*($H$3*0.35/3.6*(M11-0.65-0.8*0.87*15)-$H$2) -> 0 | J34: =I11*($I$3*(0.35/3.6)*(M11+45-0.65-0.8*0.87*15)-$I$2) -> 741990.86 | K34: =SUM(F34:J34) -> 2713864.6 | L34: 1509.0622 | M34: 2537.219 | N34: 4676.5476 | O34: 1299.0019 | P34: 491850 | Q34: 36.35 | R34: Colombian coal | S34: 3588.5714 | T34: 348.88889 | U34: 2.4422222 | V34: 17.987716 | W34: 10.44 | X34: =1/T34 -> 0.002866242
B35: =C10 -> 0 | C35: <= | D35: =B10*1000 -> 96000 | E35: July - Weekday Off-peak | F35: =E12*($E$3*0.35/3.6*(M12-0.65-0.8*0.87*15)-$E$2) -> 0 | G35: =F12*($E$3*0.35/3.6*(N12-0.65-0.8*0.87*30)-$E$2) -> 0 | H35: =G12*($G$3*0.35/3.6*(M12-0.65-0.8*0.87*15)-$G$2) -> 0 | I35: =H12*($H$3*0.35/3.6*(M12-0.65-0.8*0.87*15)-$H$2) -> 0 | J35: =I12*($I$3*(0.35/3.6)*(M12+45-0.65-0.8*0.87*15)-$I$2) -> 0 | K35: =SUM(F35:J35) -> 0 | L35: -191.08323 | M35: -724.89206 | N35: -1686.6468 | O35: -85.67991 | P35: 328225 | Q35: 27 | R35: Russian coal | S35: 7000 | T35: 680.55556 | U35: 2.3819444 | V35: 18.388338 | W35: 10.44 | X35: =1/T35 -> 0.0014693878
B36: =C11 -> 264000 | C36: <= | D36: =B11*1000 -> 264000 | E36: July - Weekend Peak | F36: =E13*($E$3*0.35/3.6*(M13-0.65-0.8*0.87*15)-$E$2) -> 607415.64 | G36: =F13*($E$3*0.35/3.6*(N13-0.65-0.8*0.87*30)-$E$2) -> 0 | H36: =G13*($G$3*0.35/3.6*(M13-0.65-0.8*0.87*15)-$G$2) -> 0 | I36: =H13*($H$3*0.35/3.6*(M13-0.65-0.8*0.87*15)-$H$2) -> 0 | J36: =I13*($I$3*(0.35/3.6)*(M13+45-0.65-0.8*0.87*15)-$I$2) -> 281401.71 | K36: =SUM(F36:J36) -> 888817.36 | L36: 1136.303 | M36: 1821.9968 | N36: 3281.4087 | O36: 995.40859 | P36: 455975 | Q36: 34.3 | R36: Scottish coal | S36: 1523.2558 | T36: 148.09432 | U36: 2.5472222 | V36: 16.48855 | W36: 10.44 | X36: =1/T36 -> 0.0067524537
B37: =C12 -> 0 | C37: <= | D37: =B12*1000 -> 264000 | E37: July - Weekend Off-peak | F37: =E14*($E$3*0.35/3.6*(M14-0.65-0.8*0.87*15)-$E$2) -> 0 | G37: =F14*($E$3*0.35/3.6*(N14-0.65-0.8*0.87*30)-$E$2) -> 0 | H37: =G14*($G$3*0.35/3.6*(M14-0.65-0.8*0.87*15)-$G$2) -> 0 | I37: =H14*($H$3*0.35/3.6*(M14-0.65-0.8*0.87*15)-$H$2) -> 0 | J37: =I14*($I$3*(0.35/3.6)*(M14+45-0.65-0.8*0.87*15)-$I$2) -> 0 | K37: =SUM(F37:J37) -> 0 | L37: -318.36685 | M37: -969.11429 | N37: -2163.0357 | O37: -189.34593 | P37: 315975 | Q37: 26.3 | R37: Wood chips | S37: 180000 | T37: 17500 | U37: 1.75 | V37: 42.154286 | W37: 10.44 | X37: =1/T37 -> 5.7142857e-05
B38: =C13 -> 108000 | C38: <= | D38: =B13*1000 -> 108000 | E38: August - Weekday Peak | F38: =E15*($E$3*0.35/3.6*(M15-0.65-0.8*0.87*15)-$E$2) -> 2280753.8 | G38: =F15*($E$3*0.35/3.6*(N15-0.65-0.8*0.87*30)-$E$2) -> 0 | H38: =G15*($G$3*0.35/3.6*(M15-0.65-0.8*0.87*15)-$G$2) -> 0 | I38: =H15*($H$3*0.35/3.6*(M15-0.65-0.8*0.87*15)-$H$2) -> 0 | J38: =I15*($I$3*(0.35/3.6)*(M15+45-0.65-0.8*0.87*15)-$I$2) -> 776310.86 | K38: =SUM(F38:J38) -> 3057064.6 | L38: 1745.4461 | M38: 2990.7746 | N38: 5561.2698 | O38: 1491.5245 | P38: 514600 | Q38: 37.65
B39: =C14 -> 0 | C39: <= | D39: =B14*1000 -> 108000 | E39: August - Weekday Off-peak | F39: =E16*($E$3*0.35/3.6*(M16-0.65-0.8*0.87*15)-$E$2) -> 35433.792 | G39: =F16*($E$3*0.35/3.6*(N16-0.65-0.8*0.87*30)-$E$2) -> 0 | H39: =G16*($G$3*0.35/3.6*(M16-0.65-0.8*0.87*15)-$G$2) -> 0 | I39: =H16*($H$3*0.35/3.6*(M16-0.65-0.8*0.87*15)-$H$2) -> 0 | J39: =I16*($I$3*(0.35/3.6)*(M16+45-0.65-0.8*0.87*15)-$I$2) -> 526830.86 | K39: =SUM(F39:J39) -> 562264.65 | L39: 27.11725 | M39: -306.2254 | N39: -869.98016 | O39: 92.033269 | P39: 349225 | Q39: 28.2
B40: =C15 -> 264000 | C40: <= | D40: =B15*1000 -> 264000 | E40: August - Weekend Peak | F40: =E17*($E$3*0.35/3.6*(M17-0.65-0.8*0.87*15)-$E$2) -> 738635.64 | G40: =F17*($E$3*0.35/3.6*(N17-0.65-0.8*0.87*30)-$E$2) -> 0 | H40: =G17*($G$3*0.35/3.6*(M17-0.65-0.8*0.87*15)-$G$2) -> 0 | I40: =H17*($H$3*0.35/3.6*(M17-0.65-0.8*0.87*15)-$H$2) -> 0 | J40: =I17*($I$3*(0.35/3.6)*(M17+45-0.65-0.8*0.87*15)-$I$2) -> 295981.71 | K40: =SUM(F40:J40) -> 1034617.4 | L40: 1381.7786 | M40: 2292.9968 | N40: 4200.1587 | O40: 1195.3359 | P40: 479600 | Q40: 35.65
B41: =C16 -> 264000 | C41: <= | D41: =B16*1000 -> 264000 | E41: August - Weekend Off-peak | F41: =E18*($E$3*0.35/3.6*(M18-0.65-0.8*0.87*15)-$E$2) -> 0 | G41: =F18*($E$3*0.35/3.6*(N18-0.65-0.8*0.87*30)-$E$2) -> 0 | H41: =G18*($G$3*0.35/3.6*(M18-0.65-0.8*0.87*15)-$G$2) -> 0 | I41: =H18*($H$3*0.35/3.6*(M18-0.65-0.8*0.87*15)-$H$2) -> 0 | J41: =I18*($I$3*(0.35/3.6)*(M18+45-0.65-0.8*0.87*15)-$I$2) -> 0 | K41: =SUM(F41:J41) -> 0 | L41: -100.16636 | M41: -550.44762 | N41: -1346.369 | O41: -11.632752 | P41: 336975 | Q41: 27.5
B42: =C17 -> 108000 | C42: <= | D42: =B17*1000 -> 108000 | E42: September - Weekday Peak | F42: =E19*($E$3*0.35/3.6*(M19-0.65-0.8*0.87*15)-$E$2) -> 0 | G42: =F19*($E$3*0.35/3.6*(N19-0.65-0.8*0.87*30)-$E$2) -> 0 | H42: =G19*($G$3*0.35/3.6*(M19-0.65-0.8*0.87*15)-$G$2) -> 1429090 | I42: =H19*($H$3*0.35/3.6*(M19-0.65-0.8*0.87*15)-$H$2) -> 824179.5 | J42: =I19*($I$3*(0.35/3.6)*(M19+45-0.65-0.8*0.87*15)-$I$2) -> 794790.86 | K42: =SUM(F42:J42) -> 3048060.4 | L42: 1872.7297 | M42: 3234.9968 | N42: 6037.6587 | O42: 1595.1906 | P42: 526850 | Q42: 38.35 | T42: 22657168 | U42: 14850785 | V42: 3131566.3 | W42: 15485447 | X42: 15363585 | Y42: 15241723 | Z42: 2976258.2 | AA42: 2924488.9 | AB42: 2872719.5 | AC42: 16852966 | AD42: 16934368 | AE42: 17015771 | AF42: 12193211 | AG42: 12223029 | AH42: 12252847
B43: =C18 -> 0 | C43: <= | D43: =B18*1000 -> 108000 | E43: September - Weekday Off-peak | F43: =E20*($E$3*0.35/3.6*(M20-0.65-0.8*0.87*15)-$E$2) -> 0 | G43: =F20*($E$3*0.35/3.6*(N20-0.65-0.8*0.87*30)-$E$2) -> 0 | H43: =G20*($G$3*0.35/3.6*(M20-0.65-0.8*0.87*15)-$G$2) -> -232453.15 | I43: =H20*($H$3*0.35/3.6*(M20-0.65-0.8*0.87*15)-$H$2) -> 0 | J43: =I20*($I$3*(0.35/3.6)*(M20+45-0.65-0.8*0.87*15)-$I$2) -> 534750.86 | K43: =SUM(F43:J43) -> 302297.7 | L43: 81.667371 | M43: -201.55873 | N43: -665.81349 | O43: 136.46156 | P43: 354475 | Q43: 28.5 | U43: =U42/T42 -> 0.65545639 | V43: =V42/$T$42 -> 0.13821526 | W43: =W42/$T$42 -> 0.6834679 | X43: =X42/$T$42 -> 0.67808939 | Y43: =Y42/$T$42 -> 0.67271088 | Z43: =Z42/$T$42 -> 0.13136056 | AA43: =AA42/$T$42 -> 0.12907566 | AB43: =AB42/$T$42 -> 0.12679076 | AC43: =AC42/$T$42 -> 0.74382492 | ... AH43: =AH42/$T$42 -> 0.54079339
B44: =C19 -> 264000 | C44: <= | D44: =B19*1000 -> 264000 | E44: September - Weekend Peak | F44: =E21*($E$3*0.35/3.6*(M21-0.65-0.8*0.87*15)-$E$2) -> 0 | G44: =F21*($E$3*0.35/3.6*(N21-0.65-0.8*0.87*30)-$E$2) -> 0 | H44: =G21*($G$3*0.35/3.6*(M21-0.65-0.8*0.87*15)-$G$2) -> 546191.58 | I44: =H21*($H$3*0.35/3.6*(M21-0.65-0.8*0.87*15)-$H$2) -> 0 | J44: =I21*($I$3*(0.35/3.6)*(M21+45-0.65-0.8*0.87*15)-$I$2) -> 264534.86 | K44: =SUM(F44:J44) -> 810726.44 | L44: 1409.0536 | M44: 2345.3302 | N44: 4302.2421 | O44: 1217.5501 | P44: 482225 | Q44: 35.8
B45: =C20 -> 264000 | C45: <= | D45: =B20*1000 -> 264000 | E45: September - Weekend Off-peak | F45: =E22*($E$3*0.35/3.6*(M22-0.65-0.8*0.87*15)-$E$2) -> 0 | G45: =F22*($E$3*0.35/3.6*(N22-0.65-0.8*0.87*30)-$E$2) -> 0 | H45: =G22*($G$3*0.35/3.6*(M22-0.65-0.8*0.87*15)-$G$2) -> 0 | I45: =H22*($H$3*0.35/3.6*(M22-0.65-0.8*0.87*15)-$H$2) -> 0 | J45: =I22*($I$3*(0.35/3.6)*(M22+45-0.65-0.8*0.87*15)-$I$2) -> 0 | K45: =SUM(F45:J45) -> 0 | L45: -72.891304 | M45: -498.11429 | N45: -1244.2857 | O45: 10.581395 | P45: 339600 | Q45: 27.65
B46: =C21 -> 96000 | C46: <= | D46: =B21*1000 -> 96000 | E46: October - Weekday Peak | F46: =E23*($E$3*0.35/3.6*(M23-0.65-0.8*0.87*15)-$E$2) -> 0 | G46: =F23*($E$3*0.35/3.6*(N23-0.65-0.8*0.87*30)-$E$2) -> 0 | H46: =G23*($G$3*0.35/3.6*(M23-0.65-0.8*0.87*15)-$G$2) -> 3225472.9 | I46: =H23*($H$3*0.35/3.6*(M23-0.65-0.8*0.87*15)-$H$2) -> 0 | J46: =I23*($I$3*(0.35/3.6)*(M23+45-0.65-0.8*0.87*15)-$I$2) -> 893484 | K46: =SUM(F46:J46) -> 4118956.9 | L46: 2845.5402 | M46: 5101.5524 | N46: 9678.631 | O46: 2387.4952 | P46: 620475 | Q46: 43.7 | T46: =T42*109.81% -> 24879836 | U46: =T42*109.07% -> 24712173 | V46: =108.32%*T42 -> 24542244
B47: =C22 -> 0 | C47: <= | D47: =B22*1000 -> 96000 | E47: October - Weekday Off-peak | F47: =E24*($E$3*0.35/3.6*(M24-0.65-0.8*0.87*15)-$E$2) -> 0 | G47: =F24*($E$3*0.35/3.6*(N24-0.65-0.8*0.87*30)-$E$2) -> 0 | H47: =G24*($G$3*0.35/3.6*(M24-0.65-0.8*0.87*15)-$G$2) -> 503872.9 | I47: =H24*($H$3*0.35/3.6*(M24-0.65-0.8*0.87*15)-$H$2) -> 0 | J47: =I24*($I$3*(0.35/3.6)*(M24+45-0.65-0.8*0.87*15)-$I$2) -> 591084 | K47: =SUM(F47:J47) -> 1094956.9 | L47: 663.53533 | M47: 914.88571 | N47: 1511.9643 | O47: 610.36337 | P47: 410475 | Q47: 31.7 | T47: 24864910 | U47: 24692960 | V47: 24521010
B48: =C23 -> 252000 | C48: <= | D48: =B23*1000 -> 252000 | E48: October - Weekend Peak | F48: =E25*($E$3*0.35/3.6*(M25-0.65-0.8*0.87*15)-$E$2) -> 0 | G48: =F25*($E$3*0.35/3.6*(N25-0.65-0.8*0.87*30)-$E$2) -> 0 | H48: =G25*($G$3*0.35/3.6*(M25-0.65-0.8*0.87*15)-$G$2) -> 995939.48 | I48: =H25*($H$3*0.35/3.6*(M25-0.65-0.8*0.87*15)-$H$2) -> 0 | J48: =I25*($I$3*(0.35/3.6)*(M25+45-0.65-0.8*0.87*15)-$I$2) -> 365468.57 | K48: =SUM(F48:J48) -> 1361408 | L48: 1936.3715 | M48: 3357.1079 | N48: 6275.8532 | O48: 1647.0236 | P48: 532975 | Q48: 38.7 | T48: =T47/T42 -> 1.0974412 | U48: =U47/T42 -> 1.089852 | V48: =V47/T42 -> 1.0822628
B49: =C24 -> 252000 | C49: <= | D49: =B24*1000 -> 252000 | E49: October - Weekend Off-peak | F49: =E26*($E$3*0.35/3.6*(M26-0.65-0.8*0.87*15)-$E$2) -> 0 | G49: =F26*($E$3*0.35/3.6*(N26-0.65-0.8*0.87*30)-$E$2) -> 0 | H49: =G26*($G$3*0.35/3.6*(M26-0.65-0.8*0.87*15)-$G$2) -> 67139.475 | I49: =H26*($H$3*0.35/3.6*(M26-0.65-0.8*0.87*15)-$H$2) -> 0 | J49: =I26*($I$3*(0.35/3.6)*(M26+45-0.65-0.8*0.87*15)-$I$2) -> 262268.57 | K49: =SUM(F49:J49) -> 329408.05 | L49: 372.60135 | M49: 356.66349 | N49: 423.0754 | O49: 373.41247 | P49: 382475 | Q49: 30.1
B50: =C25 -> 120000 | C50: <= | D50: =B25*1000 -> 120000 | F50: =SUM(F30:F49) -> 7993631.5 | G50: =F27*($F$3*M27*0.35/3.6-0.65*F$3*0.35/3.6-$F$2-0.8*0.87*15) -> 0 | H50: =SUM(H30:H49) -> 6535253.2 | I50: =SUM(I30:I49) -> 824179.5 | J50: =SUM(J30:J49) -> 7304103.4 | K50: =SUM(F50:J50) -> 22657168
B51: =C26 -> 120000 | C51: <= | D51: =B26*1000 -> 120000
A52: Biomix_CV | B52: =0.9*T7 - 0.1*X7 -> 0 | C52: <= | D52: 0 | F52: =F50 -> 7993631.5 | G52: =G50 -> 0 | H52: =H50 -> 6535253.2 | I52: =I50 -> 824179.5 | J52: =J50 -> 7304103.4 | K52: =SUM(F52:J52) -> 22657168
B53: =0.9*T8 - 0.1*X8 -> 0 | C53: <= | D53: 0 | E53: MWh | F53: =E27*E3*0.35/3.6 -> 1231200 | G53: =F27*F3*0.35/3.6 -> 0 | H53: =G27*G3*0.35/3.6 -> 1154684.8 | I53: =H27*H3*0.35/3.6 -> 76515.183 | J53: =I27*I3*0.35/3.6 -> 273600 | K53: =SUM(F53:J53) -> 2736000
B54: =0.9*T9 - 0.1*X9 -> 0 | C54: <= | D54: 0 | E54: CO2 cost | F54: =F53*0.8*0.87*15 -> 12853728 | G54: =G53*0.8*0.87*15 -> 0 | H54: =H53*0.8*0.87*15 -> 12054909 | I54: =I53*0.8*0.87*15 -> 798818.51 | J54: =J53*0.8*0.87*15 -> 2856384 | K54: =SUM(F54:J54) -> 28563840
B55: =0.9*T10 - 0.1*X10 -> 0 | C55: <= | D55: 0 | E55: Revenue | F55: =F52+F54+F56+F57 -> 42529860 | G55: =G52+G54+G56+G57 -> 0 | H55: =H52+H54+H56+H57 -> 40573443 | I55: =I52+I54+I56+I57 -> 2934357.3 | J55: =J52+J54+J56+J57 -> 21871740 | K55: =SUM(F55:J55) -> 1.079094e+08 | L55: 33713477
B56: =0.9*T11 - 0.1*X11 -> 0 | C56: <= | D56: 0 | E56: Transmission cost | F56: =0.65*F53 -> 800280 | G56: =0.65*G53 -> 0 | H56: =0.65*H53 -> 750545.13 | I56: =0.65*I53 -> 49734.869 | J56: =0.65*J53 -> 177840 | K56: =SUM(F56:J56) -> 1778400 | L56: =SUM(K57+K56+K54) -> 85252232 | M56: 30374834 | N56: 27.5
B57: =0.9*T12 - 0.1*X12 -> 0 | C57: <= | D57: 0 | E57: Fuel Cosst | F57: =E27*E2 -> 20882221 | G57: =F27*F2 -> 0 | H57: =G27*G2 -> 21232735 | I57: =H27*H2 -> 1261624.4 | J57: =I27*I2 -> 11533413 | K57: =SUM(F57:J57) -> 54909992
B58: =0.9*T13 - 0.1*X13 -> 0 | C58: <= | D58: 0 | E58: SO2 | F58: =E27*E4*0.01 -> 6771.0208 | G58: =F27*F4*0.01 -> 0 | H58: =G27*G4*0.01 -> 1696.6797 | I58: =H27*H4*0.01 -> 516.66523 | J58: =I27*I4*0.01 -> 15.634286 | K58: =SUM(F58:J58) -> 9000
B59: =0.9*T14 - 0.1*X14 -> 0 | C59: <= | D59: 0 | E59: SO2 cost | F59: =F58*40 -> 270840.83 | G59: =G58*40 -> 0 | H59: =H58*40 -> 67867.189 | I59: =I58*40 -> 20666.609 | J59: =J58*40 -> 625.37143
B60: =0.9*T15 - 0.1*X15 -> 0 | C60: <= | D60: 0
B61: =0.9*T16 - 0.1*X16 -> 0 | C61: <= | D61: 0
B62: =0.9*T17 - 0.1*X17 -> 0 | C62: <= | D62: 0
B63: =0.9*T18 - 0.1*X18 -> 0 | C63: <= | D63: 0
B64: =0.9*T19 - 0.1*X19 -> 0 | C64: <= | D64: 0 | F64: MWh | G64: CO2 cost | H64: Revenue | I64: Transmission cost | J64: Fuel Cosst | K64: SO2
B65: =0.9*T20 - 0.1*X20 -> 0 | C65: <= | D65: 0 | E65: Stockpile coal | F65: 1231200 | G65: 12853728 | H65: 42529860 | I65: 800280 | J65: 20882221 | K65: 6771.0208
B66: =0.9*T21 - 0.1*X21 -> 0 | C66: <= | D66: 0 | E66: Colombian coal | F66: 0 | G66: 0 | H66: 0 | I66: 0 | J66: 0 | K66: 0
B67: =0.9*T22 - 0.1*X22 -> 0 | C67: <= | D67: 0 | E67: Russian coal | F67: 1154684.8 | G67: 12054909 | H67: 40573443 | I67: 750545.13 | J67: 21232735 | K67: 1696.6797
B68: =0.9*T23 - 0.1*X23 -> 0 | C68: <= | D68: 0 | E68: Scottish coal | F68: 76515.183 | G68: 798818.51 | H68: 2934357.3 | I68: 49734.869 | J68: 1261624.4 | K68: 516.66523
B69: =0.9*T24 - 0.1*X24 -> 0 | C69: <= | D69: 0 | E69: Wood chips | F69: 273600 | G69: 2856384 | H69: 21871740 | I69: 177840 | J69: 11533413 | K69: 15.634286
B70: =0.9*T25 - 0.1*X25 -> 0 | C70: <= | D70: 0 | E70: Total | F70: 2736000 | G70: 28563840 | H70: 107909400 | I70: 1778400 | J70: 54909992 | K70: 9000
B71: =0.9*T26 - 0.1*X26 -> 0 | C71: <= | D71: 0 | I71: =SUM(I70+J70+G70) -> 85252232
A72: FGD | B72: =SUM(D7:D26) -> 10000000 | C72: >= | D72: 10000000 | I72: 85252232
F74: MWh | G74: CO2 cost | H74: Revenue | I74: Transmission cost | J74: Fuel Cosst | K74: SO2
E75: Stockpile coal | F75: 1505583.3 | G75: 15718290 | H75: 49986810 | I75: 978629.17 | J75: 25536000 | K75: 8280
E76: Colombian coal | F76: 0 | G76: 0 | H76: 0 | I76: 0 | J76: 0 | K76: 0
E77: Russian coal | F77: 0 | G77: 0 | H77: 0 | I77: 0 | J77: 0 | K77: 0
E78: Scottish coal | F78: 1317600 | G78: 13755744 | H78: 45896760 | I78: 856440 | J78: 21725313 | K78: 8897.0329
E79: Wood chips | F79: 313687.04 | G79: 3274892.7 | H79: 24769647 | I79: 203896.57 | J79: 13223253 | K79: 17.924974
E80: Total | F80: 3136870.4 | G80: 32748927 | H80: 1.2065322e+08 | I80: 2038965.7 | J80: 60484566 | K80: 17194.958
I81: =SUM(I80+J80+G80+K80*50) -> 96132206
I82: =H80-I81 -> 24521010
I83: 96132206
E87: 24864910
E88: 24521010
